Workbook

Sheet summary
H1: 12月31日（实际 | J1: 1月2日（实际 | L1: 1月5日（实际 | N1: 1月6日（实际 | P1: 1月7日（实际 | T1: 1月8日（实际 | V1: 1月9日（实际 | X1: 1月12日（实际 | Z1: 1月13日（实际 | AB1: 1月14日（实际 | AF1: 1月15日（实际 | AH1: 1月16日（实际 | AJ1: 1月19日（实际 | AL1: 1月20日（实际 | AN1: 1月21日（实际 | AR1: 1月22日（实际 | AY1: 2026年02月24日 | BA1: 2026年02月26日 | BC1: 2026年02月26日 | BG1: 2025年08月01日 | BI1: 2025年12月05日 | BK1: 2026年02月24日 | BM1: 2025年09月12日 | BO1: 2025年06月23日 | BQ1: 2025年06月23日 | BS1: 2025年07月14日 | BU1: 2026年02月26日 | BW1: 2026年02月26日
B2: 參與者編號 | C2: 中央結算系統參與者名稱 | D2: 1月2日持股量 | E2: 1月3日持股量 | F2: 1月3日VS1月2日 | G2: 1月5日持股量 | H2: 1月5日VS1月3日 | I2: 1月6日持股量 | J2: 1月6日VS1月5日 | K2: 1月7日持股量 | L2: 1月7日VS1月6日 | M2: 1月8日持股量 | N2: 1月8日VS1月7日 | O2: 1月9日持股量 | P2: 1月9日VS1月8日 | Q2: 1月10日持股量 | R2: 1月10日VS1月9日 | S2: 1月12日持股量 | T2: 1月12日VS1月10日 | U2: 1月13日持股量 | V2: 1月13日VS1月12日 | W2: 1月14日持股量 | X2: 1月14日VS1月13日 | Y2: 1月15日持股量 | Z2: 1月15日VS1月14日 | AA2: 1月16日持股量 | AB2: 1月16日VS1月15日 | AC2: 1月17日持股量 | AD2: 1月17日VS1月16日 | AE2: 1月19日持股量 | AF2: 1月19日VS1月17日 | AG2: 1月20日持股量 | AH2: 1月20日VS1月19日 | AI2: 1月21日持股量 | AJ2: 1月21日VS1月20日 | AK2: 1月22日持股量 | AL2: 1月22日VS1月21日 | AM2: 1月23日持股量 | AN2: 1月23日VS1月22日 | AO2: 1月24日持股量 | AP2: 1月24日VS1月23日 | AQ2: 1月26日持股量 | AR2: 1月26日VS1月24日 | AS2: 2026年02月23日持股量 | AT2: 02月23日 VS1月26日 | AU2: 2026年02月24日持股量 | AV2: 02月24日 VS02月23日 | AW2: 2026年02月25日持股量 | AX2: 02月25日 VS02月24日 | AY2: 2026年02月26日持股量 | AZ2: 02月26日 VS02月25日 | BA2: 2026年03月02日持股量 | BB2: 03月02日 VS02月26日 | BC2: 2026年03月02日持股量 | BD2: 03月02日 VS03月02日 | BE2: 2025年12月09日持股量 | BF2: 12月09日 VS03月02日 | BG2: 2025年08月05日持股量 | BH2: 08月05日 VS12月09日 | BI2: 2025年12月09日持股量 | BJ2: 12月09日 VS08月05日 | BK2: 2026年02月26日持股量 | BL2: 02月26日 VS12月09日 | BM2: 2025年09月16日持股量 | BN2: 09月16日 VS02月26日 | BO2: 2025年06月25日持股量 | BP2: 06月25日 VS09月16日 | BQ2: 2025年06月25日持股量 | BR2: 06月25日 VS06月25日 | BS2: 2025年07月16日持股量 | BT2: 07月16日 VS06月25日 | BU2: 2026年03月02日持股量 | BV2: 03月02日 VS07月16日 | BW2: 2026年03月02日持股量 | BX2: 03月02日 VS03月02日
B3: C00019 | C3: 香港上海匯豐銀行有限公司 | D3: =_xlfn.IFNA(VLOOKUP($B3,'2026年1月2日'!$B:$E,4,0),0) | E3: =_xlfn.IFNA(VLOOKUP($B3,'2026年1月3日'!$B:$E,4,0),0) | F3: =E3-D3 | G3: =_xlfn.IFNA(VLOOKUP($B3,'2026年1月5日'!$B:$E,4,0),0) | H3: =G3-E3 | I3: =_xlfn.IFNA(VLOOKUP($B3,'2026年1月6日'!$B:$E,4,0),0) | J3: =I3-G3 | K3: =_xlfn.IFNA(VLOOKUP($B3,'2026年1月7日'!$B:$E,4,0),0) | L3: =K3-I3 | M3: =_xlfn.IFNA(VLOOKUP($B3,'2026年1月8日'!$B:$E,4,0),0) | N3: =M3-K3 | O3: =_xlfn.IFNA(VLOOKUP($B3,'2026年1月9日'!$B:$E,4,0),0) | P3: =O3-M3 | Q3: =_xlfn.IFNA(VLOOKUP($B3,'2026年1月10日'!$B:$E,4,0),0) | R3: =Q3-O3 | S3: =_xlfn.IFNA(VLOOKUP($B3,'2026年1月12日'!$B:$E,4,0),0) | T3: =S3-Q3 | U3: =_xlfn.IFNA(VLOOKUP($B3,'2026年1月13日'!$B:$E,4,0),0) | V3: =U3-S3 | W3: =_xlfn.IFNA(VLOOKUP($B3,'2026年1月14日'!$B:$E,4,0),0) | X3: =W3-U3 | Y3: =_xlfn.IFNA(VLOOKUP($B3,'2026年1月15日'!$B:$E,4,0),0) | Z3: =Y3-W3 | AA3: =_xlfn.IFNA(VLOOKUP($B3,'2026年1月16日'!$B:$E,4,0),0) | AB3: =AA3-Y3 | AC3: =_xlfn.IFNA(VLOOKUP($B3,'2026年1月17日'!$B:$E,4,0),0) | AD3: =AC3-AA3 | AE3: =_xlfn.IFNA(VLOOKUP($B3,'2026年1月19日'!$B:$E,4,0),0) | AF3: =AE3-AC3 | AG3: =_xlfn.IFNA(VLOOKUP($B3,'2026年1月20日'!$B:$E,4,0),0) | AH3: =AG3-AE3 | AI3: =_xlfn.IFNA(VLOOKUP($B3,'2026年1月21日'!$B:$E,4,0),0) | AJ3: =AI3-AG3 | AK3: =_xlfn.IFNA(VLOOKUP($B3,'2026年1月22日'!$B:$E,4,0),0) | AL3: =AK3-AI3 | AM3: =_xlfn.IFNA(VLOOKUP($B3,'2026年1月23日'!$B:$E,4,0),0) | AN3: =AM3-AK3 | AO3: =_xlfn.IFNA(VLOOKUP($B3,'2026年1月24日'!$B:$E,4,0),0) | AP3: =AO3-AM3 | AQ3: =_xlfn.IFNA(VLOOKUP($B3,'2026年1月26日'!$B:$E,4,0),0) | AR3: =AQ3-AO3 | AS3: 132692081 | AU3: 133000181 | AV3: 308100 | AW3: 133273799 | AX3: 273618 | AY3: 131170184 | AZ3: -2103615 | BA3: 129426200 | BB3: -1743984 | BC3: 130124247 | BD3: 698047 | BE3: 118322617 | BF3: -11801630 | BG3: 130559200 | BH3: 12236583 | BI3: 118322617 | BJ3: -12236583 | BK3: 131170184 | BL3: 12847567 | BM3: 134681115 | BN3: 3510931 | BO3: 129147620 | BP3: -5533495 | BQ3: 129147620 | BR3: 0 | BS3: 116350356 | BT3: -12797264 | BU3: 129426200 | BV3: 13075844 | BW3: 129426200 | BX3: 0
B4: A00004 | C4: CHINA SECURITIES DEPOSITORY AND CLEARING | D4: =_xlfn.IFNA(VLOOKUP($B4,'2026年1月2日'!$B:$E,4,0),0) | E4: =_xlfn.IFNA(VLOOKUP($B4,'2026年1月2日'!$B:$E,4,0),0) | F4: =E4-D4 | G4: =_xlfn.IFNA(VLOOKUP($B4,'2026年1月5日'!$B:$E,4,0),0) | H4: =G4-E4 | I4: =_xlfn.IFNA(VLOOKUP($B4,'2026年1月6日'!$B:$E,4,0),0) | J4: =I4-G4 | K4: =_xlfn.IFNA(VLOOKUP($B4,'2026年1月7日'!$B:$E,4,0),0) | L4: =K4-I4 | M4: =_xlfn.IFNA(VLOOKUP($B4,'2026年1月8日'!$B:$E,4,0),0) | N4: =M4-K4 | O4: =_xlfn.IFNA(VLOOKUP($B4,'2026年1月9日'!$B:$E,4,0),0) | P4: =O4-M4 | Q4: =_xlfn.IFNA(VLOOKUP($B4,'2026年1月10日'!$B:$E,4,0),0) | R4: =Q4-O4 | S4: =_xlfn.IFNA(VLOOKUP($B4,'2026年1月12日'!$B:$E,4,0),0) | T4: =S4-Q4 | U4: =_xlfn.IFNA(VLOOKUP($B4,'2026年1月13日'!$B:$E,4,0),0) | V4: =U4-S4 | W4: =_xlfn.IFNA(VLOOKUP($B4,'2026年1月14日'!$B:$E,4,0),0) | X4: =W4-U4 | Y4: =_xlfn.IFNA(VLOOKUP($B4,'2026年1月15日'!$B:$E,4,0),0) | Z4: =Y4-W4 | AA4: =_xlfn.IFNA(VLOOKUP($B4,'2026年1月16日'!$B:$E,4,0),0) | AB4: =AA4-W4 | AC4: =_xlfn.IFNA(VLOOKUP($B4,'2026年1月17日'!$B:$E,4,0),0) | AD4: =AC4-AA4 | AE4: =_xlfn.IFNA(VLOOKUP($B4,'2026年1月19日'!$B:$E,4,0),0) | AF4: =AE4-AC4 | AG4: =_xlfn.IFNA(VLOOKUP($B4,'2026年1月20日'!$B:$E,4,0),0) | AH4: =AG4-AE4 | AI4: =_xlfn.IFNA(VLOOKUP($B4,'2026年1月21日'!$B:$E,4,0),0) | AJ4: =AI4-AG4 | AK4: =_xlfn.IFNA(VLOOKUP($B4,'2026年1月22日'!$B:$E,4,0),0) | AL4: =AK4-AI4 | AM4: =_xlfn.IFNA(VLOOKUP($B4,'2026年1月23日'!$B:$E,4,0),0) | AN4: =AM4-AK4 | AO4: =_xlfn.IFNA(VLOOKUP($B4,'2026年1月24日'!$B:$E,4,0),0) | AP4: =AO4-AM4 | AQ4: =_xlfn.IFNA(VLOOKUP($B4,'2026年1月26日'!$B:$E,4,0),0) | AR4: =AQ4-AO4 | AS4: 91218748 | AU4: 91218748 | AV4: 0 | AW4: 91218748 | AX4: 0 | AY4: 92029348 | AZ4: 810600 | BA4: 93232548 | BB4: 1203200 | BC4: 92868848 | BD4: -363700 | BE4: 95039348 | BF4: 2170500 | BG4: 70290634 | BH4: -24748714 | BI4: 95039348 | BJ4: 24748714 | BK4: 92029348 | BL4: -3010000 | BM4: 81468734 | BN4: -10560614 | BO4: 75013234 | BP4: -6455500 | BQ4: 75013234 | BR4: 0 | BS4: 75026034 | BT4: 12800 | BU4: 93232548 | BV4: 18206514 | BW4: 93232548 | BX4: 0
B5: B01955 | C5: 富途證券國際(香港)有限公司 | D5: =_xlfn.IFNA(VLOOKUP($B5,'2026年1月2日'!$B:$E,4,0),0) | E5: =_xlfn.IFNA(VLOOKUP($B5,'2026年1月2日'!$B:$E,4,0),0) | F5: =E5-D5 | G5: =_xlfn.IFNA(VLOOKUP($B5,'2026年1月5日'!$B:$E,4,0),0) | H5: =G5-E5 | I5: =_xlfn.IFNA(VLOOKUP($B5,'2026年1月6日'!$B:$E,4,0),0) | J5: =I5-G5 | K5: =_xlfn.IFNA(VLOOKUP($B5,'2026年1月7日'!$B:$E,4,0),0) | L5: =K5-I5 | M5: =_xlfn.IFNA(VLOOKUP($B5,'2026年1月8日'!$B:$E,4,0),0) | N5: =M5-K5 | O5: =_xlfn.IFNA(VLOOKUP($B5,'2026年1月9日'!$B:$E,4,0),0) | P5: =O5-M5 | Q5: =_xlfn.IFNA(VLOOKUP($B5,'2026年1月10日'!$B:$E,4,0),0) | R5: =Q5-O5 | S5: =_xlfn.IFNA(VLOOKUP($B5,'2026年1月12日'!$B:$E,4,0),0) | T5: =S5-Q5 | U5: =_xlfn.IFNA(VLOOKUP($B5,'2026年1月13日'!$B:$E,4,0),0) | V5: =U5-S5 | W5: =_xlfn.IFNA(VLOOKUP($B5,'2026年1月14日'!$B:$E,4,0),0) | X5: =W5-U5 | Y5: =_xlfn.IFNA(VLOOKUP($B5,'2026年1月15日'!$B:$E,4,0),0) | Z5: =Y5-W5 | AA5: =_xlfn.IFNA(VLOOKUP($B5,'2026年1月16日'!$B:$E,4,0),0) | AB5: =AA5-W5 | AC5: =_xlfn.IFNA(VLOOKUP($B5,'2026年1月17日'!$B:$E,4,0),0) | AD5: =AC5-AA5 | AE5: =_xlfn.IFNA(VLOOKUP($B5,'2026年1月19日'!$B:$E,4,0),0) | AF5: =AE5-AC5 | AG5: =_xlfn.IFNA(VLOOKUP($B5,'2026年1月20日'!$B:$E,4,0),0) | AH5: =AG5-AE5 | AI5: =_xlfn.IFNA(VLOOKUP($B5,'2026年1月21日'!$B:$E,4,0),0) | AJ5: =AI5-AG5 | AK5: =_xlfn.IFNA(VLOOKUP($B5,'2026年1月22日'!$B:$E,4,0),0) | AL5: =AK5-AI5 | AM5: =_xlfn.IFNA(VLOOKUP($B5,'2026年1月23日'!$B:$E,4,0),0) | AN5: =AM5-AK5 | AO5: =_xlfn.IFNA(VLOOKUP($B5,'2026年1月24日'!$B:$E,4,0),0) | AP5: =AO5-AM5 | AQ5: =_xlfn.IFNA(VLOOKUP($B5,'2026年1月26日'!$B:$E,4,0),0) | AR5: =AQ5-AO5 | AS5: 44421885 | AU5: 44644385 | AV5: 222500 | AW5: 44505885 | AX5: -138500 | AY5: 44915985 | AZ5: 410100 | BA5: 45951335 | BB5: 1035350 | BC5: 45997935 | BD5: 46600 | BE5: 46443241 | BF5: 445306 | BG5: 44455884 | BH5: -1987357 | BI5: 46443241 | BJ5: 1987357 | BK5: 44915985 | BL5: -1527256 | BM5: 50611056 | BN5: 5695071 | BO5: 43584404 | BP5: -7026652 | BQ5: 43584404 | BR5: 0 | BS5: 46479609 | BT5: 2895205 | BU5: 45951335 | BV5: -528274 | BW5: 45951335 | BX5: 0
B6: A00003 | C6: 中國証券登記結算有限責任公司 | D6: =_xlfn.IFNA(VLOOKUP($B6,'2026年1月2日'!$B:$E,4,0),0) | E6: =_xlfn.IFNA(VLOOKUP($B6,'2026年1月2日'!$B:$E,4,0),0) | F6: =E6-D6 | G6: =_xlfn.IFNA(VLOOKUP($B6,'2026年1月5日'!$B:$E,4,0),0) | H6: =G6-E6 | I6: =_xlfn.IFNA(VLOOKUP($B6,'2026年1月6日'!$B:$E,4,0),0) | J6: =I6-G6 | K6: =_xlfn.IFNA(VLOOKUP($B6,'2026年1月7日'!$B:$E,4,0),0) | L6: =K6-I6 | M6: =_xlfn.IFNA(VLOOKUP($B6,'2026年1月8日'!$B:$E,4,0),0) | N6: =M6-K6 | O6: =_xlfn.IFNA(VLOOKUP($B6,'2026年1月9日'!$B:$E,4,0),0) | P6: =O6-M6 | Q6: =_xlfn.IFNA(VLOOKUP($B6,'2026年1月10日'!$B:$E,4,0),0) | R6: =Q6-O6 | S6: =_xlfn.IFNA(VLOOKUP($B6,'2026年1月12日'!$B:$E,4,0),0) | T6: =S6-Q6 | U6: =_xlfn.IFNA(VLOOKUP($B6,'2026年1月13日'!$B:$E,4,0),0) | V6: =U6-S6 | W6: =_xlfn.IFNA(VLOOKUP($B6,'2026年1月14日'!$B:$E,4,0),0) | X6: =W6-U6 | Y6: =_xlfn.IFNA(VLOOKUP($B6,'2026年1月15日'!$B:$E,4,0),0) | Z6: =Y6-W6 | AA6: =_xlfn.IFNA(VLOOKUP($B6,'2026年1月16日'!$B:$E,4,0),0) | AB6: =AA6-W6 | AC6: =_xlfn.IFNA(VLOOKUP($B6,'2026年1月17日'!$B:$E,4,0),0) | AD6: =AC6-AA6 | AE6: =_xlfn.IFNA(VLOOKUP($B6,'2026年1月19日'!$B:$E,4,0),0) | AF6: =AE6-AC6 | AG6: =_xlfn.IFNA(VLOOKUP($B6,'2026年1月20日'!$B:$E,4,0),0) | AH6: =AG6-AE6 | AI6: =_xlfn.IFNA(VLOOKUP($B6,'2026年1月21日'!$B:$E,4,0),0) | AJ6: =AI6-AG6 | AK6: =_xlfn.IFNA(VLOOKUP($B6,'2026年1月22日'!$B:$E,4,0),0) | AL6: =AK6-AI6 | AM6: =_xlfn.IFNA(VLOOKUP($B6,'2026年1月23日'!$B:$E,4,0),0) | AN6: =AM6-AK6 | AO6: =_xlfn.IFNA(VLOOKUP($B6,'2026年1月24日'!$B:$E,4,0),0) | AP6: =AO6-AM6 | AQ6: =_xlfn.IFNA(VLOOKUP($B6,'2026年1月26日'!$B:$E,4,0),0) | AR6: =AQ6-AO6 | AS6: 151148600 | AU6: 151148600 | AV6: 0 | AW6: 151148600 | AX6: 0 | AY6: 150844100 | AZ6: -304500 | BA6: 151646900 | BB6: 802800 | BC6: 151083800 | BD6: -563100 | BE6: 157431800 | BF6: 6348000 | BG6: 128024900 | BH6: -29406900 | BI6: 157431800 | BJ6: 29406900 | BK6: 150844100 | BL6: -6587700 | BM6: 133048500 | BN6: -17795600 | BO6: 124071600 | BP6: -8976900 | BQ6: 124071600 | BR6: 0 | BS6: 134887100 | BT6: 10815500 | BU6: 151646900 | BV6: 16759800 | BW6: 151646900 | BX6: 0
B7: B01451 | C7: 高盛(亞洲)證券有限公司 | D7: =_xlfn.IFNA(VLOOKUP($B7,'2026年1月2日'!$B:$E,4,0),0) | E7: =_xlfn.IFNA(VLOOKUP($B7,'2026年1月2日'!$B:$E,4,0),0) | F7: =E7-D7 | G7: =_xlfn.IFNA(VLOOKUP($B7,'2026年1月5日'!$B:$E,4,0),0) | H7: =G7-E7 | I7: =_xlfn.IFNA(VLOOKUP($B7,'2026年1月6日'!$B:$E,4,0),0) | J7: =I7-G7 | K7: =_xlfn.IFNA(VLOOKUP($B7,'2026年1月7日'!$B:$E,4,0),0) | L7: =K7-I7 | M7: =_xlfn.IFNA(VLOOKUP($B7,'2026年1月8日'!$B:$E,4,0),0) | N7: =M7-K7 | O7: =_xlfn.IFNA(VLOOKUP($B7,'2026年1月9日'!$B:$E,4,0),0) | P7: =O7-M7 | Q7: =_xlfn.IFNA(VLOOKUP($B7,'2026年1月10日'!$B:$E,4,0),0) | R7: =Q7-O7 | S7: =_xlfn.IFNA(VLOOKUP($B7,'2026年1月12日'!$B:$E,4,0),0) | T7: =S7-Q7 | U7: =_xlfn.IFNA(VLOOKUP($B7,'2026年1月13日'!$B:$E,4,0),0) | V7: =U7-S7 | W7: =_xlfn.IFNA(VLOOKUP($B7,'2026年1月14日'!$B:$E,4,0),0) | X7: =W7-U7 | Y7: =_xlfn.IFNA(VLOOKUP($B7,'2026年1月15日'!$B:$E,4,0),0) | Z7: =Y7-W7 | AA7: =_xlfn.IFNA(VLOOKUP($B7,'2026年1月16日'!$B:$E,4,0),0) | AB7: =AA7-W7 | AC7: =_xlfn.IFNA(VLOOKUP($B7,'2026年1月17日'!$B:$E,4,0),0) | AD7: =AC7-AA7 | AE7: =_xlfn.IFNA(VLOOKUP($B7,'2026年1月19日'!$B:$E,4,0),0) | AF7: =AE7-AC7 | AG7: =_xlfn.IFNA(VLOOKUP($B7,'2026年1月20日'!$B:$E,4,0),0) | AH7: =AG7-AE7 | AI7: =_xlfn.IFNA(VLOOKUP($B7,'2026年1月21日'!$B:$E,4,0),0) | AJ7: =AI7-AG7 | AK7: =_xlfn.IFNA(VLOOKUP($B7,'2026年1月22日'!$B:$E,4,0),0) | AL7: =AK7-AI7 | AM7: =_xlfn.IFNA(VLOOKUP($B7,'2026年1月23日'!$B:$E,4,0),0) | AN7: =AM7-AK7 | AO7: =_xlfn.IFNA(VLOOKUP($B7,'2026年1月24日'!$B:$E,4,0),0) | AP7: =AO7-AM7 | AQ7: =_xlfn.IFNA(VLOOKUP($B7,'2026年1月26日'!$B:$E,4,0),0) | AR7: =AQ7-AO7 | AS7: 39729324 | AU7: 39728624 | AV7: -700 | AW7: 39728424 | AX7: -200 | AY7: 39728524 | AZ7: 100 | BA7: 39728405 | BB7: -119 | BC7: 39728405 | BD7: 0 | BE7: 30238705 | BF7: -9489700 | BG7: 27050205 | BH7: -3188500 | BI7: 30238705 | BJ7: 3188500 | BK7: 39728524 | BL7: 9489819 | BM7: 45772375 | BN7: 6043851 | BO7: 27058905 | BP7: -18713470 | BQ7: 27058905 | BR7: 0 | BS7: 27267205 | BT7: 208300 | BU7: 39728405 | BV7: 12461200 | BW7: 39728405 | BX7: 0
B8: B01274 | C8: MORGAN STANLEY HONG KONG SECURITIES LTD | D8: =_xlfn.IFNA(VLOOKUP($B8,'2026年1月2日'!$B:$E,4,0),0) | E8: =_xlfn.IFNA(VLOOKUP($B8,'2026年1月2日'!$B:$E,4,0),0) | F8: =E8-D8 | G8: =_xlfn.IFNA(VLOOKUP($B8,'2026年1月5日'!$B:$E,4,0),0) | H8: =G8-E8 | I8: =_xlfn.IFNA(VLOOKUP($B8,'2026年1月6日'!$B:$E,4,0),0) | J8: =I8-G8 | K8: =_xlfn.IFNA(VLOOKUP($B8,'2026年1月7日'!$B:$E,4,0),0) | L8: =K8-I8 | M8: =_xlfn.IFNA(VLOOKUP($B8,'2026年1月8日'!$B:$E,4,0),0) | N8: =M8-K8 | O8: =_xlfn.IFNA(VLOOKUP($B8,'2026年1月9日'!$B:$E,4,0),0) | P8: =O8-M8 | Q8: =_xlfn.IFNA(VLOOKUP($B8,'2026年1月10日'!$B:$E,4,0),0) | R8: =Q8-O8 | S8: =_xlfn.IFNA(VLOOKUP($B8,'2026年1月12日'!$B:$E,4,0),0) | T8: =S8-Q8 | U8: =_xlfn.IFNA(VLOOKUP($B8,'2026年1月13日'!$B:$E,4,0),0) | V8: =U8-S8 | W8: =_xlfn.IFNA(VLOOKUP($B8,'2026年1月14日'!$B:$E,4,0),0) | X8: =W8-U8 | Y8: =_xlfn.IFNA(VLOOKUP($B8,'2026年1月15日'!$B:$E,4,0),0) | Z8: =Y8-W8 | AA8: =_xlfn.IFNA(VLOOKUP($B8,'2026年1月16日'!$B:$E,4,0),0) | AB8: =AA8-W8 | AC8: =_xlfn.IFNA(VLOOKUP($B8,'2026年1月17日'!$B:$E,4,0),0) | AD8: =AC8-AA8 | AE8: =_xlfn.IFNA(VLOOKUP($B8,'2026年1月19日'!$B:$E,4,0),0) | AF8: =AE8-AC8 | AG8: =_xlfn.IFNA(VLOOKUP($B8,'2026年1月20日'!$B:$E,4,0),0) | AH8: =AG8-AE8 | AI8: =_xlfn.IFNA(VLOOKUP($B8,'2026年1月21日'!$B:$E,4,0),0) | AJ8: =AI8-AG8 | AK8: =_xlfn.IFNA(VLOOKUP($B8,'2026年1月22日'!$B:$E,4,0),0) | AL8: =AK8-AI8 | AM8: =_xlfn.IFNA(VLOOKUP($B8,'2026年1月23日'!$B:$E,4,0),0) | AN8: =AM8-AK8 | AO8: =_xlfn.IFNA(VLOOKUP($B8,'2026年1月24日'!$B:$E,4,0),0) | AP8: =AO8-AM8 | AQ8: =_xlfn.IFNA(VLOOKUP($B8,'2026年1月26日'!$B:$E,4,0),0) | AR8: =AQ8-AO8 | AS8: 2517378 | AU8: 2603327 | AV8: 85949 | AW8: 2649827 | AX8: 46500 | AY8: 2545370 | AZ8: -104457 | BA8: 2505717 | BB8: -39653 | BE8: 2745550 | BG8: 2404549 | BH8: -341001 | BI8: 2745550 | BJ8: 341001 | BK8: 2545370 | BL8: -200180 | BM8: 2951598 | BN8: 406228 | BO8: 4596952 | BP8: 1645354 | BQ8: 4596952 | BR8: 0 | BS8: 4606849 | BT8: 9897 | BU8: 2505717 | BV8: -2101132 | BW8: 2505717 | BX8: 0
B9: C00100 | C9: JPMORGAN CHASE BANK, NATIONAL ASSOCIATION | D9: =_xlfn.IFNA(VLOOKUP($B9,'2026年1月2日'!$B:$E,4,0),0) | E9: =_xlfn.IFNA(VLOOKUP($B9,'2026年1月2日'!$B:$E,4,0),0) | F9: =E9-D9 | G9: =_xlfn.IFNA(VLOOKUP($B9,'2026年1月5日'!$B:$E,4,0),0) | H9: =G9-E9 | I9: =_xlfn.IFNA(VLOOKUP($B9,'2026年1月6日'!$B:$E,4,0),0) | J9: =I9-G9 | K9: =_xlfn.IFNA(VLOOKUP($B9,'2026年1月7日'!$B:$E,4,0),0) | L9: =K9-I9 | M9: =_xlfn.IFNA(VLOOKUP($B9,'2026年1月8日'!$B:$E,4,0),0) | N9: =M9-K9 | O9: =_xlfn.IFNA(VLOOKUP($B9,'2026年1月9日'!$B:$E,4,0),0) | P9: =O9-M9 | Q9: =_xlfn.IFNA(VLOOKUP($B9,'2026年1月10日'!$B:$E,4,0),0) | R9: =Q9-O9 | S9: =_xlfn.IFNA(VLOOKUP($B9,'2026年1月12日'!$B:$E,4,0),0) | T9: =S9-Q9 | U9: =_xlfn.IFNA(VLOOKUP($B9,'2026年1月13日'!$B:$E,4,0),0) | V9: =U9-S9 | W9: =_xlfn.IFNA(VLOOKUP($B9,'2026年1月14日'!$B:$E,4,0),0) | X9: =W9-U9 | Y9: =_xlfn.IFNA(VLOOKUP($B9,'2026年1月15日'!$B:$E,4,0),0) | Z9: =Y9-W9 | AA9: =_xlfn.IFNA(VLOOKUP($B9,'2026年1月16日'!$B:$E,4,0),0) | AB9: =AA9-W9 | AC9: =_xlfn.IFNA(VLOOKUP($B9,'2026年1月17日'!$B:$E,4,0),0) | AD9: =AC9-AA9 | AE9: =_xlfn.IFNA(VLOOKUP($B9,'2026年1月19日'!$B:$E,4,0),0) | AF9: =AE9-AC9 | AG9: =_xlfn.IFNA(VLOOKUP($B9,'2026年1月20日'!$B:$E,4,0),0) | AH9: =AG9-AE9 | AI9: =_xlfn.IFNA(VLOOKUP($B9,'2026年1月21日'!$B:$E,4,0),0) | AJ9: =AI9-AG9 | AK9: =_xlfn.IFNA(VLOOKUP($B9,'2026年1月22日'!$B:$E,4,0),0) | AL9: =AK9-AI9 | AM9: =_xlfn.IFNA(VLOOKUP($B9,'2026年1月23日'!$B:$E,4,0),0) | AN9: =AM9-AK9 | AO9: =_xlfn.IFNA(VLOOKUP($B9,'2026年1月24日'!$B:$E,4,0),0) | AP9: =AO9-AM9 | AQ9: =_xlfn.IFNA(VLOOKUP($B9,'2026年1月26日'!$B:$E,4,0),0) | AR9: =AQ9-AO9
B10: C00033 | C10: 中國銀行(香港)有限公司 | D10: =_xlfn.IFNA(VLOOKUP($B10,'2026年1月2日'!$B:$E,4,0),0) | E10: =_xlfn.IFNA(VLOOKUP($B10,'2026年1月2日'!$B:$E,4,0),0) | F10: =E10-D10 | G10: =_xlfn.IFNA(VLOOKUP($B10,'2026年1月5日'!$B:$E,4,0),0) | H10: =G10-E10 | I10: =_xlfn.IFNA(VLOOKUP($B10,'2026年1月6日'!$B:$E,4,0),0) | J10: =I10-G10 | K10: =_xlfn.IFNA(VLOOKUP($B10,'2026年1月7日'!$B:$E,4,0),0) | L10: =K10-I10 | M10: =_xlfn.IFNA(VLOOKUP($B10,'2026年1月8日'!$B:$E,4,0),0) | N10: =M10-K10 | O10: =_xlfn.IFNA(VLOOKUP($B10,'2026年1月9日'!$B:$E,4,0),0) | P10: =O10-M10 | Q10: =_xlfn.IFNA(VLOOKUP($B10,'2026年1月10日'!$B:$E,4,0),0) | R10: =Q10-O10 | S10: =_xlfn.IFNA(VLOOKUP($B10,'2026年1月12日'!$B:$E,4,0),0) | T10: =S10-Q10 | U10: =_xlfn.IFNA(VLOOKUP($B10,'2026年1月13日'!$B:$E,4,0),0) | V10: =U10-S10 | W10: =_xlfn.IFNA(VLOOKUP($B10,'2026年1月14日'!$B:$E,4,0),0) | X10: =W10-U10 | Y10: =_xlfn.IFNA(VLOOKUP($B10,'2026年1月15日'!$B:$E,4,0),0) | Z10: =Y10-W10 | AA10: =_xlfn.IFNA(VLOOKUP($B10,'2026年1月16日'!$B:$E,4,0),0) | AB10: =AA10-W10 | AC10: =_xlfn.IFNA(VLOOKUP($B10,'2026年1月17日'!$B:$E,4,0),0) | AD10: =AC10-AA10 | AE10: =_xlfn.IFNA(VLOOKUP($B10,'2026年1月19日'!$B:$E,4,0),0) | AF10: =AE10-AC10 | AG10: =_xlfn.IFNA(VLOOKUP($B10,'2026年1月20日'!$B:$E,4,0),0) | AH10: =AG10-AE10 | AI10: =_xlfn.IFNA(VLOOKUP($B10,'2026年1月21日'!$B:$E,4,0),0) | AJ10: =AI10-AG10 | AK10: =_xlfn.IFNA(VLOOKUP($B10,'2026年1月22日'!$B:$E,4,0),0) | AL10: =AK10-AI10 | AM10: =_xlfn.IFNA(VLOOKUP($B10,'2026年1月23日'!$B:$E,4,0),0) | AN10: =AM10-AK10 | AO10: =_xlfn.IFNA(VLOOKUP($B10,'2026年1月24日'!$B:$E,4,0),0) | AP10: =AO10-AM10 | AQ10: =_xlfn.IFNA(VLOOKUP($B10,'2026年1月26日'!$B:$E,4,0),0) | AR10: =AQ10-AO10 | AS10: 20918600 | AU10: 20938400 | AV10: 19800 | AW10: 20912300 | AX10: -26100 | AY10: 20977500 | AZ10: 65200 | BA10: 20886200 | BB10: -91300 | BC10: 20869500 | BD10: -16700 | BE10: 23724000 | BF10: 2854500 | BG10: 20883400 | BH10: -2840600 | BI10: 23724000 | BJ10: 2840600 | BK10: 20977500 | BL10: -2746500 | BM10: 21912800 | BN10: 935300 | BO10: 21713300 | BP10: -199500 | BQ10: 21713300 | BR10: 0 | BS10: 23279400 | BT10: 1566100 | BU10: 20886200 | BV10: -2393200 | BW10: 20886200 | BX10: 0
B11: B01912 | C11: 核聚證券有限公司 | D11: =_xlfn.IFNA(VLOOKUP($B11,'2026年1月2日'!$B:$E,4,0),0) | E11: =_xlfn.IFNA(VLOOKUP($B11,'2026年1月2日'!$B:$E,4,0),0) | F11: =E11-D11 | G11: =_xlfn.IFNA(VLOOKUP($B11,'2026年1月5日'!$B:$E,4,0),0) | H11: =G11-E11 | I11: =_xlfn.IFNA(VLOOKUP($B11,'2026年1月6日'!$B:$E,4,0),0) | J11: =I11-G11 | K11: =_xlfn.IFNA(VLOOKUP($B11,'2026年1月7日'!$B:$E,4,0),0) | L11: =K11-I11 | M11: =_xlfn.IFNA(VLOOKUP($B11,'2026年1月8日'!$B:$E,4,0),0) | N11: =M11-K11 | O11: =_xlfn.IFNA(VLOOKUP($B11,'2026年1月9日'!$B:$E,4,0),0) | P11: =O11-M11 | Q11: =_xlfn.IFNA(VLOOKUP($B11,'2026年1月10日'!$B:$E,4,0),0) | R11: =Q11-O11 | S11: =_xlfn.IFNA(VLOOKUP($B11,'2026年1月12日'!$B:$E,4,0),0) | T11: =S11-Q11 | U11: =_xlfn.IFNA(VLOOKUP($B11,'2026年1月13日'!$B:$E,4,0),0) | V11: =U11-S11 | W11: =_xlfn.IFNA(VLOOKUP($B11,'2026年1月14日'!$B:$E,4,0),0) | X11: =W11-U11 | Y11: =_xlfn.IFNA(VLOOKUP($B11,'2026年1月15日'!$B:$E,4,0),0) | Z11: =Y11-W11 | AA11: =_xlfn.IFNA(VLOOKUP($B11,'2026年1月16日'!$B:$E,4,0),0) | AB11: =AA11-W11 | AC11: =_xlfn.IFNA(VLOOKUP($B11,'2026年1月17日'!$B:$E,4,0),0) | AD11: =AC11-AA11 | AE11: =_xlfn.IFNA(VLOOKUP($B11,'2026年1月19日'!$B:$E,4,0),0) | AF11: =AE11-AC11 | AG11: =_xlfn.IFNA(VLOOKUP($B11,'2026年1月20日'!$B:$E,4,0),0) | AH11: =AG11-AE11 | AI11: =_xlfn.IFNA(VLOOKUP($B11,'2026年1月21日'!$B:$E,4,0),0) | AJ11: =AI11-AG11 | AK11: =_xlfn.IFNA(VLOOKUP($B11,'2026年1月22日'!$B:$E,4,0),0) | AL11: =AK11-AI11 | AM11: =_xlfn.IFNA(VLOOKUP($B11,'2026年1月23日'!$B:$E,4,0),0) | AN11: =AM11-AK11 | AO11: =_xlfn.IFNA(VLOOKUP($B11,'2026年1月24日'!$B:$E,4,0),0) | AP11: =AO11-AM11 | AQ11: =_xlfn.IFNA(VLOOKUP($B11,'2026年1月26日'!$B:$E,4,0),0) | AR11: =AQ11-AO11 | AS11: 19883897 | AU11: 19883897 | AV11: 0 | AW11: 19883897 | AX11: 0 | AY11: 19883897 | AZ11: 0 | BA11: 19883897 | BB11: 0 | BC11: 19883897 | BD11: 0 | BE11: 19643916 | BF11: -239981 | BG11: 20315016 | BH11: 671100 | BI11: 19643916 | BJ11: -671100 | BK11: 19883897 | BL11: 239981 | BM11: 19833916 | BN11: -49981 | BO11: 19289317 | BP11: -544599 | BQ11: 19289317 | BR11: 0 | BS11: 19795842 | BT11: 506525 | BU11: 19883897 | BV11: 88055 | BW11: 19883897 | BX11: 0
B12: C00010 | C12: 花旗銀行 | D12: =_xlfn.IFNA(VLOOKUP($B12,'2026年1月2日'!$B:$E,4,0),0) | E12: =_xlfn.IFNA(VLOOKUP($B12,'2026年1月2日'!$B:$E,4,0),0) | F12: =E12-D12 | G12: =_xlfn.IFNA(VLOOKUP($B12,'2026年1月5日'!$B:$E,4,0),0) | H12: =G12-E12 | I12: =_xlfn.IFNA(VLOOKUP($B12,'2026年1月6日'!$B:$E,4,0),0) | J12: =I12-G12 | K12: =_xlfn.IFNA(VLOOKUP($B12,'2026年1月7日'!$B:$E,4,0),0) | L12: =K12-I12 | M12: =_xlfn.IFNA(VLOOKUP($B12,'2026年1月8日'!$B:$E,4,0),0) | N12: =M12-K12 | O12: =_xlfn.IFNA(VLOOKUP($B12,'2026年1月9日'!$B:$E,4,0),0) | P12: =O12-M12 | Q12: =_xlfn.IFNA(VLOOKUP($B12,'2026年1月10日'!$B:$E,4,0),0) | R12: =Q12-O12 | S12: =_xlfn.IFNA(VLOOKUP($B12,'2026年1月12日'!$B:$E,4,0),0) | T12: =S12-Q12 | U12: =_xlfn.IFNA(VLOOKUP($B12,'2026年1月13日'!$B:$E,4,0),0) | V12: =U12-S12 | W12: =_xlfn.IFNA(VLOOKUP($B12,'2026年1月14日'!$B:$E,4,0),0) | X12: =W12-U12 | Y12: =_xlfn.IFNA(VLOOKUP($B12,'2026年1月15日'!$B:$E,4,0),0) | Z12: =Y12-W12 | AA12: =_xlfn.IFNA(VLOOKUP($B12,'2026年1月16日'!$B:$E,4,0),0) | AB12: =AA12-W12 | AC12: =_xlfn.IFNA(VLOOKUP($B12,'2026年1月17日'!$B:$E,4,0),0) | AD12: =AC12-AA12 | AE12: =_xlfn.IFNA(VLOOKUP($B12,'2026年1月19日'!$B:$E,4,0),0) | AF12: =AE12-AC12 | AG12: =_xlfn.IFNA(VLOOKUP($B12,'2026年1月20日'!$B:$E,4,0),0) | AH12: =AG12-AE12 | AI12: =_xlfn.IFNA(VLOOKUP($B12,'2026年1月21日'!$B:$E,4,0),0) | AJ12: =AI12-AG12 | AK12: =_xlfn.IFNA(VLOOKUP($B12,'2026年1月22日'!$B:$E,4,0),0) | AL12: =AK12-AI12 | AM12: =_xlfn.IFNA(VLOOKUP($B12,'2026年1月23日'!$B:$E,4,0),0) | AN12: =AM12-AK12 | AO12: =_xlfn.IFNA(VLOOKUP($B12,'2026年1月24日'!$B:$E,4,0),0) | AP12: =AO12-AM12 | AQ12: =_xlfn.IFNA(VLOOKUP($B12,'2026年1月26日'!$B:$E,4,0),0) | AR12: =AQ12-AO12 | AS12: 24615911 | AU12: 25465144 | AV12: 849233 | AW12: 23874326 | AX12: -1590818 | AY12: 24279548 | AZ12: 405222 | BA12: 22680945 | BB12: -1598603 | BC12: 23215345 | BD12: 534400 | BE12: 21695290 | BF12: -1520055 | BG12: 19653679 | BH12: -2041611 | BI12: 21695290 | BJ12: 2041611 | BK12: 24279548 | BL12: 2584258 | BM12: 18486615 | BN12: -5792933 | BO12: 20737157 | BP12: 2250542 | BQ12: 20737157 | BR12: 0 | BS12: 12610040 | BT12: -8127117 | BU12: 22680945 | BV12: 10070905 | BW12: 22680945 | BX12: 0
B13: B01161 | C13: UBS SECURITIES HONG KONG LTD | D13: =_xlfn.IFNA(VLOOKUP($B13,'2026年1月2日'!$B:$E,4,0),0) | E13: =_xlfn.IFNA(VLOOKUP($B13,'2026年1月2日'!$B:$E,4,0),0) | F13: =E13-D13 | G13: =_xlfn.IFNA(VLOOKUP($B13,'2026年1月5日'!$B:$E,4,0),0) | H13: =G13-E13 | I13: =_xlfn.IFNA(VLOOKUP($B13,'2026年1月6日'!$B:$E,4,0),0) | J13: =I13-G13 | K13: =_xlfn.IFNA(VLOOKUP($B13,'2026年1月7日'!$B:$E,4,0),0) | L13: =K13-I13 | M13: =_xlfn.IFNA(VLOOKUP($B13,'2026年1月8日'!$B:$E,4,0),0) | N13: =M13-K13 | O13: =_xlfn.IFNA(VLOOKUP($B13,'2026年1月9日'!$B:$E,4,0),0) | P13: =O13-M13 | Q13: =_xlfn.IFNA(VLOOKUP($B13,'2026年1月10日'!$B:$E,4,0),0) | R13: =Q13-O13 | S13: =_xlfn.IFNA(VLOOKUP($B13,'2026年1月12日'!$B:$E,4,0),0) | T13: =S13-Q13 | U13: =_xlfn.IFNA(VLOOKUP($B13,'2026年1月13日'!$B:$E,4,0),0) | V13: =U13-S13 | W13: =_xlfn.IFNA(VLOOKUP($B13,'2026年1月14日'!$B:$E,4,0),0) | X13: =W13-U13 | Y13: =_xlfn.IFNA(VLOOKUP($B13,'2026年1月15日'!$B:$E,4,0),0) | Z13: =Y13-W13 | AA13: =_xlfn.IFNA(VLOOKUP($B13,'2026年1月16日'!$B:$E,4,0),0) | AB13: =AA13-W13 | AC13: =_xlfn.IFNA(VLOOKUP($B13,'2026年1月17日'!$B:$E,4,0),0) | AD13: =AC13-AA13 | AE13: =_xlfn.IFNA(VLOOKUP($B13,'2026年1月19日'!$B:$E,4,0),0) | AF13: =AE13-AC13 | AG13: =_xlfn.IFNA(VLOOKUP($B13,'2026年1月20日'!$B:$E,4,0),0) | AH13: =AG13-AE13 | AI13: =_xlfn.IFNA(VLOOKUP($B13,'2026年1月21日'!$B:$E,4,0),0) | AJ13: =AI13-AG13 | AK13: =_xlfn.IFNA(VLOOKUP($B13,'2026年1月22日'!$B:$E,4,0),0) | AL13: =AK13-AI13 | AM13: =_xlfn.IFNA(VLOOKUP($B13,'2026年1月23日'!$B:$E,4,0),0) | AN13: =AM13-AK13 | AO13: =_xlfn.IFNA(VLOOKUP($B13,'2026年1月24日'!$B:$E,4,0),0) | AP13: =AO13-AM13 | AQ13: =_xlfn.IFNA(VLOOKUP($B13,'2026年1月26日'!$B:$E,4,0),0) | AR13: =AQ13-AO13 | AS13: 2204036 | AU13: 2156087 | AV13: -47949 | AW13: 2176087 | AX13: 20000 | AY13: 2176037 | AZ13: -50 | BA13: 2202103 | BB13: 26066 | BE13: 2334631 | BG13: 2154892 | BH13: -179739 | BI13: 2334631 | BJ13: 179739 | BK13: 2176037 | BL13: -158594 | BM13: 2736602 | BN13: 560565 | BO13: 2137497 | BP13: -599105 | BQ13: 2137497 | BR13: 0 | BS13: 2184592 | BT13: 47095 | BU13: 2202103 | BV13: 17511 | BW13: 2202103 | BX13: 0
B14: B01901 | C14: 招銀國際證券有限公司 | D14: =_xlfn.IFNA(VLOOKUP($B14,'2026年1月2日'!$B:$E,4,0),0) | E14: =_xlfn.IFNA(VLOOKUP($B14,'2026年1月2日'!$B:$E,4,0),0) | F14: =E14-D14 | G14: =_xlfn.IFNA(VLOOKUP($B14,'2026年1月5日'!$B:$E,4,0),0) | H14: =G14-E14 | I14: =_xlfn.IFNA(VLOOKUP($B14,'2026年1月6日'!$B:$E,4,0),0) | J14: =I14-G14 | K14: =_xlfn.IFNA(VLOOKUP($B14,'2026年1月7日'!$B:$E,4,0),0) | L14: =K14-I14 | M14: =_xlfn.IFNA(VLOOKUP($B14,'2026年1月8日'!$B:$E,4,0),0) | N14: =M14-K14 | O14: =_xlfn.IFNA(VLOOKUP($B14,'2026年1月9日'!$B:$E,4,0),0) | P14: =O14-M14 | Q14: =_xlfn.IFNA(VLOOKUP($B14,'2026年1月10日'!$B:$E,4,0),0) | R14: =Q14-O14 | S14: =_xlfn.IFNA(VLOOKUP($B14,'2026年1月12日'!$B:$E,4,0),0) | T14: =S14-Q14 | U14: =_xlfn.IFNA(VLOOKUP($B14,'2026年1月13日'!$B:$E,4,0),0) | V14: =U14-S14 | W14: =_xlfn.IFNA(VLOOKUP($B14,'2026年1月14日'!$B:$E,4,0),0) | X14: =W14-U14 | Y14: =_xlfn.IFNA(VLOOKUP($B14,'2026年1月15日'!$B:$E,4,0),0) | Z14: =Y14-W14 | AA14: =_xlfn.IFNA(VLOOKUP($B14,'2026年1月16日'!$B:$E,4,0),0) | AB14: =AA14-W14 | AC14: =_xlfn.IFNA(VLOOKUP($B14,'2026年1月17日'!$B:$E,4,0),0) | AD14: =AC14-AA14 | AE14: =_xlfn.IFNA(VLOOKUP($B14,'2026年1月19日'!$B:$E,4,0),0) | AF14: =AE14-AC14 | AG14: =_xlfn.IFNA(VLOOKUP($B14,'2026年1月20日'!$B:$E,4,0),0) | AH14: =AG14-AE14 | AI14: =_xlfn.IFNA(VLOOKUP($B14,'2026年1月21日'!$B:$E,4,0),0) | AJ14: =AI14-AG14 | AK14: =_xlfn.IFNA(VLOOKUP($B14,'2026年1月22日'!$B:$E,4,0),0) | AL14: =AK14-AI14 | AM14: =_xlfn.IFNA(VLOOKUP($B14,'2026年1月23日'!$B:$E,4,0),0) | AN14: =AM14-AK14 | AO14: =_xlfn.IFNA(VLOOKUP($B14,'2026年1月24日'!$B:$E,4,0),0) | AP14: =AO14-AM14 | AQ14: =_xlfn.IFNA(VLOOKUP($B14,'2026年1月26日'!$B:$E,4,0),0) | AR14: =AQ14-AO14 | AS14: 6816190 | AU14: 6816190 | AV14: 0 | AW14: 6816190 | AX14: 0 | AY14: 6816390 | AZ14: 200 | BA14: 6817590 | BB14: 1200 | BC14: 6817590 | BD14: 0 | BE14: 6935990 | BF14: 118400 | BG14: 5858690 | BH14: -1077300 | BI14: 6935990 | BJ14: 1077300 | BK14: 6816390 | BL14: -119600 | BM14: 7174190 | BN14: 357800 | BO14: 5504590 | BP14: -1669600 | BQ14: 5504590 | BR14: 0 | BS14: 5710190 | BT14: 205600 | BU14: 6817590 | BV14: 1107400 | BW14: 6817590 | BX14: 0
B15: B01590 | C15: 盈透證券香港有限公司 | D15: =_xlfn.IFNA(VLOOKUP($B15,'2026年1月2日'!$B:$E,4,0),0) | E15: =_xlfn.IFNA(VLOOKUP($B15,'2026年1月2日'!$B:$E,4,0),0) | F15: =E15-D15 | G15: =_xlfn.IFNA(VLOOKUP($B15,'2026年1月5日'!$B:$E,4,0),0) | H15: =G15-E15 | I15: =_xlfn.IFNA(VLOOKUP($B15,'2026年1月6日'!$B:$E,4,0),0) | J15: =I15-G15 | K15: =_xlfn.IFNA(VLOOKUP($B15,'2026年1月7日'!$B:$E,4,0),0) | L15: =K15-I15 | M15: =_xlfn.IFNA(VLOOKUP($B15,'2026年1月8日'!$B:$E,4,0),0) | N15: =M15-K15 | O15: =_xlfn.IFNA(VLOOKUP($B15,'2026年1月9日'!$B:$E,4,0),0) | P15: =O15-M15 | Q15: =_xlfn.IFNA(VLOOKUP($B15,'2026年1月10日'!$B:$E,4,0),0) | R15: =Q15-O15 | S15: =_xlfn.IFNA(VLOOKUP($B15,'2026年1月12日'!$B:$E,4,0),0) | T15: =S15-Q15 | U15: =_xlfn.IFNA(VLOOKUP($B15,'2026年1月13日'!$B:$E,4,0),0) | V15: =U15-S15 | W15: =_xlfn.IFNA(VLOOKUP($B15,'2026年1月14日'!$B:$E,4,0),0) | X15: =W15-U15 | Y15: =_xlfn.IFNA(VLOOKUP($B15,'2026年1月15日'!$B:$E,4,0),0) | Z15: =Y15-W15 | AA15: =_xlfn.IFNA(VLOOKUP($B15,'2026年1月16日'!$B:$E,4,0),0) | AB15: =AA15-W15 | AC15: =_xlfn.IFNA(VLOOKUP($B15,'2026年1月17日'!$B:$E,4,0),0) | AD15: =AC15-AA15 | AE15: =_xlfn.IFNA(VLOOKUP($B15,'2026年1月19日'!$B:$E,4,0),0) | AF15: =AE15-AC15 | AG15: =_xlfn.IFNA(VLOOKUP($B15,'2026年1月20日'!$B:$E,4,0),0) | AH15: =AG15-AE15 | AI15: =_xlfn.IFNA(VLOOKUP($B15,'2026年1月21日'!$B:$E,4,0),0) | AJ15: =AI15-AG15 | AK15: =_xlfn.IFNA(VLOOKUP($B15,'2026年1月22日'!$B:$E,4,0),0) | AL15: =AK15-AI15 | AM15: =_xlfn.IFNA(VLOOKUP($B15,'2026年1月23日'!$B:$E,4,0),0) | AN15: =AM15-AK15 | AO15: =_xlfn.IFNA(VLOOKUP($B15,'2026年1月24日'!$B:$E,4,0),0) | AP15: =AO15-AM15 | AQ15: =_xlfn.IFNA(VLOOKUP($B15,'2026年1月26日'!$B:$E,4,0),0) | AR15: =AQ15-AO15 | AS15: 1911100 | AU15: 968400 | AV15: -942700 | AW15: 1129700 | AX15: 161300 | AY15: 1099000 | AZ15: -30700 | BA15: 1228393 | BB15: 129393 | BE15: 1003188 | BG15: 657719 | BH15: -345469 | BI15: 1003188 | BJ15: 345469 | BK15: 1099000 | BL15: 95812 | BM15: 908522 | BN15: -190478 | BO15: 1071888 | BP15: 163366 | BQ15: 1071888 | BR15: 0 | BS15: 1033688 | BT15: -38200 | BU15: 1228393 | BV15: 194705 | BW15: 1228393 | BX15: 0
B16: C00039 | C16: 渣打銀行(香港)有限公司 | D16: =_xlfn.IFNA(VLOOKUP($B16,'2026年1月2日'!$B:$E,4,0),0) | E16: =_xlfn.IFNA(VLOOKUP($B16,'2026年1月2日'!$B:$E,4,0),0) | F16: =E16-D16 | G16: =_xlfn.IFNA(VLOOKUP($B16,'2026年1月5日'!$B:$E,4,0),0) | H16: =G16-E16 | I16: =_xlfn.IFNA(VLOOKUP($B16,'2026年1月6日'!$B:$E,4,0),0) | J16: =I16-G16 | K16: =_xlfn.IFNA(VLOOKUP($B16,'2026年1月7日'!$B:$E,4,0),0) | L16: =K16-I16 | M16: =_xlfn.IFNA(VLOOKUP($B16,'2026年1月8日'!$B:$E,4,0),0) | N16: =M16-K16 | O16: =_xlfn.IFNA(VLOOKUP($B16,'2026年1月9日'!$B:$E,4,0),0) | P16: =O16-M16 | Q16: =_xlfn.IFNA(VLOOKUP($B16,'2026年1月10日'!$B:$E,4,0),0) | R16: =Q16-O16 | S16: =_xlfn.IFNA(VLOOKUP($B16,'2026年1月12日'!$B:$E,4,0),0) | T16: =S16-Q16 | U16: =_xlfn.IFNA(VLOOKUP($B16,'2026年1月13日'!$B:$E,4,0),0) | V16: =U16-S16 | W16: =_xlfn.IFNA(VLOOKUP($B16,'2026年1月14日'!$B:$E,4,0),0) | X16: =W16-U16 | Y16: =_xlfn.IFNA(VLOOKUP($B16,'2026年1月15日'!$B:$E,4,0),0) | Z16: =Y16-W16 | AA16: =_xlfn.IFNA(VLOOKUP($B16,'2026年1月16日'!$B:$E,4,0),0) | AB16: =AA16-W16 | AC16: =_xlfn.IFNA(VLOOKUP($B16,'2026年1月17日'!$B:$E,4,0),0) | AD16: =AC16-AA16 | AE16: =_xlfn.IFNA(VLOOKUP($B16,'2026年1月19日'!$B:$E,4,0),0) | AF16: =AE16-AC16 | AG16: =_xlfn.IFNA(VLOOKUP($B16,'2026年1月20日'!$B:$E,4,0),0) | AH16: =AG16-AE16 | AI16: =_xlfn.IFNA(VLOOKUP($B16,'2026年1月21日'!$B:$E,4,0),0) | AJ16: =AI16-AG16 | AK16: =_xlfn.IFNA(VLOOKUP($B16,'2026年1月22日'!$B:$E,4,0),0) | AL16: =AK16-AI16 | AM16: =_xlfn.IFNA(VLOOKUP($B16,'2026年1月23日'!$B:$E,4,0),0) | AN16: =AM16-AK16 | AO16: =_xlfn.IFNA(VLOOKUP($B16,'2026年1月24日'!$B:$E,4,0),0) | AP16: =AO16-AM16 | AQ16: =_xlfn.IFNA(VLOOKUP($B16,'2026年1月26日'!$B:$E,4,0),0) | AR16: =AQ16-AO16 | AS16: 9893437 | AU16: 9875337 | AV16: -18100 | AW16: 9855237 | AX16: -20100 | AY16: 9825737 | AZ16: -29500 | BA16: 9815437 | BB16: -10300 | BC16: 9823437 | BD16: 8000 | BE16: 10279729 | BF16: 456292 | BG16: 8626387 | BH16: -1653342 | BI16: 10279729 | BJ16: 1653342 | BK16: 9825737 | BL16: -453992 | BM16: 9350435 | BN16: -475302 | BO16: 8758389 | BP16: -592046 | BQ16: 8758389 | BR16: 0 | BS16: 8772987 | BT16: 14598 | BU16: 9815437 | BV16: 1042450 | BW16: 9815437 | BX16: 0
B17: B01284 | C17: 恒生證券有限公司 | D17: =_xlfn.IFNA(VLOOKUP($B17,'2026年1月2日'!$B:$E,4,0),0) | E17: =_xlfn.IFNA(VLOOKUP($B17,'2026年1月2日'!$B:$E,4,0),0) | F17: =E17-D17 | G17: =_xlfn.IFNA(VLOOKUP($B17,'2026年1月5日'!$B:$E,4,0),0) | H17: =G17-E17 | I17: =_xlfn.IFNA(VLOOKUP($B17,'2026年1月6日'!$B:$E,4,0),0) | J17: =I17-G17 | K17: =_xlfn.IFNA(VLOOKUP($B17,'2026年1月7日'!$B:$E,4,0),0) | L17: =K17-I17 | M17: =_xlfn.IFNA(VLOOKUP($B17,'2026年1月8日'!$B:$E,4,0),0) | N17: =M17-K17 | O17: =_xlfn.IFNA(VLOOKUP($B17,'2026年1月9日'!$B:$E,4,0),0) | P17: =O17-M17 | Q17: =_xlfn.IFNA(VLOOKUP($B17,'2026年1月10日'!$B:$E,4,0),0) | R17: =Q17-O17 | S17: =_xlfn.IFNA(VLOOKUP($B17,'2026年1月12日'!$B:$E,4,0),0) | T17: =S17-Q17 | U17: =_xlfn.IFNA(VLOOKUP($B17,'2026年1月13日'!$B:$E,4,0),0) | V17: =U17-S17 | W17: =_xlfn.IFNA(VLOOKUP($B17,'2026年1月14日'!$B:$E,4,0),0) | X17: =W17-U17 | Y17: =_xlfn.IFNA(VLOOKUP($B17,'2026年1月15日'!$B:$E,4,0),0) | Z17: =Y17-W17 | AA17: =_xlfn.IFNA(VLOOKUP($B17,'2026年1月16日'!$B:$E,4,0),0) | AB17: =AA17-W17 | AC17: =_xlfn.IFNA(VLOOKUP($B17,'2026年1月17日'!$B:$E,4,0),0) | AD17: =AC17-AA17 | AE17: =_xlfn.IFNA(VLOOKUP($B17,'2026年1月19日'!$B:$E,4,0),0) | AF17: =AE17-AC17 | AG17: =_xlfn.IFNA(VLOOKUP($B17,'2026年1月20日'!$B:$E,4,0),0) | AH17: =AG17-AE17 | AI17: =_xlfn.IFNA(VLOOKUP($B17,'2026年1月21日'!$B:$E,4,0),0) | AJ17: =AI17-AG17 | AK17: =_xlfn.IFNA(VLOOKUP($B17,'2026年1月22日'!$B:$E,4,0),0) | AL17: =AK17-AI17 | AM17: =_xlfn.IFNA(VLOOKUP($B17,'2026年1月23日'!$B:$E,4,0),0) | AN17: =AM17-AK17 | AO17: =_xlfn.IFNA(VLOOKUP($B17,'2026年1月24日'!$B:$E,4,0),0) | AP17: =AO17-AM17 | AQ17: =_xlfn.IFNA(VLOOKUP($B17,'2026年1月26日'!$B:$E,4,0),0) | AR17: =AQ17-AO17 | AS17: 8821500 | AU17: 8820700 | AV17: -800 | AW17: 8836700 | AX17: 16000 | AY17: 8823000 | AZ17: -13700 | BA17: 8850500 | BB17: 27500 | BC17: 8846600 | BD17: -3900 | BE17: 9697100 | BF17: 850500 | BG17: 9391400 | BH17: -305700 | BI17: 9697100 | BJ17: 305700 | BK17: 8823000 | BL17: -874100 | BM17: 9888100 | BN17: 1065100 | BO17: 9351600 | BP17: -536500 | BQ17: 9351600 | BR17: 0 | BS17: 9778500 | BT17: 426900 | BU17: 8850500 | BV17: -928000 | BW17: 8850500 | BX17: 0
B18: C00093 | C18: BNP PARIBAS SECURITIES SERVICES | D18: =_xlfn.IFNA(VLOOKUP($B18,'2026年1月2日'!$B:$E,4,0),0) | E18: =_xlfn.IFNA(VLOOKUP($B18,'2026年1月2日'!$B:$E,4,0),0) | F18: =E18-D18 | G18: =_xlfn.IFNA(VLOOKUP($B18,'2026年1月5日'!$B:$E,4,0),0) | H18: =G18-E18 | I18: =_xlfn.IFNA(VLOOKUP($B18,'2026年1月6日'!$B:$E,4,0),0) | J18: =I18-G18 | K18: =_xlfn.IFNA(VLOOKUP($B18,'2026年1月7日'!$B:$E,4,0),0) | L18: =K18-I18 | M18: =_xlfn.IFNA(VLOOKUP($B18,'2026年1月8日'!$B:$E,4,0),0) | N18: =M18-K18 | O18: =_xlfn.IFNA(VLOOKUP($B18,'2026年1月9日'!$B:$E,4,0),0) | P18: =O18-M18 | Q18: =_xlfn.IFNA(VLOOKUP($B18,'2026年1月10日'!$B:$E,4,0),0) | R18: =Q18-O18 | S18: =_xlfn.IFNA(VLOOKUP($B18,'2026年1月12日'!$B:$E,4,0),0) | T18: =S18-Q18 | U18: =_xlfn.IFNA(VLOOKUP($B18,'2026年1月13日'!$B:$E,4,0),0) | V18: =U18-S18 | W18: =_xlfn.IFNA(VLOOKUP($B18,'2026年1月14日'!$B:$E,4,0),0) | X18: =W18-U18 | Y18: =_xlfn.IFNA(VLOOKUP($B18,'2026年1月15日'!$B:$E,4,0),0) | Z18: =Y18-W18 | AA18: =_xlfn.IFNA(VLOOKUP($B18,'2026年1月16日'!$B:$E,4,0),0) | AB18: =AA18-W18 | AC18: =_xlfn.IFNA(VLOOKUP($B18,'2026年1月17日'!$B:$E,4,0),0) | AD18: =AC18-AA18 | AE18: =_xlfn.IFNA(VLOOKUP($B18,'2026年1月19日'!$B:$E,4,0),0) | AF18: =AE18-AC18 | AG18: =_xlfn.IFNA(VLOOKUP($B18,'2026年1月20日'!$B:$E,4,0),0) | AH18: =AG18-AE18 | AI18: =_xlfn.IFNA(VLOOKUP($B18,'2026年1月21日'!$B:$E,4,0),0) | AJ18: =AI18-AG18 | AK18: =_xlfn.IFNA(VLOOKUP($B18,'2026年1月22日'!$B:$E,4,0),0) | AL18: =AK18-AI18 | AM18: =_xlfn.IFNA(VLOOKUP($B18,'2026年1月23日'!$B:$E,4,0),0) | AN18: =AM18-AK18 | AO18: =_xlfn.IFNA(VLOOKUP($B18,'2026年1月24日'!$B:$E,4,0),0) | AP18: =AO18-AM18 | AQ18: =_xlfn.IFNA(VLOOKUP($B18,'2026年1月26日'!$B:$E,4,0),0) | AR18: =AQ18-AO18 | AS18: 1021828 | AU18: 786428 | AV18: -235400 | AW18: 1583128 | AX18: 796700 | AY18: 2245528 | AZ18: 662400 | BA18: 2507028 | BB18: 261500 | BE18: 1842382 | BG18: 424982 | BH18: -1417400 | BI18: 1842382 | BJ18: 1417400 | BK18: 2245528 | BL18: 403146 | BM18: 1954467 | BN18: -291061 | BO18: 174901 | BP18: -1779566 | BQ18: 174901 | BR18: 0 | BS18: 340692 | BT18: 165791 | BU18: 2507028 | BV18: 2166336 | BW18: 2507028 | BX18: 0
B19: B01130 | C19: 中銀國際證券有限公司 | D19: =_xlfn.IFNA(VLOOKUP($B19,'2026年1月2日'!$B:$E,4,0),0) | E19: =_xlfn.IFNA(VLOOKUP($B19,'2026年1月2日'!$B:$E,4,0),0) | F19: =E19-D19 | G19: =_xlfn.IFNA(VLOOKUP($B19,'2026年1月5日'!$B:$E,4,0),0) | H19: =G19-E19 | I19: =_xlfn.IFNA(VLOOKUP($B19,'2026年1月6日'!$B:$E,4,0),0) | J19: =I19-G19 | K19: =_xlfn.IFNA(VLOOKUP($B19,'2026年1月7日'!$B:$E,4,0),0) | L19: =K19-I19 | M19: =_xlfn.IFNA(VLOOKUP($B19,'2026年1月8日'!$B:$E,4,0),0) | N19: =M19-K19 | O19: =_xlfn.IFNA(VLOOKUP($B19,'2026年1月9日'!$B:$E,4,0),0) | P19: =O19-M19 | Q19: =_xlfn.IFNA(VLOOKUP($B19,'2026年1月10日'!$B:$E,4,0),0) | R19: =Q19-O19 | S19: =_xlfn.IFNA(VLOOKUP($B19,'2026年1月12日'!$B:$E,4,0),0) | T19: =S19-Q19 | U19: =_xlfn.IFNA(VLOOKUP($B19,'2026年1月13日'!$B:$E,4,0),0) | V19: =U19-S19 | W19: =_xlfn.IFNA(VLOOKUP($B19,'2026年1月14日'!$B:$E,4,0),0) | X19: =W19-U19 | Y19: =_xlfn.IFNA(VLOOKUP($B19,'2026年1月15日'!$B:$E,4,0),0) | Z19: =Y19-W19 | AA19: =_xlfn.IFNA(VLOOKUP($B19,'2026年1月16日'!$B:$E,4,0),0) | AB19: =AA19-W19 | AC19: =_xlfn.IFNA(VLOOKUP($B19,'2026年1月17日'!$B:$E,4,0),0) | AD19: =AC19-AA19 | AE19: =_xlfn.IFNA(VLOOKUP($B19,'2026年1月19日'!$B:$E,4,0),0) | AF19: =AE19-AC19 | AG19: =_xlfn.IFNA(VLOOKUP($B19,'2026年1月20日'!$B:$E,4,0),0) | AH19: =AG19-AE19 | AI19: =_xlfn.IFNA(VLOOKUP($B19,'2026年1月21日'!$B:$E,4,0),0) | AJ19: =AI19-AG19 | AK19: =_xlfn.IFNA(VLOOKUP($B19,'2026年1月22日'!$B:$E,4,0),0) | AL19: =AK19-AI19 | AM19: =_xlfn.IFNA(VLOOKUP($B19,'2026年1月23日'!$B:$E,4,0),0) | AN19: =AM19-AK19 | AO19: =_xlfn.IFNA(VLOOKUP($B19,'2026年1月24日'!$B:$E,4,0),0) | AP19: =AO19-AM19 | AQ19: =_xlfn.IFNA(VLOOKUP($B19,'2026年1月26日'!$B:$E,4,0),0) | AR19: =AQ19-AO19 | AS19: 5766000 | AU19: 5761500 | AV19: -4500 | AW19: 5769000 | AX19: 7500 | AY19: 5750100 | AZ19: -18900 | BA19: 5812500 | BB19: 62400 | BC19: 5781600 | BD19: -30900 | BE19: 7326000 | BF19: 1544400 | BG19: 6971900 | BH19: -354100 | BI19: 7326000 | BJ19: 354100 | BK19: 5750100 | BL19: -1575900 | BM19: 7298700 | BN19: 1548600 | BO19: 7017600 | BP19: -281100 | BQ19: 7017600 | BR19: 0 | BS19: 7575800 | BT19: 558200 | BU19: 5812500 | BV19: -1763300 | BW19: 5812500 | BX19: 0
B20: B01668 | C20: 耀才證券國際(香港)有限公司 | D20: =_xlfn.IFNA(VLOOKUP($B20,'2026年1月2日'!$B:$E,4,0),0) | E20: =_xlfn.IFNA(VLOOKUP($B20,'2026年1月2日'!$B:$E,4,0),0) | F20: =E20-D20 | G20: =_xlfn.IFNA(VLOOKUP($B20,'2026年1月5日'!$B:$E,4,0),0) | H20: =G20-E20 | I20: =_xlfn.IFNA(VLOOKUP($B20,'2026年1月6日'!$B:$E,4,0),0) | J20: =I20-G20 | K20: =_xlfn.IFNA(VLOOKUP($B20,'2026年1月7日'!$B:$E,4,0),0) | L20: =K20-I20 | M20: =_xlfn.IFNA(VLOOKUP($B20,'2026年1月8日'!$B:$E,4,0),0) | N20: =M20-K20 | O20: =_xlfn.IFNA(VLOOKUP($B20,'2026年1月9日'!$B:$E,4,0),0) | P20: =O20-M20 | Q20: =_xlfn.IFNA(VLOOKUP($B20,'2026年1月10日'!$B:$E,4,0),0) | R20: =Q20-O20 | S20: =_xlfn.IFNA(VLOOKUP($B20,'2026年1月12日'!$B:$E,4,0),0) | T20: =S20-Q20 | U20: =_xlfn.IFNA(VLOOKUP($B20,'2026年1月13日'!$B:$E,4,0),0) | V20: =U20-S20 | W20: =_xlfn.IFNA(VLOOKUP($B20,'2026年1月14日'!$B:$E,4,0),0) | X20: =W20-U20 | Y20: =_xlfn.IFNA(VLOOKUP($B20,'2026年1月15日'!$B:$E,4,0),0) | Z20: =Y20-W20 | AA20: =_xlfn.IFNA(VLOOKUP($B20,'2026年1月16日'!$B:$E,4,0),0) | AB20: =AA20-W20 | AC20: =_xlfn.IFNA(VLOOKUP($B20,'2026年1月17日'!$B:$E,4,0),0) | AD20: =AC20-AA20 | AE20: =_xlfn.IFNA(VLOOKUP($B20,'2026年1月19日'!$B:$E,4,0),0) | AF20: =AE20-AC20 | AG20: =_xlfn.IFNA(VLOOKUP($B20,'2026年1月20日'!$B:$E,4,0),0) | AH20: =AG20-AE20 | AI20: =_xlfn.IFNA(VLOOKUP($B20,'2026年1月21日'!$B:$E,4,0),0) | AJ20: =AI20-AG20 | AK20: =_xlfn.IFNA(VLOOKUP($B20,'2026年1月22日'!$B:$E,4,0),0) | AL20: =AK20-AI20 | AM20: =_xlfn.IFNA(VLOOKUP($B20,'2026年1月23日'!$B:$E,4,0),0) | AN20: =AM20-AK20 | AO20: =_xlfn.IFNA(VLOOKUP($B20,'2026年1月24日'!$B:$E,4,0),0) | AP20: =AO20-AM20 | AQ20: =_xlfn.IFNA(VLOOKUP($B20,'2026年1月26日'!$B:$E,4,0),0) | AR20: =AQ20-AO20 | AS20: 4475600 | AU20: 4472800 | AV20: -2800 | AW20: 4470400 | AX20: -2400 | AY20: 4482700 | AZ20: 12300 | BA20: 4537400 | BB20: 54700 | BE20: 5157900 | BG20: 4490400 | BH20: -667500 | BI20: 5157900 | BJ20: 667500 | BK20: 4482700 | BL20: -675200 | BM20: 4634200 | BN20: 151500 | BO20: 3815700 | BP20: -818500 | BQ20: 3815700 | BR20: 0 | BS20: 4066900 | BT20: 251200 | BU20: 4537400 | BV20: 470500 | BW20: 4537400 | BX20: 0
B21: B01918 | C21: 偉祿亞太證券有限公司 | D21: =_xlfn.IFNA(VLOOKUP($B21,'2026年1月2日'!$B:$E,4,0),0) | E21: =_xlfn.IFNA(VLOOKUP($B21,'2026年1月2日'!$B:$E,4,0),0) | F21: =E21-D21 | G21: =_xlfn.IFNA(VLOOKUP($B21,'2026年1月5日'!$B:$E,4,0),0) | H21: =G21-E21 | I21: =_xlfn.IFNA(VLOOKUP($B21,'2026年1月6日'!$B:$E,4,0),0) | J21: =I21-G21 | K21: =_xlfn.IFNA(VLOOKUP($B21,'2026年1月7日'!$B:$E,4,0),0) | L21: =K21-I21 | M21: =_xlfn.IFNA(VLOOKUP($B21,'2026年1月8日'!$B:$E,4,0),0) | N21: =M21-K21 | O21: =_xlfn.IFNA(VLOOKUP($B21,'2026年1月9日'!$B:$E,4,0),0) | P21: =O21-M21 | Q21: =_xlfn.IFNA(VLOOKUP($B21,'2026年1月10日'!$B:$E,4,0),0) | R21: =Q21-O21 | S21: =_xlfn.IFNA(VLOOKUP($B21,'2026年1月12日'!$B:$E,4,0),0) | T21: =S21-Q21 | U21: =_xlfn.IFNA(VLOOKUP($B21,'2026年1月13日'!$B:$E,4,0),0) | V21: =U21-S21 | W21: =_xlfn.IFNA(VLOOKUP($B21,'2026年1月14日'!$B:$E,4,0),0) | X21: =W21-U21 | Y21: =_xlfn.IFNA(VLOOKUP($B21,'2026年1月15日'!$B:$E,4,0),0) | Z21: =Y21-W21 | AA21: =_xlfn.IFNA(VLOOKUP($B21,'2026年1月16日'!$B:$E,4,0),0) | AB21: =AA21-W21 | AC21: =_xlfn.IFNA(VLOOKUP($B21,'2026年1月17日'!$B:$E,4,0),0) | AD21: =AC21-AA21 | AE21: =_xlfn.IFNA(VLOOKUP($B21,'2026年1月19日'!$B:$E,4,0),0) | AF21: =AE21-AC21 | AG21: =_xlfn.IFNA(VLOOKUP($B21,'2026年1月20日'!$B:$E,4,0),0) | AH21: =AG21-AE21 | AI21: =_xlfn.IFNA(VLOOKUP($B21,'2026年1月21日'!$B:$E,4,0),0) | AJ21: =AI21-AG21 | AK21: =_xlfn.IFNA(VLOOKUP($B21,'2026年1月22日'!$B:$E,4,0),0) | AL21: =AK21-AI21 | AM21: =_xlfn.IFNA(VLOOKUP($B21,'2026年1月23日'!$B:$E,4,0),0) | AN21: =AM21-AK21 | AO21: =_xlfn.IFNA(VLOOKUP($B21,'2026年1月24日'!$B:$E,4,0),0) | AP21: =AO21-AM21 | AQ21: =_xlfn.IFNA(VLOOKUP($B21,'2026年1月26日'!$B:$E,4,0),0) | AR21: =AQ21-AO21 | AS21: 824 | AU21: 824 | AV21: 0 | AW21: 824 | AX21: 0 | AY21: 824 | AZ21: 0 | BA21: 824 | BB21: 0 | BE21: 824 | BG21: 824 | BH21: 0 | BI21: 824 | BJ21: 0 | BK21: 824 | BL21: 0 | BM21: 824 | BN21: 0 | BO21: 342124 | BP21: 341300 | BQ21: 342124 | BR21: 0 | BS21: 824 | BT21: -341300 | BU21: 824 | BV21: 0 | BW21: 824 | BX21: 0
B22: B01086 | C22: 新鴻基投資服務有限公司 | D22: =_xlfn.IFNA(VLOOKUP($B22,'2026年1月2日'!$B:$E,4,0),0) | E22: =_xlfn.IFNA(VLOOKUP($B22,'2026年1月2日'!$B:$E,4,0),0) | F22: =E22-D22 | G22: =_xlfn.IFNA(VLOOKUP($B22,'2026年1月5日'!$B:$E,4,0),0) | H22: =G22-E22 | I22: =_xlfn.IFNA(VLOOKUP($B22,'2026年1月6日'!$B:$E,4,0),0) | J22: =I22-G22 | K22: =_xlfn.IFNA(VLOOKUP($B22,'2026年1月7日'!$B:$E,4,0),0) | L22: =K22-I22 | M22: =_xlfn.IFNA(VLOOKUP($B22,'2026年1月8日'!$B:$E,4,0),0) | N22: =M22-K22 | O22: =_xlfn.IFNA(VLOOKUP($B22,'2026年1月9日'!$B:$E,4,0),0) | P22: =O22-M22 | Q22: =_xlfn.IFNA(VLOOKUP($B22,'2026年1月10日'!$B:$E,4,0),0) | R22: =Q22-O22 | S22: =_xlfn.IFNA(VLOOKUP($B22,'2026年1月12日'!$B:$E,4,0),0) | T22: =S22-Q22 | U22: =_xlfn.IFNA(VLOOKUP($B22,'2026年1月13日'!$B:$E,4,0),0) | V22: =U22-S22 | W22: =_xlfn.IFNA(VLOOKUP($B22,'2026年1月14日'!$B:$E,4,0),0) | X22: =W22-U22 | Y22: =_xlfn.IFNA(VLOOKUP($B22,'2026年1月15日'!$B:$E,4,0),0) | Z22: =Y22-W22 | AA22: =_xlfn.IFNA(VLOOKUP($B22,'2026年1月16日'!$B:$E,4,0),0) | AB22: =AA22-W22 | AC22: =_xlfn.IFNA(VLOOKUP($B22,'2026年1月17日'!$B:$E,4,0),0) | AD22: =AC22-AA22 | AE22: =_xlfn.IFNA(VLOOKUP($B22,'2026年1月19日'!$B:$E,4,0),0) | AF22: =AE22-AC22 | AG22: =_xlfn.IFNA(VLOOKUP($B22,'2026年1月20日'!$B:$E,4,0),0) | AH22: =AG22-AE22 | AI22: =_xlfn.IFNA(VLOOKUP($B22,'2026年1月21日'!$B:$E,4,0),0) | AJ22: =AI22-AG22 | AK22: =_xlfn.IFNA(VLOOKUP($B22,'2026年1月22日'!$B:$E,4,0),0) | AL22: =AK22-AI22 | AM22: =_xlfn.IFNA(VLOOKUP($B22,'2026年1月23日'!$B:$E,4,0),0) | AN22: =AM22-AK22 | AO22: =_xlfn.IFNA(VLOOKUP($B22,'2026年1月24日'!$B:$E,4,0),0) | AP22: =AO22-AM22 | AQ22: =_xlfn.IFNA(VLOOKUP($B22,'2026年1月26日'!$B:$E,4,0),0) | AR22: =AQ22-AO22 | AS22: 1987700 | AU22: 1987700 | AV22: 0 | AW22: 1947700 | AX22: -40000 | AY22: 1939700 | AZ22: -8000 | BA22: 1939700 | BB22: 0 | BE22: 1736000 | BG22: 1404500 | BH22: -331500 | BI22: 1736000 | BJ22: 331500 | BK22: 1939700 | BL22: 203700 | BM22: 1955500 | BN22: 15800 | BO22: 1161200 | BP22: -794300 | BQ22: 1161200 | BR22: 0 | BS22: 1174100 | BT22: 12900 | BU22: 1939700 | BV22: 765600 | BW22: 1939700 | BX22: 0
B23: C00088 | C23: 招商銀行股份有限公司 | D23: =_xlfn.IFNA(VLOOKUP($B23,'2026年1月2日'!$B:$E,4,0),0) | E23: =_xlfn.IFNA(VLOOKUP($B23,'2026年1月2日'!$B:$E,4,0),0) | F23: =E23-D23 | G23: =_xlfn.IFNA(VLOOKUP($B23,'2026年1月5日'!$B:$E,4,0),0) | H23: =G23-E23 | I23: =_xlfn.IFNA(VLOOKUP($B23,'2026年1月6日'!$B:$E,4,0),0) | J23: =I23-G23 | K23: =_xlfn.IFNA(VLOOKUP($B23,'2026年1月7日'!$B:$E,4,0),0) | L23: =K23-I23 | M23: =_xlfn.IFNA(VLOOKUP($B23,'2026年1月8日'!$B:$E,4,0),0) | N23: =M23-K23 | O23: =_xlfn.IFNA(VLOOKUP($B23,'2026年1月9日'!$B:$E,4,0),0) | P23: =O23-M23 | Q23: =_xlfn.IFNA(VLOOKUP($B23,'2026年1月10日'!$B:$E,4,0),0) | R23: =Q23-O23 | S23: =_xlfn.IFNA(VLOOKUP($B23,'2026年1月12日'!$B:$E,4,0),0) | T23: =S23-Q23 | U23: =_xlfn.IFNA(VLOOKUP($B23,'2026年1月13日'!$B:$E,4,0),0) | V23: =U23-S23 | W23: =_xlfn.IFNA(VLOOKUP($B23,'2026年1月14日'!$B:$E,4,0),0) | X23: =W23-U23 | Y23: =_xlfn.IFNA(VLOOKUP($B23,'2026年1月15日'!$B:$E,4,0),0) | Z23: =Y23-W23 | AA23: =_xlfn.IFNA(VLOOKUP($B23,'2026年1月16日'!$B:$E,4,0),0) | AB23: =AA23-W23 | AC23: =_xlfn.IFNA(VLOOKUP($B23,'2026年1月17日'!$B:$E,4,0),0) | AD23: =AC23-AA23 | AE23: =_xlfn.IFNA(VLOOKUP($B23,'2026年1月19日'!$B:$E,4,0),0) | AF23: =AE23-AC23 | AG23: =_xlfn.IFNA(VLOOKUP($B23,'2026年1月20日'!$B:$E,4,0),0) | AH23: =AG23-AE23 | AI23: =_xlfn.IFNA(VLOOKUP($B23,'2026年1月21日'!$B:$E,4,0),0) | AJ23: =AI23-AG23 | AK23: =_xlfn.IFNA(VLOOKUP($B23,'2026年1月22日'!$B:$E,4,0),0) | AL23: =AK23-AI23 | AM23: =_xlfn.IFNA(VLOOKUP($B23,'2026年1月23日'!$B:$E,4,0),0) | AN23: =AM23-AK23 | AO23: =_xlfn.IFNA(VLOOKUP($B23,'2026年1月24日'!$B:$E,4,0),0) | AP23: =AO23-AM23 | AQ23: =_xlfn.IFNA(VLOOKUP($B23,'2026年1月26日'!$B:$E,4,0),0) | AR23: =AQ23-AO23 | AS23: 1355500 | AU23: 1386300 | AV23: 30800 | AW23: 1344300 | AX23: -42000 | AY23: 1358500 | AZ23: 14200 | BA23: 1357700 | BB23: -800 | BE23: 1538100 | BG23: 3644200 | BH23: 2106100 | BI23: 1538100 | BJ23: -2106100 | BK23: 1358500 | BL23: -179600 | BM23: 3704600 | BN23: 2346100 | BO23: 3559700 | BP23: -144900 | BQ23: 3559700 | BR23: 0 | BS23: 3775000 | BT23: 215300 | BU23: 1357700 | BV23: -2417300 | BW23: 1357700 | BX23: 0
B24: C00042 | C24: 招商永隆銀行有限公司 | D24: =_xlfn.IFNA(VLOOKUP($B24,'2026年1月2日'!$B:$E,4,0),0) | E24: =_xlfn.IFNA(VLOOKUP($B24,'2026年1月2日'!$B:$E,4,0),0) | F24: =E24-D24 | G24: =_xlfn.IFNA(VLOOKUP($B24,'2026年1月5日'!$B:$E,4,0),0) | H24: =G24-E24 | I24: =_xlfn.IFNA(VLOOKUP($B24,'2026年1月6日'!$B:$E,4,0),0) | J24: =I24-G24 | K24: =_xlfn.IFNA(VLOOKUP($B24,'2026年1月7日'!$B:$E,4,0),0) | L24: =K24-I24 | M24: =_xlfn.IFNA(VLOOKUP($B24,'2026年1月8日'!$B:$E,4,0),0) | N24: =M24-K24 | O24: =_xlfn.IFNA(VLOOKUP($B24,'2026年1月9日'!$B:$E,4,0),0) | P24: =O24-M24 | Q24: =_xlfn.IFNA(VLOOKUP($B24,'2026年1月10日'!$B:$E,4,0),0) | R24: =Q24-O24 | S24: =_xlfn.IFNA(VLOOKUP($B24,'2026年1月12日'!$B:$E,4,0),0) | T24: =S24-Q24 | U24: =_xlfn.IFNA(VLOOKUP($B24,'2026年1月13日'!$B:$E,4,0),0) | V24: =U24-S24 | W24: =_xlfn.IFNA(VLOOKUP($B24,'2026年1月14日'!$B:$E,4,0),0) | X24: =W24-U24 | Y24: =_xlfn.IFNA(VLOOKUP($B24,'2026年1月15日'!$B:$E,4,0),0) | Z24: =Y24-W24 | AA24: =_xlfn.IFNA(VLOOKUP($B24,'2026年1月16日'!$B:$E,4,0),0) | AB24: =AA24-W24 | AC24: =_xlfn.IFNA(VLOOKUP($B24,'2026年1月17日'!$B:$E,4,0),0) | AD24: =AC24-AA24 | AE24: =_xlfn.IFNA(VLOOKUP($B24,'2026年1月19日'!$B:$E,4,0),0) | AF24: =AE24-AC24 | AG24: =_xlfn.IFNA(VLOOKUP($B24,'2026年1月20日'!$B:$E,4,0),0) | AH24: =AG24-AE24 | AI24: =_xlfn.IFNA(VLOOKUP($B24,'2026年1月21日'!$B:$E,4,0),0) | AJ24: =AI24-AG24 | AK24: =_xlfn.IFNA(VLOOKUP($B24,'2026年1月22日'!$B:$E,4,0),0) | AL24: =AK24-AI24 | AM24: =_xlfn.IFNA(VLOOKUP($B24,'2026年1月23日'!$B:$E,4,0),0) | AN24: =AM24-AK24 | AO24: =_xlfn.IFNA(VLOOKUP($B24,'2026年1月24日'!$B:$E,4,0),0) | AP24: =AO24-AM24 | AQ24: =_xlfn.IFNA(VLOOKUP($B24,'2026年1月26日'!$B:$E,4,0),0) | AR24: =AQ24-AO24 | AS24: 4752200 | AU24: 4751200 | AV24: -1000 | AW24: 4775700 | AX24: 24500 | AY24: 4775800 | AZ24: 100 | BA24: 4750100 | BB24: -25700 | BC24: 4748400 | BD24: -1700 | BE24: 5286600 | BF24: 538200 | BG24: 5337900 | BH24: 51300 | BI24: 5286600 | BJ24: -51300 | BK24: 4775800 | BL24: -510800 | BM24: 5866100 | BN24: 1090300 | BO24: 4991200 | BP24: -874900 | BQ24: 4991200 | BR24: 0 | BS24: 5232500 | BT24: 241300 | BU24: 4750100 | BV24: -482400 | BW24: 4750100 | BX24: 0
B25: B01829 | C25: 華泰金融控股(香港)有限公司 | D25: =_xlfn.IFNA(VLOOKUP($B25,'2026年1月2日'!$B:$E,4,0),0) | E25: =_xlfn.IFNA(VLOOKUP($B25,'2026年1月2日'!$B:$E,4,0),0) | F25: =E25-D25 | G25: =_xlfn.IFNA(VLOOKUP($B25,'2026年1月5日'!$B:$E,4,0),0) | H25: =G25-E25 | I25: =_xlfn.IFNA(VLOOKUP($B25,'2026年1月6日'!$B:$E,4,0),0) | J25: =I25-G25 | K25: =_xlfn.IFNA(VLOOKUP($B25,'2026年1月7日'!$B:$E,4,0),0) | L25: =K25-I25 | M25: =_xlfn.IFNA(VLOOKUP($B25,'2026年1月8日'!$B:$E,4,0),0) | N25: =M25-K25 | O25: =_xlfn.IFNA(VLOOKUP($B25,'2026年1月9日'!$B:$E,4,0),0) | P25: =O25-M25 | Q25: =_xlfn.IFNA(VLOOKUP($B25,'2026年1月10日'!$B:$E,4,0),0) | R25: =Q25-O25 | S25: =_xlfn.IFNA(VLOOKUP($B25,'2026年1月12日'!$B:$E,4,0),0) | T25: =S25-Q25 | U25: =_xlfn.IFNA(VLOOKUP($B25,'2026年1月13日'!$B:$E,4,0),0) | V25: =U25-S25 | W25: =_xlfn.IFNA(VLOOKUP($B25,'2026年1月14日'!$B:$E,4,0),0) | X25: =W25-U25 | Y25: =_xlfn.IFNA(VLOOKUP($B25,'2026年1月15日'!$B:$E,4,0),0) | Z25: =Y25-W25 | AA25: =_xlfn.IFNA(VLOOKUP($B25,'2026年1月16日'!$B:$E,4,0),0) | AB25: =AA25-W25 | AC25: =_xlfn.IFNA(VLOOKUP($B25,'2026年1月17日'!$B:$E,4,0),0) | AD25: =AC25-AA25 | AE25: =_xlfn.IFNA(VLOOKUP($B25,'2026年1月19日'!$B:$E,4,0),0) | AF25: =AE25-AC25 | AG25: =_xlfn.IFNA(VLOOKUP($B25,'2026年1月20日'!$B:$E,4,0),0) | AH25: =AG25-AE25 | AI25: =_xlfn.IFNA(VLOOKUP($B25,'2026年1月21日'!$B:$E,4,0),0) | AJ25: =AI25-AG25 | AK25: =_xlfn.IFNA(VLOOKUP($B25,'2026年1月22日'!$B:$E,4,0),0) | AL25: =AK25-AI25 | AM25: =_xlfn.IFNA(VLOOKUP($B25,'2026年1月23日'!$B:$E,4,0),0) | AN25: =AM25-AK25 | AO25: =_xlfn.IFNA(VLOOKUP($B25,'2026年1月24日'!$B:$E,4,0),0) | AP25: =AO25-AM25 | AQ25: =_xlfn.IFNA(VLOOKUP($B25,'2026年1月26日'!$B:$E,4,0),0) | AR25: =AQ25-AO25 | AS25: 1998900 | AU25: 2002400 | AV25: 3500 | AW25: 2000500 | AX25: -1900 | AY25: 1998900 | AZ25: -1600 | BA25: 1998900 | BB25: 0 | BE25: 1869000 | BG25: 2154400 | BH25: 285400 | BI25: 1869000 | BJ25: -285400 | BK25: 1998900 | BL25: 129900 | BM25: 1747000 | BN25: -251900 | BO25: 1734100 | BP25: -12900 | BQ25: 1734100 | BR25: 0 | BS25: 2014700 | BT25: 280600 | BU25: 1998900 | BV25: -15800 | BW25: 1998900 | BX25: 0
B26: B01929 | C26: 中國銀河國際證券(香港)有限公司 | D26: =_xlfn.IFNA(VLOOKUP($B26,'2026年1月2日'!$B:$E,4,0),0) | E26: =_xlfn.IFNA(VLOOKUP($B26,'2026年1月2日'!$B:$E,4,0),0) | F26: =E26-D26 | G26: =_xlfn.IFNA(VLOOKUP($B26,'2026年1月5日'!$B:$E,4,0),0) | H26: =G26-E26 | I26: =_xlfn.IFNA(VLOOKUP($B26,'2026年1月6日'!$B:$E,4,0),0) | J26: =I26-G26 | K26: =_xlfn.IFNA(VLOOKUP($B26,'2026年1月7日'!$B:$E,4,0),0) | L26: =K26-I26 | M26: =_xlfn.IFNA(VLOOKUP($B26,'2026年1月8日'!$B:$E,4,0),0) | N26: =M26-K26 | O26: =_xlfn.IFNA(VLOOKUP($B26,'2026年1月9日'!$B:$E,4,0),0) | P26: =O26-M26 | Q26: =_xlfn.IFNA(VLOOKUP($B26,'2026年1月10日'!$B:$E,4,0),0) | R26: =Q26-O26 | S26: =_xlfn.IFNA(VLOOKUP($B26,'2026年1月12日'!$B:$E,4,0),0) | T26: =S26-Q26 | U26: =_xlfn.IFNA(VLOOKUP($B26,'2026年1月13日'!$B:$E,4,0),0) | V26: =U26-S26 | W26: =_xlfn.IFNA(VLOOKUP($B26,'2026年1月14日'!$B:$E,4,0),0) | X26: =W26-U26 | Y26: =_xlfn.IFNA(VLOOKUP($B26,'2026年1月15日'!$B:$E,4,0),0) | Z26: =Y26-W26 | AA26: =_xlfn.IFNA(VLOOKUP($B26,'2026年1月16日'!$B:$E,4,0),0) | AB26: =AA26-W26 | AC26: =_xlfn.IFNA(VLOOKUP($B26,'2026年1月17日'!$B:$E,4,0),0) | AD26: =AC26-AA26 | AE26: =_xlfn.IFNA(VLOOKUP($B26,'2026年1月19日'!$B:$E,4,0),0) | AF26: =AE26-AC26 | AG26: =_xlfn.IFNA(VLOOKUP($B26,'2026年1月20日'!$B:$E,4,0),0) | AH26: =AG26-AE26 | AI26: =_xlfn.IFNA(VLOOKUP($B26,'2026年1月21日'!$B:$E,4,0),0) | AJ26: =AI26-AG26 | AK26: =_xlfn.IFNA(VLOOKUP($B26,'2026年1月22日'!$B:$E,4,0),0) | AL26: =AK26-AI26 | AM26: =_xlfn.IFNA(VLOOKUP($B26,'2026年1月23日'!$B:$E,4,0),0) | AN26: =AM26-AK26 | AO26: =_xlfn.IFNA(VLOOKUP($B26,'2026年1月24日'!$B:$E,4,0),0) | AP26: =AO26-AM26 | AQ26: =_xlfn.IFNA(VLOOKUP($B26,'2026年1月26日'!$B:$E,4,0),0) | AR26: =AQ26-AO26 | AS26: 149800 | AU26: 149800 | AV26: 0 | AW26: 149800 | AX26: 0 | AY26: 149800 | AZ26: 0 | BA26: 129800 | BB26: -20000 | BE26: 302700 | BG26: 272800 | BH26: -29900 | BI26: 302700 | BJ26: 29900 | BK26: 149800 | BL26: -152900 | BM26: 551800 | BN26: 402000 | BO26: 220000 | BP26: -331800 | BQ26: 220000 | BR26: 0 | BS26: 168800 | BT26: -51200 | BU26: 129800 | BV26: -39000 | BW26: 129800 | BX26: 0
B27: B01727 | C27: 工銀亞洲証券有限公司 | D27: =_xlfn.IFNA(VLOOKUP($B27,'2026年1月2日'!$B:$E,4,0),0) | E27: =_xlfn.IFNA(VLOOKUP($B27,'2026年1月2日'!$B:$E,4,0),0) | F27: =E27-D27 | G27: =_xlfn.IFNA(VLOOKUP($B27,'2026年1月5日'!$B:$E,4,0),0) | H27: =G27-E27 | I27: =_xlfn.IFNA(VLOOKUP($B27,'2026年1月6日'!$B:$E,4,0),0) | J27: =I27-G27 | K27: =_xlfn.IFNA(VLOOKUP($B27,'2026年1月7日'!$B:$E,4,0),0) | L27: =K27-I27 | M27: =_xlfn.IFNA(VLOOKUP($B27,'2026年1月8日'!$B:$E,4,0),0) | N27: =M27-K27 | O27: =_xlfn.IFNA(VLOOKUP($B27,'2026年1月9日'!$B:$E,4,0),0) | P27: =O27-M27 | Q27: =_xlfn.IFNA(VLOOKUP($B27,'2026年1月10日'!$B:$E,4,0),0) | R27: =Q27-O27 | S27: =_xlfn.IFNA(VLOOKUP($B27,'2026年1月12日'!$B:$E,4,0),0) | T27: =S27-Q27 | U27: =_xlfn.IFNA(VLOOKUP($B27,'2026年1月13日'!$B:$E,4,0),0) | V27: =U27-S27 | W27: =_xlfn.IFNA(VLOOKUP($B27,'2026年1月14日'!$B:$E,4,0),0) | X27: =W27-U27 | Y27: =_xlfn.IFNA(VLOOKUP($B27,'2026年1月15日'!$B:$E,4,0),0) | Z27: =Y27-W27 | AA27: =_xlfn.IFNA(VLOOKUP($B27,'2026年1月16日'!$B:$E,4,0),0) | AB27: =AA27-W27 | AC27: =_xlfn.IFNA(VLOOKUP($B27,'2026年1月17日'!$B:$E,4,0),0) | AD27: =AC27-AA27 | AE27: =_xlfn.IFNA(VLOOKUP($B27,'2026年1月19日'!$B:$E,4,0),0) | AF27: =AE27-AC27 | AG27: =_xlfn.IFNA(VLOOKUP($B27,'2026年1月20日'!$B:$E,4,0),0) | AH27: =AG27-AE27 | AI27: =_xlfn.IFNA(VLOOKUP($B27,'2026年1月21日'!$B:$E,4,0),0) | AJ27: =AI27-AG27 | AK27: =_xlfn.IFNA(VLOOKUP($B27,'2026年1月22日'!$B:$E,4,0),0) | AL27: =AK27-AI27 | AM27: =_xlfn.IFNA(VLOOKUP($B27,'2026年1月23日'!$B:$E,4,0),0) | AN27: =AM27-AK27 | AO27: =_xlfn.IFNA(VLOOKUP($B27,'2026年1月24日'!$B:$E,4,0),0) | AP27: =AO27-AM27 | AQ27: =_xlfn.IFNA(VLOOKUP($B27,'2026年1月26日'!$B:$E,4,0),0) | AR27: =AQ27-AO27 | AS27: 2723500 | AU27: 2683400 | AV27: -40100 | AW27: 2674400 | AX27: -9000 | AY27: 2704300 | AZ27: 29900 | BA27: 2652700 | BB27: -51600 | BE27: 3075600 | BG27: 2663900 | BH27: -411700 | BI27: 3075600 | BJ27: 411700 | BK27: 2704300 | BL27: -371300 | BM27: 2541200 | BN27: -163100 | BO27: 2575700 | BP27: 34500 | BQ27: 2575700 | BR27: 0 | BS27: 2844800 | BT27: 269100 | BU27: 2652700 | BV27: -192100 | BW27: 2652700 | BX27: 0
B28: C00002 | C28: 交通銀行信託有限公司 | D28: =_xlfn.IFNA(VLOOKUP($B28,'2026年1月2日'!$B:$E,4,0),0) | E28: =_xlfn.IFNA(VLOOKUP($B28,'2026年1月2日'!$B:$E,4,0),0) | F28: =E28-D28 | G28: =_xlfn.IFNA(VLOOKUP($B28,'2026年1月5日'!$B:$E,4,0),0) | H28: =G28-E28 | I28: =_xlfn.IFNA(VLOOKUP($B28,'2026年1月6日'!$B:$E,4,0),0) | J28: =I28-G28 | K28: =_xlfn.IFNA(VLOOKUP($B28,'2026年1月7日'!$B:$E,4,0),0) | L28: =K28-I28 | M28: =_xlfn.IFNA(VLOOKUP($B28,'2026年1月8日'!$B:$E,4,0),0) | N28: =M28-K28 | O28: =_xlfn.IFNA(VLOOKUP($B28,'2026年1月9日'!$B:$E,4,0),0) | P28: =O28-M28 | Q28: =_xlfn.IFNA(VLOOKUP($B28,'2026年1月10日'!$B:$E,4,0),0) | R28: =Q28-O28 | S28: =_xlfn.IFNA(VLOOKUP($B28,'2026年1月12日'!$B:$E,4,0),0) | T28: =S28-Q28 | U28: =_xlfn.IFNA(VLOOKUP($B28,'2026年1月13日'!$B:$E,4,0),0) | V28: =U28-S28 | W28: =_xlfn.IFNA(VLOOKUP($B28,'2026年1月14日'!$B:$E,4,0),0) | X28: =W28-U28 | Y28: =_xlfn.IFNA(VLOOKUP($B28,'2026年1月15日'!$B:$E,4,0),0) | Z28: =Y28-W28 | AA28: =_xlfn.IFNA(VLOOKUP($B28,'2026年1月16日'!$B:$E,4,0),0) | AB28: =AA28-W28 | AC28: =_xlfn.IFNA(VLOOKUP($B28,'2026年1月17日'!$B:$E,4,0),0) | AD28: =AC28-AA28 | AE28: =_xlfn.IFNA(VLOOKUP($B28,'2026年1月19日'!$B:$E,4,0),0) | AF28: =AE28-AC28 | AG28: =_xlfn.IFNA(VLOOKUP($B28,'2026年1月20日'!$B:$E,4,0),0) | AH28: =AG28-AE28 | AI28: =_xlfn.IFNA(VLOOKUP($B28,'2026年1月21日'!$B:$E,4,0),0) | AJ28: =AI28-AG28 | AK28: =_xlfn.IFNA(VLOOKUP($B28,'2026年1月22日'!$B:$E,4,0),0) | AL28: =AK28-AI28 | AM28: =_xlfn.IFNA(VLOOKUP($B28,'2026年1月23日'!$B:$E,4,0),0) | AN28: =AM28-AK28 | AO28: =_xlfn.IFNA(VLOOKUP($B28,'2026年1月24日'!$B:$E,4,0),0) | AP28: =AO28-AM28 | AQ28: =_xlfn.IFNA(VLOOKUP($B28,'2026年1月26日'!$B:$E,4,0),0) | AR28: =AQ28-AO28 | AS28: 1573400 | AU28: 1573400 | AV28: 0 | AW28: 1577400 | AX28: 4000 | AY28: 1583700 | AZ28: 6300 | BA28: 1587600 | BB28: 3900 | BE28: 2022400 | BG28: 1551000 | BH28: -471400 | BI28: 2022400 | BJ28: 471400 | BK28: 1583700 | BL28: -438700 | BM28: 1587900 | BN28: 4200 | BO28: 1797900 | BP28: 210000 | BQ28: 1797900 | BR28: 0 | BS28: 1828100 | BT28: 30200 | BU28: 1587600 | BV28: -240500 | BW28: 1587600 | BX28: 0
B29: B01345 | C29: 輝立証券(香港)有限公司 | D29: =_xlfn.IFNA(VLOOKUP($B29,'2026年1月2日'!$B:$E,4,0),0) | E29: =_xlfn.IFNA(VLOOKUP($B29,'2026年1月2日'!$B:$E,4,0),0) | F29: =E29-D29 | G29: =_xlfn.IFNA(VLOOKUP($B29,'2026年1月5日'!$B:$E,4,0),0) | H29: =G29-E29 | I29: =_xlfn.IFNA(VLOOKUP($B29,'2026年1月6日'!$B:$E,4,0),0) | J29: =I29-G29 | K29: =_xlfn.IFNA(VLOOKUP($B29,'2026年1月7日'!$B:$E,4,0),0) | L29: =K29-I29 | M29: =_xlfn.IFNA(VLOOKUP($B29,'2026年1月8日'!$B:$E,4,0),0) | N29: =M29-K29 | O29: =_xlfn.IFNA(VLOOKUP($B29,'2026年1月9日'!$B:$E,4,0),0) | P29: =O29-M29 | Q29: =_xlfn.IFNA(VLOOKUP($B29,'2026年1月10日'!$B:$E,4,0),0) | R29: =Q29-O29 | S29: =_xlfn.IFNA(VLOOKUP($B29,'2026年1月12日'!$B:$E,4,0),0) | T29: =S29-Q29 | U29: =_xlfn.IFNA(VLOOKUP($B29,'2026年1月13日'!$B:$E,4,0),0) | V29: =U29-S29 | W29: =_xlfn.IFNA(VLOOKUP($B29,'2026年1月14日'!$B:$E,4,0),0) | X29: =W29-U29 | Y29: =_xlfn.IFNA(VLOOKUP($B29,'2026年1月15日'!$B:$E,4,0),0) | Z29: =Y29-W29 | AA29: =_xlfn.IFNA(VLOOKUP($B29,'2026年1月16日'!$B:$E,4,0),0) | AB29: =AA29-W29 | AC29: =_xlfn.IFNA(VLOOKUP($B29,'2026年1月17日'!$B:$E,4,0),0) | AD29: =AC29-AA29 | AE29: =_xlfn.IFNA(VLOOKUP($B29,'2026年1月19日'!$B:$E,4,0),0) | AF29: =AE29-AC29 | AG29: =_xlfn.IFNA(VLOOKUP($B29,'2026年1月20日'!$B:$E,4,0),0) | AH29: =AG29-AE29 | AI29: =_xlfn.IFNA(VLOOKUP($B29,'2026年1月21日'!$B:$E,4,0),0) | AJ29: =AI29-AG29 | AK29: =_xlfn.IFNA(VLOOKUP($B29,'2026年1月22日'!$B:$E,4,0),0) | AL29: =AK29-AI29 | AM29: =_xlfn.IFNA(VLOOKUP($B29,'2026年1月23日'!$B:$E,4,0),0) | AN29: =AM29-AK29 | AO29: =_xlfn.IFNA(VLOOKUP($B29,'2026年1月24日'!$B:$E,4,0),0) | AP29: =AO29-AM29 | AQ29: =_xlfn.IFNA(VLOOKUP($B29,'2026年1月26日'!$B:$E,4,0),0) | AR29: =AQ29-AO29 | AS29: 2719400 | AU29: 2710100 | AV29: -9300 | AW29: 2714000 | AX29: 3900 | AY29: 2714900 | AZ29: 900 | BA29: 2669900 | BB29: -45000 | BE29: 2775200 | BG29: 2733600 | BH29: -41600 | BI29: 2775200 | BJ29: 41600 | BK29: 2714900 | BL29: -60300 | BM29: 2914700 | BN29: 199800 | BO29: 2272100 | BP29: -642600 | BQ29: 2272100 | BR29: 0 | BS29: 2359700 | BT29: 87600 | BU29: 2669900 | BV29: 310200 | BW29: 2669900 | BX29: 0
B30: C00028 | C30: 南洋商業銀行有限公司 | D30: =_xlfn.IFNA(VLOOKUP($B30,'2026年1月2日'!$B:$E,4,0),0) | E30: =_xlfn.IFNA(VLOOKUP($B30,'2026年1月2日'!$B:$E,4,0),0) | F30: =E30-D30 | G30: =_xlfn.IFNA(VLOOKUP($B30,'2026年1月5日'!$B:$E,4,0),0) | H30: =G30-E30 | I30: =_xlfn.IFNA(VLOOKUP($B30,'2026年1月6日'!$B:$E,4,0),0) | J30: =I30-G30 | K30: =_xlfn.IFNA(VLOOKUP($B30,'2026年1月7日'!$B:$E,4,0),0) | L30: =K30-I30 | M30: =_xlfn.IFNA(VLOOKUP($B30,'2026年1月8日'!$B:$E,4,0),0) | N30: =M30-K30 | O30: =_xlfn.IFNA(VLOOKUP($B30,'2026年1月9日'!$B:$E,4,0),0) | P30: =O30-M30 | Q30: =_xlfn.IFNA(VLOOKUP($B30,'2026年1月10日'!$B:$E,4,0),0) | R30: =Q30-O30 | S30: =_xlfn.IFNA(VLOOKUP($B30,'2026年1月12日'!$B:$E,4,0),0) | T30: =S30-Q30 | U30: =_xlfn.IFNA(VLOOKUP($B30,'2026年1月13日'!$B:$E,4,0),0) | V30: =U30-S30 | W30: =_xlfn.IFNA(VLOOKUP($B30,'2026年1月14日'!$B:$E,4,0),0) | X30: =W30-U30 | Y30: =_xlfn.IFNA(VLOOKUP($B30,'2026年1月15日'!$B:$E,4,0),0) | Z30: =Y30-W30 | AA30: =_xlfn.IFNA(VLOOKUP($B30,'2026年1月16日'!$B:$E,4,0),0) | AB30: =AA30-W30 | AC30: =_xlfn.IFNA(VLOOKUP($B30,'2026年1月17日'!$B:$E,4,0),0) | AD30: =AC30-AA30 | AE30: =_xlfn.IFNA(VLOOKUP($B30,'2026年1月19日'!$B:$E,4,0),0) | AF30: =AE30-AC30 | AG30: =_xlfn.IFNA(VLOOKUP($B30,'2026年1月20日'!$B:$E,4,0),0) | AH30: =AG30-AE30 | AI30: =_xlfn.IFNA(VLOOKUP($B30,'2026年1月21日'!$B:$E,4,0),0) | AJ30: =AI30-AG30 | AK30: =_xlfn.IFNA(VLOOKUP($B30,'2026年1月22日'!$B:$E,4,0),0) | AL30: =AK30-AI30 | AM30: =_xlfn.IFNA(VLOOKUP($B30,'2026年1月23日'!$B:$E,4,0),0) | AN30: =AM30-AK30 | AO30: =_xlfn.IFNA(VLOOKUP($B30,'2026年1月24日'!$B:$E,4,0),0) | AP30: =AO30-AM30 | AQ30: =_xlfn.IFNA(VLOOKUP($B30,'2026年1月26日'!$B:$E,4,0),0) | AR30: =AQ30-AO30 | AS30: 1094200 | AU30: 1091200 | AV30: -3000 | AW30: 1091200 | AX30: 0 | AY30: 1091200 | AZ30: 0 | BA30: 1089200 | BB30: -2000 | BE30: 1194600 | BG30: 1271000 | BH30: 76400 | BI30: 1194600 | BJ30: -76400 | BK30: 1091200 | BL30: -103400 | BM30: 1364600 | BN30: 273400 | BO30: 1300100 | BP30: -64500 | BQ30: 1300100 | BR30: 0 | BS30: 1340200 | BT30: 40100 | BU30: 1089200 | BV30: -251000 | BW30: 1089200 | BX30: 0
B31: B01890 | C31: 國信證券(香港)經紀有限公司 | D31: =_xlfn.IFNA(VLOOKUP($B31,'2026年1月2日'!$B:$E,4,0),0) | E31: =_xlfn.IFNA(VLOOKUP($B31,'2026年1月2日'!$B:$E,4,0),0) | F31: =E31-D31 | G31: =_xlfn.IFNA(VLOOKUP($B31,'2026年1月5日'!$B:$E,4,0),0) | H31: =G31-E31 | I31: =_xlfn.IFNA(VLOOKUP($B31,'2026年1月6日'!$B:$E,4,0),0) | J31: =I31-G31 | K31: =_xlfn.IFNA(VLOOKUP($B31,'2026年1月7日'!$B:$E,4,0),0) | L31: =K31-I31 | M31: =_xlfn.IFNA(VLOOKUP($B31,'2026年1月8日'!$B:$E,4,0),0) | N31: =M31-K31 | O31: =_xlfn.IFNA(VLOOKUP($B31,'2026年1月9日'!$B:$E,4,0),0) | P31: =O31-M31 | Q31: =_xlfn.IFNA(VLOOKUP($B31,'2026年1月10日'!$B:$E,4,0),0) | R31: =Q31-O31 | S31: =_xlfn.IFNA(VLOOKUP($B31,'2026年1月12日'!$B:$E,4,0),0) | T31: =S31-Q31 | U31: =_xlfn.IFNA(VLOOKUP($B31,'2026年1月13日'!$B:$E,4,0),0) | V31: =U31-S31 | W31: =_xlfn.IFNA(VLOOKUP($B31,'2026年1月14日'!$B:$E,4,0),0) | X31: =W31-U31 | Y31: =_xlfn.IFNA(VLOOKUP($B31,'2026年1月15日'!$B:$E,4,0),0) | Z31: =Y31-W31 | AA31: =_xlfn.IFNA(VLOOKUP($B31,'2026年1月16日'!$B:$E,4,0),0) | AB31: =AA31-W31 | AC31: =_xlfn.IFNA(VLOOKUP($B31,'2026年1月17日'!$B:$E,4,0),0) | AD31: =AC31-AA31 | AE31: =_xlfn.IFNA(VLOOKUP($B31,'2026年1月19日'!$B:$E,4,0),0) | AF31: =AE31-AC31 | AG31: =_xlfn.IFNA(VLOOKUP($B31,'2026年1月20日'!$B:$E,4,0),0) | AH31: =AG31-AE31 | AI31: =_xlfn.IFNA(VLOOKUP($B31,'2026年1月21日'!$B:$E,4,0),0) | AJ31: =AI31-AG31 | AK31: =_xlfn.IFNA(VLOOKUP($B31,'2026年1月22日'!$B:$E,4,0),0) | AL31: =AK31-AI31 | AM31: =_xlfn.IFNA(VLOOKUP($B31,'2026年1月23日'!$B:$E,4,0),0) | AN31: =AM31-AK31 | AO31: =_xlfn.IFNA(VLOOKUP($B31,'2026年1月24日'!$B:$E,4,0),0) | AP31: =AO31-AM31 | AQ31: =_xlfn.IFNA(VLOOKUP($B31,'2026年1月26日'!$B:$E,4,0),0) | AR31: =AQ31-AO31 | AS31: 887200 | AU31: 895200 | AV31: 8000 | AW31: 887200 | AX31: -8000 | AY31: 878100 | AZ31: -9100 | BA31: 874700 | BB31: -3400 | BE31: 836800 | BG31: 961000 | BH31: 124200 | BI31: 836800 | BJ31: -124200 | BK31: 878100 | BL31: 41300 | BM31: 668000 | BN31: -210100 | BO31: 1120600 | BP31: 452600 | BQ31: 1120600 | BR31: 0 | BS31: 942600 | BT31: -178000 | BU31: 874700 | BV31: -67900 | BW31: 874700 | BX31: 0
B32: B01143 | C32: 海通國際證券有限公司 | D32: =_xlfn.IFNA(VLOOKUP($B32,'2026年1月2日'!$B:$E,4,0),0) | E32: =_xlfn.IFNA(VLOOKUP($B32,'2026年1月2日'!$B:$E,4,0),0) | F32: =E32-D32 | G32: =_xlfn.IFNA(VLOOKUP($B32,'2026年1月5日'!$B:$E,4,0),0) | H32: =G32-E32 | I32: =_xlfn.IFNA(VLOOKUP($B32,'2026年1月6日'!$B:$E,4,0),0) | J32: =I32-G32 | K32: =_xlfn.IFNA(VLOOKUP($B32,'2026年1月7日'!$B:$E,4,0),0) | L32: =K32-I32 | M32: =_xlfn.IFNA(VLOOKUP($B32,'2026年1月8日'!$B:$E,4,0),0) | N32: =M32-K32 | O32: =_xlfn.IFNA(VLOOKUP($B32,'2026年1月9日'!$B:$E,4,0),0) | P32: =O32-M32 | Q32: =_xlfn.IFNA(VLOOKUP($B32,'2026年1月10日'!$B:$E,4,0),0) | R32: =Q32-O32 | S32: =_xlfn.IFNA(VLOOKUP($B32,'2026年1月12日'!$B:$E,4,0),0) | T32: =S32-Q32 | U32: =_xlfn.IFNA(VLOOKUP($B32,'2026年1月13日'!$B:$E,4,0),0) | V32: =U32-S32 | W32: =_xlfn.IFNA(VLOOKUP($B32,'2026年1月14日'!$B:$E,4,0),0) | X32: =W32-U32 | Y32: =_xlfn.IFNA(VLOOKUP($B32,'2026年1月15日'!$B:$E,4,0),0) | Z32: =Y32-W32 | AA32: =_xlfn.IFNA(VLOOKUP($B32,'2026年1月16日'!$B:$E,4,0),0) | AB32: =AA32-W32 | AC32: =_xlfn.IFNA(VLOOKUP($B32,'2026年1月17日'!$B:$E,4,0),0) | AD32: =AC32-AA32 | AE32: =_xlfn.IFNA(VLOOKUP($B32,'2026年1月19日'!$B:$E,4,0),0) | AF32: =AE32-AC32 | AG32: =_xlfn.IFNA(VLOOKUP($B32,'2026年1月20日'!$B:$E,4,0),0) | AH32: =AG32-AE32 | AI32: =_xlfn.IFNA(VLOOKUP($B32,'2026年1月21日'!$B:$E,4,0),0) | AJ32: =AI32-AG32 | AK32: =_xlfn.IFNA(VLOOKUP($B32,'2026年1月22日'!$B:$E,4,0),0) | AL32: =AK32-AI32 | AM32: =_xlfn.IFNA(VLOOKUP($B32,'2026年1月23日'!$B:$E,4,0),0) | AN32: =AM32-AK32 | AO32: =_xlfn.IFNA(VLOOKUP($B32,'2026年1月24日'!$B:$E,4,0),0) | AP32: =AO32-AM32 | AQ32: =_xlfn.IFNA(VLOOKUP($B32,'2026年1月26日'!$B:$E,4,0),0) | AR32: =AQ32-AO32 | AS32: 782000 | AU32: 784500 | AV32: 2500 | AW32: 867500 | AX32: 83000 | AY32: 854500 | AZ32: -13000 | BA32: 849500 | BB32: -5000 | BE32: 551900 | BG32: 902600 | BH32: 350700 | BI32: 551900 | BJ32: -350700 | BK32: 854500 | BL32: 302600 | BM32: 1129300 | BN32: 274800 | BO32: 1085100 | BP32: -44200 | BQ32: 1085100 | BR32: 0 | BS32: 757300 | BT32: -327800 | BU32: 849500 | BV32: 92200 | BW32: 849500 | BX32: 0
B33: B01353 | C33: 大華繼顯(香港)有限公司 | D33: =_xlfn.IFNA(VLOOKUP($B33,'2026年1月2日'!$B:$E,4,0),0) | E33: =_xlfn.IFNA(VLOOKUP($B33,'2026年1月2日'!$B:$E,4,0),0) | F33: =E33-D33 | G33: =_xlfn.IFNA(VLOOKUP($B33,'2026年1月5日'!$B:$E,4,0),0) | H33: =G33-E33 | I33: =_xlfn.IFNA(VLOOKUP($B33,'2026年1月6日'!$B:$E,4,0),0) | J33: =I33-G33 | K33: =_xlfn.IFNA(VLOOKUP($B33,'2026年1月7日'!$B:$E,4,0),0) | L33: =K33-I33 | M33: =_xlfn.IFNA(VLOOKUP($B33,'2026年1月8日'!$B:$E,4,0),0) | N33: =M33-K33 | O33: =_xlfn.IFNA(VLOOKUP($B33,'2026年1月9日'!$B:$E,4,0),0) | P33: =O33-M33 | Q33: =_xlfn.IFNA(VLOOKUP($B33,'2026年1月10日'!$B:$E,4,0),0) | R33: =Q33-O33 | S33: =_xlfn.IFNA(VLOOKUP($B33,'2026年1月12日'!$B:$E,4,0),0) | T33: =S33-Q33 | U33: =_xlfn.IFNA(VLOOKUP($B33,'2026年1月13日'!$B:$E,4,0),0) | V33: =U33-S33 | W33: =_xlfn.IFNA(VLOOKUP($B33,'2026年1月14日'!$B:$E,4,0),0) | X33: =W33-U33 | Y33: =_xlfn.IFNA(VLOOKUP($B33,'2026年1月15日'!$B:$E,4,0),0) | Z33: =Y33-W33 | AA33: =_xlfn.IFNA(VLOOKUP($B33,'2026年1月16日'!$B:$E,4,0),0) | AB33: =AA33-W33 | AC33: =_xlfn.IFNA(VLOOKUP($B33,'2026年1月17日'!$B:$E,4,0),0) | AD33: =AC33-AA33 | AE33: =_xlfn.IFNA(VLOOKUP($B33,'2026年1月19日'!$B:$E,4,0),0) | AF33: =AE33-AC33 | AG33: =_xlfn.IFNA(VLOOKUP($B33,'2026年1月20日'!$B:$E,4,0),0) | AH33: =AG33-AE33 | AI33: =_xlfn.IFNA(VLOOKUP($B33,'2026年1月21日'!$B:$E,4,0),0) | AJ33: =AI33-AG33 | AK33: =_xlfn.IFNA(VLOOKUP($B33,'2026年1月22日'!$B:$E,4,0),0) | AL33: =AK33-AI33 | AM33: =_xlfn.IFNA(VLOOKUP($B33,'2026年1月23日'!$B:$E,4,0),0) | AN33: =AM33-AK33 | AO33: =_xlfn.IFNA(VLOOKUP($B33,'2026年1月24日'!$B:$E,4,0),0) | AP33: =AO33-AM33 | AQ33: =_xlfn.IFNA(VLOOKUP($B33,'2026年1月26日'!$B:$E,4,0),0) | AR33: =AQ33-AO33 | AS33: 3086700 | AU33: 3106700 | AV33: 20000 | AW33: 3106700 | AX33: 0 | AY33: 3126700 | AZ33: 20000 | BA33: 3126700 | BB33: 0 | BE33: 3118700 | BG33: 2282300 | BH33: -836400 | BI33: 3118700 | BJ33: 836400 | BK33: 3126700 | BL33: 8000 | BM33: 3525600 | BN33: 398900 | BO33: 2034100 | BP33: -1491500 | BQ33: 2034100 | BR33: 0 | BS33: 2423800 | BT33: 389700 | BU33: 3126700 | BV33: 702900 | BW33: 3126700 | BX33: 0
B34: B01089 | C34: 匯豐金融證券(香港)有限公司 | D34: =_xlfn.IFNA(VLOOKUP($B34,'2026年1月2日'!$B:$E,4,0),0) | E34: =_xlfn.IFNA(VLOOKUP($B34,'2026年1月2日'!$B:$E,4,0),0) | F34: =E34-D34 | G34: =_xlfn.IFNA(VLOOKUP($B34,'2026年1月5日'!$B:$E,4,0),0) | H34: =G34-E34 | I34: =_xlfn.IFNA(VLOOKUP($B34,'2026年1月6日'!$B:$E,4,0),0) | J34: =I34-G34 | K34: =_xlfn.IFNA(VLOOKUP($B34,'2026年1月7日'!$B:$E,4,0),0) | L34: =K34-I34 | M34: =_xlfn.IFNA(VLOOKUP($B34,'2026年1月8日'!$B:$E,4,0),0) | N34: =M34-K34 | O34: =_xlfn.IFNA(VLOOKUP($B34,'2026年1月9日'!$B:$E,4,0),0) | P34: =O34-M34 | Q34: =_xlfn.IFNA(VLOOKUP($B34,'2026年1月10日'!$B:$E,4,0),0) | R34: =Q34-O34 | S34: =_xlfn.IFNA(VLOOKUP($B34,'2026年1月12日'!$B:$E,4,0),0) | T34: =S34-Q34 | U34: =_xlfn.IFNA(VLOOKUP($B34,'2026年1月13日'!$B:$E,4,0),0) | V34: =U34-S34 | W34: =_xlfn.IFNA(VLOOKUP($B34,'2026年1月14日'!$B:$E,4,0),0) | X34: =W34-U34 | Y34: =_xlfn.IFNA(VLOOKUP($B34,'2026年1月15日'!$B:$E,4,0),0) | Z34: =Y34-W34 | AA34: =_xlfn.IFNA(VLOOKUP($B34,'2026年1月16日'!$B:$E,4,0),0) | AB34: =AA34-W34 | AC34: =_xlfn.IFNA(VLOOKUP($B34,'2026年1月17日'!$B:$E,4,0),0) | AD34: =AC34-AA34 | AE34: =_xlfn.IFNA(VLOOKUP($B34,'2026年1月19日'!$B:$E,4,0),0) | AF34: =AE34-AC34 | AG34: =_xlfn.IFNA(VLOOKUP($B34,'2026年1月20日'!$B:$E,4,0),0) | AH34: =AG34-AE34 | AI34: =_xlfn.IFNA(VLOOKUP($B34,'2026年1月21日'!$B:$E,4,0),0) | AJ34: =AI34-AG34 | AK34: =_xlfn.IFNA(VLOOKUP($B34,'2026年1月22日'!$B:$E,4,0),0) | AL34: =AK34-AI34 | AM34: =_xlfn.IFNA(VLOOKUP($B34,'2026年1月23日'!$B:$E,4,0),0) | AN34: =AM34-AK34 | AO34: =_xlfn.IFNA(VLOOKUP($B34,'2026年1月24日'!$B:$E,4,0),0) | AP34: =AO34-AM34 | AQ34: =_xlfn.IFNA(VLOOKUP($B34,'2026年1月26日'!$B:$E,4,0),0) | AR34: =AQ34-AO34 | AS34: 666700 | AU34: 666700 | AV34: 0 | AW34: 666700 | AX34: 0 | AY34: 666700 | AZ34: 0 | BA34: 666700 | BB34: 0 | BE34: 670900 | BG34: 669900 | BH34: -1000 | BI34: 670900 | BJ34: 1000 | BK34: 666700 | BL34: -4200 | BM34: 669900 | BN34: 3200 | BO34: 727300 | BP34: 57400 | BQ34: 727300 | BR34: 0 | BS34: 722000 | BT34: -5300 | BU34: 666700 | BV34: -55300 | BW34: 666700 | BX34: 0
B35: B01565 | C35: 國泰君安證券(香港)有限公司 | D35: =_xlfn.IFNA(VLOOKUP($B35,'2026年1月2日'!$B:$E,4,0),0) | E35: =_xlfn.IFNA(VLOOKUP($B35,'2026年1月2日'!$B:$E,4,0),0) | F35: =E35-D35 | G35: =_xlfn.IFNA(VLOOKUP($B35,'2026年1月5日'!$B:$E,4,0),0) | H35: =G35-E35 | I35: =_xlfn.IFNA(VLOOKUP($B35,'2026年1月6日'!$B:$E,4,0),0) | J35: =I35-G35 | K35: =_xlfn.IFNA(VLOOKUP($B35,'2026年1月7日'!$B:$E,4,0),0) | L35: =K35-I35 | M35: =_xlfn.IFNA(VLOOKUP($B35,'2026年1月8日'!$B:$E,4,0),0) | N35: =M35-K35 | O35: =_xlfn.IFNA(VLOOKUP($B35,'2026年1月9日'!$B:$E,4,0),0) | P35: =O35-M35 | Q35: =_xlfn.IFNA(VLOOKUP($B35,'2026年1月10日'!$B:$E,4,0),0) | R35: =Q35-O35 | S35: =_xlfn.IFNA(VLOOKUP($B35,'2026年1月12日'!$B:$E,4,0),0) | T35: =S35-Q35 | U35: =_xlfn.IFNA(VLOOKUP($B35,'2026年1月13日'!$B:$E,4,0),0) | V35: =U35-S35 | W35: =_xlfn.IFNA(VLOOKUP($B35,'2026年1月14日'!$B:$E,4,0),0) | X35: =W35-U35 | Y35: =_xlfn.IFNA(VLOOKUP($B35,'2026年1月15日'!$B:$E,4,0),0) | Z35: =Y35-W35 | AA35: =_xlfn.IFNA(VLOOKUP($B35,'2026年1月16日'!$B:$E,4,0),0) | AB35: =AA35-W35 | AC35: =_xlfn.IFNA(VLOOKUP($B35,'2026年1月17日'!$B:$E,4,0),0) | AD35: =AC35-AA35 | AE35: =_xlfn.IFNA(VLOOKUP($B35,'2026年1月19日'!$B:$E,4,0),0) | AF35: =AE35-AC35 | AG35: =_xlfn.IFNA(VLOOKUP($B35,'2026年1月20日'!$B:$E,4,0),0) | AH35: =AG35-AE35 | AI35: =_xlfn.IFNA(VLOOKUP($B35,'2026年1月21日'!$B:$E,4,0),0) | AJ35: =AI35-AG35 | AK35: =_xlfn.IFNA(VLOOKUP($B35,'2026年1月22日'!$B:$E,4,0),0) | AL35: =AK35-AI35 | AM35: =_xlfn.IFNA(VLOOKUP($B35,'2026年1月23日'!$B:$E,4,0),0) | AN35: =AM35-AK35 | AO35: =_xlfn.IFNA(VLOOKUP($B35,'2026年1月24日'!$B:$E,4,0),0) | AP35: =AO35-AM35 | AQ35: =_xlfn.IFNA(VLOOKUP($B35,'2026年1月26日'!$B:$E,4,0),0) | AR35: =AQ35-AO35 | AS35: 933100 | AU35: 933100 | AV35: 0 | AW35: 938200 | AX35: 5100 | AY35: 938200 | AZ35: 0 | BA35: 848900 | BB35: -89300 | BE35: 2362200 | BG35: 1481100 | BH35: -881100 | BI35: 2362200 | BJ35: 881100 | BK35: 938200 | BL35: -1424000 | BM35: 1624200 | BN35: 686000 | BO35: 1485900 | BP35: -138300 | BQ35: 1485900 | BR35: 0 | BS35: 1424400 | BT35: -61500 | BU35: 848900 | BV35: -575500 | BW35: 848900 | BX35: 0
B36: B01584 | C36: 致富證券有限公司 | D36: =_xlfn.IFNA(VLOOKUP($B36,'2026年1月2日'!$B:$E,4,0),0) | E36: =_xlfn.IFNA(VLOOKUP($B36,'2026年1月2日'!$B:$E,4,0),0) | F36: =E36-D36 | G36: =_xlfn.IFNA(VLOOKUP($B36,'2026年1月5日'!$B:$E,4,0),0) | H36: =G36-E36 | I36: =_xlfn.IFNA(VLOOKUP($B36,'2026年1月6日'!$B:$E,4,0),0) | J36: =I36-G36 | K36: =_xlfn.IFNA(VLOOKUP($B36,'2026年1月7日'!$B:$E,4,0),0) | L36: =K36-I36 | M36: =_xlfn.IFNA(VLOOKUP($B36,'2026年1月8日'!$B:$E,4,0),0) | N36: =M36-K36 | O36: =_xlfn.IFNA(VLOOKUP($B36,'2026年1月9日'!$B:$E,4,0),0) | P36: =O36-M36 | Q36: =_xlfn.IFNA(VLOOKUP($B36,'2026年1月10日'!$B:$E,4,0),0) | R36: =Q36-O36 | S36: =_xlfn.IFNA(VLOOKUP($B36,'2026年1月12日'!$B:$E,4,0),0) | T36: =S36-Q36 | U36: =_xlfn.IFNA(VLOOKUP($B36,'2026年1月13日'!$B:$E,4,0),0) | V36: =U36-S36 | W36: =_xlfn.IFNA(VLOOKUP($B36,'2026年1月14日'!$B:$E,4,0),0) | X36: =W36-U36 | Y36: =_xlfn.IFNA(VLOOKUP($B36,'2026年1月15日'!$B:$E,4,0),0) | Z36: =Y36-W36 | AA36: =_xlfn.IFNA(VLOOKUP($B36,'2026年1月16日'!$B:$E,4,0),0) | AB36: =AA36-W36 | AC36: =_xlfn.IFNA(VLOOKUP($B36,'2026年1月17日'!$B:$E,4,0),0) | AD36: =AC36-AA36 | AE36: =_xlfn.IFNA(VLOOKUP($B36,'2026年1月19日'!$B:$E,4,0),0) | AF36: =AE36-AC36 | AG36: =_xlfn.IFNA(VLOOKUP($B36,'2026年1月20日'!$B:$E,4,0),0) | AH36: =AG36-AE36 | AI36: =_xlfn.IFNA(VLOOKUP($B36,'2026年1月21日'!$B:$E,4,0),0) | AJ36: =AI36-AG36 | AK36: =_xlfn.IFNA(VLOOKUP($B36,'2026年1月22日'!$B:$E,4,0),0) | AL36: =AK36-AI36 | AM36: =_xlfn.IFNA(VLOOKUP($B36,'2026年1月23日'!$B:$E,4,0),0) | AN36: =AM36-AK36 | AO36: =_xlfn.IFNA(VLOOKUP($B36,'2026年1月24日'!$B:$E,4,0),0) | AP36: =AO36-AM36 | AQ36: =_xlfn.IFNA(VLOOKUP($B36,'2026年1月26日'!$B:$E,4,0),0) | AR36: =AQ36-AO36 | AS36: 1383200 | AU36: 1388200 | AV36: 5000 | AW36: 1384200 | AX36: -4000 | AY36: 1404200 | AZ36: 20000 | BA36: 1399600 | BB36: -4600 | BE36: 1629400 | BG36: 2404100 | BH36: 774700 | BI36: 1629400 | BJ36: -774700 | BK36: 1404200 | BL36: -225200 | BM36: 2247700 | BN36: 843500 | BO36: 1777500 | BP36: -470200 | BQ36: 1777500 | BR36: 0 | BS36: 1855600 | BT36: 78100 | BU36: 1399600 | BV36: -456000 | BW36: 1399600 | BX36: 0
... B73: B01272 | C73: 富銀證券(香港)有限公司 | D73: =_xlfn.IFNA(VLOOKUP($B73,'2026年1月2日'!$B:$E,4,0),0) | E73: =_xlfn.IFNA(VLOOKUP($B73,'2026年1月2日'!$B:$E,4,0),0) | F73: =E73-D73 | G73: =_xlfn.IFNA(VLOOKUP($B73,'2026年1月5日'!$B:$E,4,0),0) | H73: =G73-E73 | I73: =_xlfn.IFNA(VLOOKUP($B73,'2026年1月6日'!$B:$E,4,0),0) | J73: =I73-G73 | K73: =_xlfn.IFNA(VLOOKUP($B73,'2026年1月7日'!$B:$E,4,0),0) | L73: =K73-I73 | M73: =_xlfn.IFNA(VLOOKUP($B73,'2026年1月8日'!$B:$E,4,0),0) | N73: =M73-K73 | O73: =_xlfn.IFNA(VLOOKUP($B73,'2026年1月9日'!$B:$E,4,0),0) | P73: =O73-M73 | Q73: =_xlfn.IFNA(VLOOKUP($B73,'2026年1月10日'!$B:$E,4,0),0) | R73: =Q73-O73 | S73: =_xlfn.IFNA(VLOOKUP($B73,'2026年1月12日'!$B:$E,4,0),0) | T73: =S73-Q73 | U73: =_xlfn.IFNA(VLOOKUP($B73,'2026年1月13日'!$B:$E,4,0),0) | V73: =U73-S73 | W73: =_xlfn.IFNA(VLOOKUP($B73,'2026年1月14日'!$B:$E,4,0),0) | X73: =W73-U73 | Y73: =_xlfn.IFNA(VLOOKUP($B73,'2026年1月15日'!$B:$E,4,0),0) | Z73: =Y73-W73 | AA73: =_xlfn.IFNA(VLOOKUP($B73,'2026年1月16日'!$B:$E,4,0),0) | AB73: =AA73-W73 | AC73: =_xlfn.IFNA(VLOOKUP($B73,'2026年1月17日'!$B:$E,4,0),0) | AD73: =AC73-AA73 | AE73: =_xlfn.IFNA(VLOOKUP($B73,'2026年1月19日'!$B:$E,4,0),0) | AF73: =AE73-AC73 | AG73: =_xlfn.IFNA(VLOOKUP($B73,'2026年1月20日'!$B:$E,4,0),0) | AH73: =AG73-AE73 | AI73: =_xlfn.IFNA(VLOOKUP($B73,'2026年1月21日'!$B:$E,4,0),0) | AJ73: =AI73-AG73 | AK73: =_xlfn.IFNA(VLOOKUP($B73,'2026年1月22日'!$B:$E,4,0),0) | AL73: =AK73-AI73 | AM73: =_xlfn.IFNA(VLOOKUP($B73,'2026年1月23日'!$B:$E,4,0),0) | AN73: =AM73-AK73 | AO73: =_xlfn.IFNA(VLOOKUP($B73,'2026年1月24日'!$B:$E,4,0),0) | AP73: =AO73-AM73 | AQ73: =_xlfn.IFNA(VLOOKUP($B73,'2026年1月26日'!$B:$E,4,0),0) | AR73: =AQ73-AO73 | AS73: 112800 | AU73: 112800 | AV73: 0 | AW73: 112800 | AX73: 0 | AY73: 112800 | AZ73: 0 | BA73: 100800 | BB73: -12000 | BE73: 160800 | BG73: 160200 | BH73: -600 | BI73: 160800 | BJ73: 600 | BK73: 112800 | BL73: -48000 | BM73: 217100 | BN73: 104300 | BO73: 169300 | BP73: -47800 | BQ73: 169300 | BR73: 0 | BS73: 193300 | BT73: 24000 | BU73: 100800 | BV73: -92500 | BW73: 100800 | BX73: 0
B74: B01217 | C74: 太平証券(香港)有限公司 | D74: =_xlfn.IFNA(VLOOKUP($B74,'2026年1月2日'!$B:$E,4,0),0) | E74: =_xlfn.IFNA(VLOOKUP($B74,'2026年1月2日'!$B:$E,4,0),0) | F74: =E74-D74 | G74: =_xlfn.IFNA(VLOOKUP($B74,'2026年1月5日'!$B:$E,4,0),0) | H74: =G74-E74 | I74: =_xlfn.IFNA(VLOOKUP($B74,'2026年1月6日'!$B:$E,4,0),0) | J74: =I74-G74 | K74: =_xlfn.IFNA(VLOOKUP($B74,'2026年1月7日'!$B:$E,4,0),0) | L74: =K74-I74 | M74: =_xlfn.IFNA(VLOOKUP($B74,'2026年1月8日'!$B:$E,4,0),0) | N74: =M74-K74 | O74: =_xlfn.IFNA(VLOOKUP($B74,'2026年1月9日'!$B:$E,4,0),0) | P74: =O74-M74 | Q74: =_xlfn.IFNA(VLOOKUP($B74,'2026年1月10日'!$B:$E,4,0),0) | R74: =Q74-O74 | S74: =_xlfn.IFNA(VLOOKUP($B74,'2026年1月12日'!$B:$E,4,0),0) | T74: =S74-Q74 | U74: =_xlfn.IFNA(VLOOKUP($B74,'2026年1月13日'!$B:$E,4,0),0) | V74: =U74-S74 | W74: =_xlfn.IFNA(VLOOKUP($B74,'2026年1月14日'!$B:$E,4,0),0) | X74: =W74-U74 | Y74: =_xlfn.IFNA(VLOOKUP($B74,'2026年1月15日'!$B:$E,4,0),0) | Z74: =Y74-W74 | AA74: =_xlfn.IFNA(VLOOKUP($B74,'2026年1月16日'!$B:$E,4,0),0) | AB74: =AA74-W74 | AC74: =_xlfn.IFNA(VLOOKUP($B74,'2026年1月17日'!$B:$E,4,0),0) | AD74: =AC74-AA74 | AE74: =_xlfn.IFNA(VLOOKUP($B74,'2026年1月19日'!$B:$E,4,0),0) | AF74: =AE74-AC74 | AG74: =_xlfn.IFNA(VLOOKUP($B74,'2026年1月20日'!$B:$E,4,0),0) | AH74: =AG74-AE74 | AI74: =_xlfn.IFNA(VLOOKUP($B74,'2026年1月21日'!$B:$E,4,0),0) | AJ74: =AI74-AG74 | AK74: =_xlfn.IFNA(VLOOKUP($B74,'2026年1月22日'!$B:$E,4,0),0) | AL74: =AK74-AI74 | AM74: =_xlfn.IFNA(VLOOKUP($B74,'2026年1月23日'!$B:$E,4,0),0) | AN74: =AM74-AK74 | AO74: =_xlfn.IFNA(VLOOKUP($B74,'2026年1月24日'!$B:$E,4,0),0) | AP74: =AO74-AM74 | AQ74: =_xlfn.IFNA(VLOOKUP($B74,'2026年1月26日'!$B:$E,4,0),0) | AR74: =AQ74-AO74
B75: B02045 | C75: AAA SECURITIES CO. LTD | D75: =_xlfn.IFNA(VLOOKUP($B75,'2026年1月2日'!$B:$E,4,0),0) | E75: =_xlfn.IFNA(VLOOKUP($B75,'2026年1月2日'!$B:$E,4,0),0) | F75: =E75-D75 | G75: =_xlfn.IFNA(VLOOKUP($B75,'2026年1月5日'!$B:$E,4,0),0) | H75: =G75-E75 | I75: =_xlfn.IFNA(VLOOKUP($B75,'2026年1月6日'!$B:$E,4,0),0) | J75: =I75-G75 | K75: =_xlfn.IFNA(VLOOKUP($B75,'2026年1月7日'!$B:$E,4,0),0) | L75: =K75-I75 | M75: =_xlfn.IFNA(VLOOKUP($B75,'2026年1月8日'!$B:$E,4,0),0) | N75: =M75-K75 | O75: =_xlfn.IFNA(VLOOKUP($B75,'2026年1月9日'!$B:$E,4,0),0) | P75: =O75-M75 | Q75: =_xlfn.IFNA(VLOOKUP($B75,'2026年1月10日'!$B:$E,4,0),0) | R75: =Q75-O75 | S75: =_xlfn.IFNA(VLOOKUP($B75,'2026年1月12日'!$B:$E,4,0),0) | T75: =S75-Q75 | U75: =_xlfn.IFNA(VLOOKUP($B75,'2026年1月13日'!$B:$E,4,0),0) | V75: =U75-S75 | W75: =_xlfn.IFNA(VLOOKUP($B75,'2026年1月14日'!$B:$E,4,0),0) | X75: =W75-U75 | Y75: =_xlfn.IFNA(VLOOKUP($B75,'2026年1月15日'!$B:$E,4,0),0) | Z75: =Y75-W75 | AA75: =_xlfn.IFNA(VLOOKUP($B75,'2026年1月16日'!$B:$E,4,0),0) | AB75: =AA75-W75 | AC75: =_xlfn.IFNA(VLOOKUP($B75,'2026年1月17日'!$B:$E,4,0),0) | AD75: =AC75-AA75 | AE75: =_xlfn.IFNA(VLOOKUP($B75,'2026年1月19日'!$B:$E,4,0),0) | AF75: =AE75-AC75 | AG75: =_xlfn.IFNA(VLOOKUP($B75,'2026年1月20日'!$B:$E,4,0),0) | AH75: =AG75-AE75 | AI75: =_xlfn.IFNA(VLOOKUP($B75,'2026年1月21日'!$B:$E,4,0),0) | AJ75: =AI75-AG75 | AK75: =_xlfn.IFNA(VLOOKUP($B75,'2026年1月22日'!$B:$E,4,0),0) | AL75: =AK75-AI75 | AM75: =_xlfn.IFNA(VLOOKUP($B75,'2026年1月23日'!$B:$E,4,0),0) | AN75: =AM75-AK75 | AO75: =_xlfn.IFNA(VLOOKUP($B75,'2026年1月24日'!$B:$E,4,0),0) | AP75: =AO75-AM75 | AQ75: =_xlfn.IFNA(VLOOKUP($B75,'2026年1月26日'!$B:$E,4,0),0) | AR75: =AQ75-AO75 | AS75: 138900 | AU75: 138900 | AV75: 0 | AW75: 138900 | AX75: 0 | AY75: 138900 | AZ75: 0 | BA75: 138900 | BB75: 0 | BE75: 152100 | BG75: 119900 | BH75: -32200 | BI75: 152100 | BJ75: 32200 | BK75: 138900 | BL75: -13200 | BM75: 137100 | BN75: -1800 | BO75: 189900 | BP75: 52800 | BQ75: 189900 | BR75: 0 | BS75: 119900 | BT75: -70000 | BU75: 138900 | BV75: 19000 | BW75: 138900 | BX75: 0
B76: B01555 | C76: ABN AMRO CLEARING HONG KONG LTD | D76: =_xlfn.IFNA(VLOOKUP($B76,'2026年1月2日'!$B:$E,4,0),0) | E76: =_xlfn.IFNA(VLOOKUP($B76,'2026年1月2日'!$B:$E,4,0),0) | F76: =E76-D76 | G76: =_xlfn.IFNA(VLOOKUP($B76,'2026年1月5日'!$B:$E,4,0),0) | H76: =G76-E76 | I76: =_xlfn.IFNA(VLOOKUP($B76,'2026年1月6日'!$B:$E,4,0),0) | J76: =I76-G76 | K76: =_xlfn.IFNA(VLOOKUP($B76,'2026年1月7日'!$B:$E,4,0),0) | L76: =K76-I76 | M76: =_xlfn.IFNA(VLOOKUP($B76,'2026年1月8日'!$B:$E,4,0),0) | N76: =M76-K76 | O76: =_xlfn.IFNA(VLOOKUP($B76,'2026年1月9日'!$B:$E,4,0),0) | P76: =O76-M76 | Q76: =_xlfn.IFNA(VLOOKUP($B76,'2026年1月10日'!$B:$E,4,0),0) | R76: =Q76-O76 | S76: =_xlfn.IFNA(VLOOKUP($B76,'2026年1月12日'!$B:$E,4,0),0) | T76: =S76-Q76 | U76: =_xlfn.IFNA(VLOOKUP($B76,'2026年1月13日'!$B:$E,4,0),0) | V76: =U76-S76 | W76: =_xlfn.IFNA(VLOOKUP($B76,'2026年1月14日'!$B:$E,4,0),0) | X76: =W76-U76 | Y76: =_xlfn.IFNA(VLOOKUP($B76,'2026年1月15日'!$B:$E,4,0),0) | Z76: =Y76-W76 | AA76: =_xlfn.IFNA(VLOOKUP($B76,'2026年1月16日'!$B:$E,4,0),0) | AB76: =AA76-W76 | AC76: =_xlfn.IFNA(VLOOKUP($B76,'2026年1月17日'!$B:$E,4,0),0) | AD76: =AC76-AA76 | AE76: =_xlfn.IFNA(VLOOKUP($B76,'2026年1月19日'!$B:$E,4,0),0) | AF76: =AE76-AC76 | AG76: =_xlfn.IFNA(VLOOKUP($B76,'2026年1月20日'!$B:$E,4,0),0) | AH76: =AG76-AE76 | AI76: =_xlfn.IFNA(VLOOKUP($B76,'2026年1月21日'!$B:$E,4,0),0) | AJ76: =AI76-AG76 | AK76: =_xlfn.IFNA(VLOOKUP($B76,'2026年1月22日'!$B:$E,4,0),0) | AL76: =AK76-AI76 | AM76: =_xlfn.IFNA(VLOOKUP($B76,'2026年1月23日'!$B:$E,4,0),0) | AN76: =AM76-AK76 | AO76: =_xlfn.IFNA(VLOOKUP($B76,'2026年1月24日'!$B:$E,4,0),0) | AP76: =AO76-AM76 | AQ76: =_xlfn.IFNA(VLOOKUP($B76,'2026年1月26日'!$B:$E,4,0),0) | AR76: =AQ76-AO76 | AS76: 226700 | AU76: 182700 | AV76: -44000 | AW76: 170500 | AX76: -12200 | AY76: 52000 | AZ76: -118500 | BA76: 18900 | BB76: -33100 | BE76: 146200 | BG76: 95300 | BH76: -50900 | BI76: 146200 | BJ76: 50900 | BK76: 52000 | BL76: -94200 | BM76: 272700 | BN76: 220700 | BO76: 57400 | BP76: -215300 | BQ76: 57400 | BR76: 0 | BS76: 145200 | BT76: 87800 | BU76: 18900 | BV76: -126300 | BW76: 18900 | BX76: 0
B77: B02159 | C77: 盈立證券有限公司 | D77: =_xlfn.IFNA(VLOOKUP($B77,'2026年1月2日'!$B:$E,4,0),0) | E77: =_xlfn.IFNA(VLOOKUP($B77,'2026年1月2日'!$B:$E,4,0),0) | F77: =E77-D77 | G77: =_xlfn.IFNA(VLOOKUP($B77,'2026年1月5日'!$B:$E,4,0),0) | H77: =G77-E77 | I77: =_xlfn.IFNA(VLOOKUP($B77,'2026年1月6日'!$B:$E,4,0),0) | J77: =I77-G77 | K77: =_xlfn.IFNA(VLOOKUP($B77,'2026年1月7日'!$B:$E,4,0),0) | L77: =K77-I77 | M77: =_xlfn.IFNA(VLOOKUP($B77,'2026年1月8日'!$B:$E,4,0),0) | N77: =M77-K77 | O77: =_xlfn.IFNA(VLOOKUP($B77,'2026年1月9日'!$B:$E,4,0),0) | P77: =O77-M77 | Q77: =_xlfn.IFNA(VLOOKUP($B77,'2026年1月10日'!$B:$E,4,0),0) | R77: =Q77-O77 | S77: =_xlfn.IFNA(VLOOKUP($B77,'2026年1月12日'!$B:$E,4,0),0) | T77: =S77-Q77 | U77: =_xlfn.IFNA(VLOOKUP($B77,'2026年1月13日'!$B:$E,4,0),0) | V77: =U77-S77 | W77: =_xlfn.IFNA(VLOOKUP($B77,'2026年1月14日'!$B:$E,4,0),0) | X77: =W77-U77 | Y77: =_xlfn.IFNA(VLOOKUP($B77,'2026年1月15日'!$B:$E,4,0),0) | Z77: =Y77-W77 | AA77: =_xlfn.IFNA(VLOOKUP($B77,'2026年1月16日'!$B:$E,4,0),0) | AB77: =AA77-W77 | AC77: =_xlfn.IFNA(VLOOKUP($B77,'2026年1月17日'!$B:$E,4,0),0) | AD77: =AC77-AA77 | AE77: =_xlfn.IFNA(VLOOKUP($B77,'2026年1月19日'!$B:$E,4,0),0) | AF77: =AE77-AC77 | AG77: =_xlfn.IFNA(VLOOKUP($B77,'2026年1月20日'!$B:$E,4,0),0) | AH77: =AG77-AE77 | AI77: =_xlfn.IFNA(VLOOKUP($B77,'2026年1月21日'!$B:$E,4,0),0) | AJ77: =AI77-AG77 | AK77: =_xlfn.IFNA(VLOOKUP($B77,'2026年1月22日'!$B:$E,4,0),0) | AL77: =AK77-AI77 | AM77: =_xlfn.IFNA(VLOOKUP($B77,'2026年1月23日'!$B:$E,4,0),0) | AN77: =AM77-AK77 | AO77: =_xlfn.IFNA(VLOOKUP($B77,'2026年1月24日'!$B:$E,4,0),0) | AP77: =AO77-AM77 | AQ77: =_xlfn.IFNA(VLOOKUP($B77,'2026年1月26日'!$B:$E,4,0),0) | AR77: =AQ77-AO77 | AS77: 233104 | AU77: 220404 | AV77: -12700 | AW77: 221304 | AX77: 900 | AY77: 222204 | AZ77: 900 | BA77: 222404 | BB77: 200 | BE77: 282406 | BG77: 211008 | BH77: -71398 | BI77: 282406 | BJ77: 71398 | BK77: 222204 | BL77: -60202 | BM77: 292206 | BN77: 70002 | BO77: 205508 | BP77: -86698 | BQ77: 205508 | BR77: 0 | BS77: 223308 | BT77: 17800 | BU77: 222404 | BV77: -904 | BW77: 222404 | BX77: 0
B78: B01265 | C78: 華僑永亨証券有限公司 | D78: =_xlfn.IFNA(VLOOKUP($B78,'2026年1月2日'!$B:$E,4,0),0) | E78: =_xlfn.IFNA(VLOOKUP($B78,'2026年1月2日'!$B:$E,4,0),0) | F78: =E78-D78 | G78: =_xlfn.IFNA(VLOOKUP($B78,'2026年1月5日'!$B:$E,4,0),0) | H78: =G78-E78 | I78: =_xlfn.IFNA(VLOOKUP($B78,'2026年1月6日'!$B:$E,4,0),0) | J78: =I78-G78 | K78: =_xlfn.IFNA(VLOOKUP($B78,'2026年1月7日'!$B:$E,4,0),0) | L78: =K78-I78 | M78: =_xlfn.IFNA(VLOOKUP($B78,'2026年1月8日'!$B:$E,4,0),0) | N78: =M78-K78 | O78: =_xlfn.IFNA(VLOOKUP($B78,'2026年1月9日'!$B:$E,4,0),0) | P78: =O78-M78 | Q78: =_xlfn.IFNA(VLOOKUP($B78,'2026年1月10日'!$B:$E,4,0),0) | R78: =Q78-O78 | S78: =_xlfn.IFNA(VLOOKUP($B78,'2026年1月12日'!$B:$E,4,0),0) | T78: =S78-Q78 | U78: =_xlfn.IFNA(VLOOKUP($B78,'2026年1月13日'!$B:$E,4,0),0) | V78: =U78-S78 | W78: =_xlfn.IFNA(VLOOKUP($B78,'2026年1月14日'!$B:$E,4,0),0) | X78: =W78-U78 | Y78: =_xlfn.IFNA(VLOOKUP($B78,'2026年1月15日'!$B:$E,4,0),0) | Z78: =Y78-W78 | AA78: =_xlfn.IFNA(VLOOKUP($B78,'2026年1月16日'!$B:$E,4,0),0) | AB78: =AA78-W78 | AC78: =_xlfn.IFNA(VLOOKUP($B78,'2026年1月17日'!$B:$E,4,0),0) | AD78: =AC78-AA78 | AE78: =_xlfn.IFNA(VLOOKUP($B78,'2026年1月19日'!$B:$E,4,0),0) | AF78: =AE78-AC78 | AG78: =_xlfn.IFNA(VLOOKUP($B78,'2026年1月20日'!$B:$E,4,0),0) | AH78: =AG78-AE78 | AI78: =_xlfn.IFNA(VLOOKUP($B78,'2026年1月21日'!$B:$E,4,0),0) | AJ78: =AI78-AG78 | AK78: =_xlfn.IFNA(VLOOKUP($B78,'2026年1月22日'!$B:$E,4,0),0) | AL78: =AK78-AI78 | AM78: =_xlfn.IFNA(VLOOKUP($B78,'2026年1月23日'!$B:$E,4,0),0) | AN78: =AM78-AK78 | AO78: =_xlfn.IFNA(VLOOKUP($B78,'2026年1月24日'!$B:$E,4,0),0) | AP78: =AO78-AM78 | AQ78: =_xlfn.IFNA(VLOOKUP($B78,'2026年1月26日'!$B:$E,4,0),0) | AR78: =AQ78-AO78 | AS78: 339100 | AU78: 329100 | AV78: -10000 | AW78: 329100 | AX78: 0 | AY78: 349100 | AZ78: 20000 | BA78: 349100 | BB78: 0 | BE78: 436000 | BG78: 507000 | BH78: 71000 | BI78: 436000 | BJ78: -71000 | BK78: 349100 | BL78: -86900 | BM78: 317500 | BN78: -31600 | BO78: 521300 | BP78: 203800 | BQ78: 521300 | BR78: 0 | BS78: 550100 | BT78: 28800 | BU78: 349100 | BV78: -201000 | BW78: 349100 | BX78: 0
B79: B01905 | C79: 安信國際證券(香港)有限公司 | D79: =_xlfn.IFNA(VLOOKUP($B79,'2026年1月2日'!$B:$E,4,0),0) | E79: =_xlfn.IFNA(VLOOKUP($B79,'2026年1月2日'!$B:$E,4,0),0) | F79: =E79-D79 | G79: =_xlfn.IFNA(VLOOKUP($B79,'2026年1月5日'!$B:$E,4,0),0) | H79: =G79-E79 | I79: =_xlfn.IFNA(VLOOKUP($B79,'2026年1月6日'!$B:$E,4,0),0) | J79: =I79-G79 | K79: =_xlfn.IFNA(VLOOKUP($B79,'2026年1月7日'!$B:$E,4,0),0) | L79: =K79-I79 | M79: =_xlfn.IFNA(VLOOKUP($B79,'2026年1月8日'!$B:$E,4,0),0) | N79: =M79-K79 | O79: =_xlfn.IFNA(VLOOKUP($B79,'2026年1月9日'!$B:$E,4,0),0) | P79: =O79-M79 | Q79: =_xlfn.IFNA(VLOOKUP($B79,'2026年1月10日'!$B:$E,4,0),0) | R79: =Q79-O79 | S79: =_xlfn.IFNA(VLOOKUP($B79,'2026年1月12日'!$B:$E,4,0),0) | T79: =S79-Q79 | U79: =_xlfn.IFNA(VLOOKUP($B79,'2026年1月13日'!$B:$E,4,0),0) | V79: =U79-S79 | W79: =_xlfn.IFNA(VLOOKUP($B79,'2026年1月14日'!$B:$E,4,0),0) | X79: =W79-U79 | Y79: =_xlfn.IFNA(VLOOKUP($B79,'2026年1月15日'!$B:$E,4,0),0) | Z79: =Y79-W79 | AA79: =_xlfn.IFNA(VLOOKUP($B79,'2026年1月16日'!$B:$E,4,0),0) | AB79: =AA79-W79 | AC79: =_xlfn.IFNA(VLOOKUP($B79,'2026年1月17日'!$B:$E,4,0),0) | AD79: =AC79-AA79 | AE79: =_xlfn.IFNA(VLOOKUP($B79,'2026年1月19日'!$B:$E,4,0),0) | AF79: =AE79-AC79 | AG79: =_xlfn.IFNA(VLOOKUP($B79,'2026年1月20日'!$B:$E,4,0),0) | AH79: =AG79-AE79 | AI79: =_xlfn.IFNA(VLOOKUP($B79,'2026年1月21日'!$B:$E,4,0),0) | AJ79: =AI79-AG79 | AK79: =_xlfn.IFNA(VLOOKUP($B79,'2026年1月22日'!$B:$E,4,0),0) | AL79: =AK79-AI79 | AM79: =_xlfn.IFNA(VLOOKUP($B79,'2026年1月23日'!$B:$E,4,0),0) | AN79: =AM79-AK79 | AO79: =_xlfn.IFNA(VLOOKUP($B79,'2026年1月24日'!$B:$E,4,0),0) | AP79: =AO79-AM79 | AQ79: =_xlfn.IFNA(VLOOKUP($B79,'2026年1月26日'!$B:$E,4,0),0) | AR79: =AQ79-AO79 | AS79: 745700 | AU79: 745700 | AV79: 0 | AW79: 745700 | AX79: 0 | AY79: 745700 | AZ79: 0 | BA79: 745700 | BB79: 0 | BE79: 1213100 | BG79: 1275700 | BH79: 62600 | BI79: 1213100 | BJ79: -62600 | BK79: 745700 | BL79: -467400 | BM79: 1122300 | BN79: 376600 | BO79: 1526000 | BP79: 403700 | BQ79: 1526000 | BR79: 0 | BS79: 1827200 | BT79: 301200 | BU79: 745700 | BV79: -1081500 | BW79: 745700 | BX79: 0
B80: B01347 | C80: 銀河—聯昌證券(香港)有限公司 | D80: =_xlfn.IFNA(VLOOKUP($B80,'2026年1月2日'!$B:$E,4,0),0) | E80: =_xlfn.IFNA(VLOOKUP($B80,'2026年1月2日'!$B:$E,4,0),0) | F80: =E80-D80 | G80: =_xlfn.IFNA(VLOOKUP($B80,'2026年1月5日'!$B:$E,4,0),0) | H80: =G80-E80 | I80: =_xlfn.IFNA(VLOOKUP($B80,'2026年1月6日'!$B:$E,4,0),0) | J80: =I80-G80 | K80: =_xlfn.IFNA(VLOOKUP($B80,'2026年1月7日'!$B:$E,4,0),0) | L80: =K80-I80 | M80: =_xlfn.IFNA(VLOOKUP($B80,'2026年1月8日'!$B:$E,4,0),0) | N80: =M80-K80 | O80: =_xlfn.IFNA(VLOOKUP($B80,'2026年1月9日'!$B:$E,4,0),0) | P80: =O80-M80 | Q80: =_xlfn.IFNA(VLOOKUP($B80,'2026年1月10日'!$B:$E,4,0),0) | R80: =Q80-O80 | S80: =_xlfn.IFNA(VLOOKUP($B80,'2026年1月12日'!$B:$E,4,0),0) | T80: =S80-Q80 | U80: =_xlfn.IFNA(VLOOKUP($B80,'2026年1月13日'!$B:$E,4,0),0) | V80: =U80-S80 | W80: =_xlfn.IFNA(VLOOKUP($B80,'2026年1月14日'!$B:$E,4,0),0) | X80: =W80-U80 | Y80: =_xlfn.IFNA(VLOOKUP($B80,'2026年1月15日'!$B:$E,4,0),0) | Z80: =Y80-W80 | AA80: =_xlfn.IFNA(VLOOKUP($B80,'2026年1月16日'!$B:$E,4,0),0) | AB80: =AA80-W80 | AC80: =_xlfn.IFNA(VLOOKUP($B80,'2026年1月17日'!$B:$E,4,0),0) | AD80: =AC80-AA80 | AE80: =_xlfn.IFNA(VLOOKUP($B80,'2026年1月19日'!$B:$E,4,0),0) | AF80: =AE80-AC80 | AG80: =_xlfn.IFNA(VLOOKUP($B80,'2026年1月20日'!$B:$E,4,0),0) | AH80: =AG80-AE80 | AI80: =_xlfn.IFNA(VLOOKUP($B80,'2026年1月21日'!$B:$E,4,0),0) | AJ80: =AI80-AG80 | AK80: =_xlfn.IFNA(VLOOKUP($B80,'2026年1月22日'!$B:$E,4,0),0) | AL80: =AK80-AI80 | AM80: =_xlfn.IFNA(VLOOKUP($B80,'2026年1月23日'!$B:$E,4,0),0) | AN80: =AM80-AK80 | AO80: =_xlfn.IFNA(VLOOKUP($B80,'2026年1月24日'!$B:$E,4,0),0) | AP80: =AO80-AM80 | AQ80: =_xlfn.IFNA(VLOOKUP($B80,'2026年1月26日'!$B:$E,4,0),0) | AR80: =AQ80-AO80 | AS80: 480700 | AU80: 480700 | AV80: 0 | AW80: 480700 | AX80: 0 | AY80: 480700 | AZ80: 0 | BA80: 480700 | BB80: 0 | BE80: 477700 | BG80: 133200 | BH80: -344500 | BI80: 477700 | BJ80: 344500 | BK80: 480700 | BL80: 3000 | BM80: 158700 | BN80: -322000 | BO80: 129700 | BP80: -29000 | BQ80: 129700 | BR80: 0 | BS80: 143200 | BT80: 13500 | BU80: 480700 | BV80: 337500 | BW80: 480700 | BX80: 0
B81: B01338 | C81: 英皇證券(香港)有限公司 | D81: =_xlfn.IFNA(VLOOKUP($B81,'2026年1月2日'!$B:$E,4,0),0) | E81: =_xlfn.IFNA(VLOOKUP($B81,'2026年1月2日'!$B:$E,4,0),0) | F81: =E81-D81 | G81: =_xlfn.IFNA(VLOOKUP($B81,'2026年1月5日'!$B:$E,4,0),0) | H81: =G81-E81 | I81: =_xlfn.IFNA(VLOOKUP($B81,'2026年1月6日'!$B:$E,4,0),0) | J81: =I81-G81 | K81: =_xlfn.IFNA(VLOOKUP($B81,'2026年1月7日'!$B:$E,4,0),0) | L81: =K81-I81 | M81: =_xlfn.IFNA(VLOOKUP($B81,'2026年1月8日'!$B:$E,4,0),0) | N81: =M81-K81 | O81: =_xlfn.IFNA(VLOOKUP($B81,'2026年1月9日'!$B:$E,4,0),0) | P81: =O81-M81 | Q81: =_xlfn.IFNA(VLOOKUP($B81,'2026年1月10日'!$B:$E,4,0),0) | R81: =Q81-O81 | S81: =_xlfn.IFNA(VLOOKUP($B81,'2026年1月12日'!$B:$E,4,0),0) | T81: =S81-Q81 | U81: =_xlfn.IFNA(VLOOKUP($B81,'2026年1月13日'!$B:$E,4,0),0) | V81: =U81-S81 | W81: =_xlfn.IFNA(VLOOKUP($B81,'2026年1月14日'!$B:$E,4,0),0) | X81: =W81-U81 | Y81: =_xlfn.IFNA(VLOOKUP($B81,'2026年1月15日'!$B:$E,4,0),0) | Z81: =Y81-W81 | AA81: =_xlfn.IFNA(VLOOKUP($B81,'2026年1月16日'!$B:$E,4,0),0) | AB81: =AA81-W81 | AC81: =_xlfn.IFNA(VLOOKUP($B81,'2026年1月17日'!$B:$E,4,0),0) | AD81: =AC81-AA81 | AE81: =_xlfn.IFNA(VLOOKUP($B81,'2026年1月19日'!$B:$E,4,0),0) | AF81: =AE81-AC81 | AG81: =_xlfn.IFNA(VLOOKUP($B81,'2026年1月20日'!$B:$E,4,0),0) | AH81: =AG81-AE81 | AI81: =_xlfn.IFNA(VLOOKUP($B81,'2026年1月21日'!$B:$E,4,0),0) | AJ81: =AI81-AG81 | AK81: =_xlfn.IFNA(VLOOKUP($B81,'2026年1月22日'!$B:$E,4,0),0) | AL81: =AK81-AI81 | AM81: =_xlfn.IFNA(VLOOKUP($B81,'2026年1月23日'!$B:$E,4,0),0) | AN81: =AM81-AK81 | AO81: =_xlfn.IFNA(VLOOKUP($B81,'2026年1月24日'!$B:$E,4,0),0) | AP81: =AO81-AM81 | AQ81: =_xlfn.IFNA(VLOOKUP($B81,'2026年1月26日'!$B:$E,4,0),0) | AR81: =AQ81-AO81 | AS81: 94500 | AU81: 94500 | AV81: 0 | AW81: 94500 | AX81: 0 | AY81: 94500 | AZ81: 0 | BA81: 118500 | BB81: 24000 | BE81: 157400 | BG81: 327100 | BH81: 169700 | BI81: 157400 | BJ81: -169700 | BK81: 94500 | BL81: -62900 | BM81: 107100 | BN81: 12600 | BO81: 277100 | BP81: 170000 | BQ81: 277100 | BR81: 0 | BS81: 353600 | BT81: 76500 | BU81: 118500 | BV81: -235100 | BW81: 118500 | BX81: 0
B82: B01813 | C82: 建銀國際證券有限公司 | D82: =_xlfn.IFNA(VLOOKUP($B82,'2026年1月2日'!$B:$E,4,0),0) | E82: =_xlfn.IFNA(VLOOKUP($B82,'2026年1月2日'!$B:$E,4,0),0) | F82: =E82-D82 | G82: =_xlfn.IFNA(VLOOKUP($B82,'2026年1月5日'!$B:$E,4,0),0) | H82: =G82-E82 | I82: =_xlfn.IFNA(VLOOKUP($B82,'2026年1月6日'!$B:$E,4,0),0) | J82: =I82-G82 | K82: =_xlfn.IFNA(VLOOKUP($B82,'2026年1月7日'!$B:$E,4,0),0) | L82: =K82-I82 | M82: =_xlfn.IFNA(VLOOKUP($B82,'2026年1月8日'!$B:$E,4,0),0) | N82: =M82-K82 | O82: =_xlfn.IFNA(VLOOKUP($B82,'2026年1月9日'!$B:$E,4,0),0) | P82: =O82-M82 | Q82: =_xlfn.IFNA(VLOOKUP($B82,'2026年1月10日'!$B:$E,4,0),0) | R82: =Q82-O82 | S82: =_xlfn.IFNA(VLOOKUP($B82,'2026年1月12日'!$B:$E,4,0),0) | T82: =S82-Q82 | U82: =_xlfn.IFNA(VLOOKUP($B82,'2026年1月13日'!$B:$E,4,0),0) | V82: =U82-S82 | W82: =_xlfn.IFNA(VLOOKUP($B82,'2026年1月14日'!$B:$E,4,0),0) | X82: =W82-U82 | Y82: =_xlfn.IFNA(VLOOKUP($B82,'2026年1月15日'!$B:$E,4,0),0) | Z82: =Y82-W82 | AA82: =_xlfn.IFNA(VLOOKUP($B82,'2026年1月16日'!$B:$E,4,0),0) | AB82: =AA82-W82 | AC82: =_xlfn.IFNA(VLOOKUP($B82,'2026年1月17日'!$B:$E,4,0),0) | AD82: =AC82-AA82 | AE82: =_xlfn.IFNA(VLOOKUP($B82,'2026年1月19日'!$B:$E,4,0),0) | AF82: =AE82-AC82 | AG82: =_xlfn.IFNA(VLOOKUP($B82,'2026年1月20日'!$B:$E,4,0),0) | AH82: =AG82-AE82 | AI82: =_xlfn.IFNA(VLOOKUP($B82,'2026年1月21日'!$B:$E,4,0),0) | AJ82: =AI82-AG82 | AK82: =_xlfn.IFNA(VLOOKUP($B82,'2026年1月22日'!$B:$E,4,0),0) | AL82: =AK82-AI82 | AM82: =_xlfn.IFNA(VLOOKUP($B82,'2026年1月23日'!$B:$E,4,0),0) | AN82: =AM82-AK82 | AO82: =_xlfn.IFNA(VLOOKUP($B82,'2026年1月24日'!$B:$E,4,0),0) | AP82: =AO82-AM82 | AQ82: =_xlfn.IFNA(VLOOKUP($B82,'2026年1月26日'!$B:$E,4,0),0) | AR82: =AQ82-AO82 | AS82: 71900 | AU82: 71900 | AV82: 0 | AW82: 71900 | AX82: 0 | AY82: 71900 | AZ82: 0 | BA82: 71900 | BB82: 0 | BE82: 94800 | BG82: 127800 | BH82: 33000 | BI82: 94800 | BJ82: -33000 | BK82: 71900 | BL82: -22900 | BM82: 111800 | BN82: 39900 | BO82: 139300 | BP82: 27500 | BQ82: 139300 | BR82: 0 | BS82: 151300 | BT82: 12000 | BU82: 71900 | BV82: -79400 | BW82: 71900 | BX82: 0
B83: B02047 | C83: 艾德證券期貨有限公司 | D83: =_xlfn.IFNA(VLOOKUP($B83,'2026年1月2日'!$B:$E,4,0),0) | E83: =_xlfn.IFNA(VLOOKUP($B83,'2026年1月2日'!$B:$E,4,0),0) | F83: =E83-D83 | G83: =_xlfn.IFNA(VLOOKUP($B83,'2026年1月5日'!$B:$E,4,0),0) | H83: =G83-E83 | I83: =_xlfn.IFNA(VLOOKUP($B83,'2026年1月6日'!$B:$E,4,0),0) | J83: =I83-G83 | K83: =_xlfn.IFNA(VLOOKUP($B83,'2026年1月7日'!$B:$E,4,0),0) | L83: =K83-I83 | M83: =_xlfn.IFNA(VLOOKUP($B83,'2026年1月8日'!$B:$E,4,0),0) | N83: =M83-K83 | O83: =_xlfn.IFNA(VLOOKUP($B83,'2026年1月9日'!$B:$E,4,0),0) | P83: =O83-M83 | Q83: =_xlfn.IFNA(VLOOKUP($B83,'2026年1月10日'!$B:$E,4,0),0) | R83: =Q83-O83 | S83: =_xlfn.IFNA(VLOOKUP($B83,'2026年1月12日'!$B:$E,4,0),0) | T83: =S83-Q83 | U83: =_xlfn.IFNA(VLOOKUP($B83,'2026年1月13日'!$B:$E,4,0),0) | V83: =U83-S83 | W83: =_xlfn.IFNA(VLOOKUP($B83,'2026年1月14日'!$B:$E,4,0),0) | X83: =W83-U83 | Y83: =_xlfn.IFNA(VLOOKUP($B83,'2026年1月15日'!$B:$E,4,0),0) | Z83: =Y83-W83 | AA83: =_xlfn.IFNA(VLOOKUP($B83,'2026年1月16日'!$B:$E,4,0),0) | AB83: =AA83-W83 | AC83: =_xlfn.IFNA(VLOOKUP($B83,'2026年1月17日'!$B:$E,4,0),0) | AD83: =AC83-AA83 | AE83: =_xlfn.IFNA(VLOOKUP($B83,'2026年1月19日'!$B:$E,4,0),0) | AF83: =AE83-AC83 | AG83: =_xlfn.IFNA(VLOOKUP($B83,'2026年1月20日'!$B:$E,4,0),0) | AH83: =AG83-AE83 | AI83: =_xlfn.IFNA(VLOOKUP($B83,'2026年1月21日'!$B:$E,4,0),0) | AJ83: =AI83-AG83 | AK83: =_xlfn.IFNA(VLOOKUP($B83,'2026年1月22日'!$B:$E,4,0),0) | AL83: =AK83-AI83 | AM83: =_xlfn.IFNA(VLOOKUP($B83,'2026年1月23日'!$B:$E,4,0),0) | AN83: =AM83-AK83 | AO83: =_xlfn.IFNA(VLOOKUP($B83,'2026年1月24日'!$B:$E,4,0),0) | AP83: =AO83-AM83 | AQ83: =_xlfn.IFNA(VLOOKUP($B83,'2026年1月26日'!$B:$E,4,0),0) | AR83: =AQ83-AO83 | AS83: 171800 | AU83: 171800 | AV83: 0 | AW83: 171800 | AX83: 0 | AY83: 172000 | AZ83: 200 | BA83: 172400 | BB83: 400 | BE83: 181600 | BG83: 178000 | BH83: -3600 | BI83: 181600 | BJ83: 3600 | BK83: 172000 | BL83: -9600 | BM83: 177500 | BN83: 5500 | BO83: 177400 | BP83: -100 | BQ83: 177400 | BR83: 0 | BS83: 181900 | BT83: 4500 | BU83: 172400 | BV83: -9500 | BW83: 172400 | BX83: 0
B84: B02102 | C84: 尊嘉證券國際有限公司 | D84: =_xlfn.IFNA(VLOOKUP($B84,'2026年1月2日'!$B:$E,4,0),0) | E84: =_xlfn.IFNA(VLOOKUP($B84,'2026年1月2日'!$B:$E,4,0),0) | F84: =E84-D84 | G84: =_xlfn.IFNA(VLOOKUP($B84,'2026年1月5日'!$B:$E,4,0),0) | H84: =G84-E84 | I84: =_xlfn.IFNA(VLOOKUP($B84,'2026年1月6日'!$B:$E,4,0),0) | J84: =I84-G84 | K84: =_xlfn.IFNA(VLOOKUP($B84,'2026年1月7日'!$B:$E,4,0),0) | L84: =K84-I84 | M84: =_xlfn.IFNA(VLOOKUP($B84,'2026年1月8日'!$B:$E,4,0),0) | N84: =M84-K84 | O84: =_xlfn.IFNA(VLOOKUP($B84,'2026年1月9日'!$B:$E,4,0),0) | P84: =O84-M84 | Q84: =_xlfn.IFNA(VLOOKUP($B84,'2026年1月10日'!$B:$E,4,0),0) | R84: =Q84-O84 | S84: =_xlfn.IFNA(VLOOKUP($B84,'2026年1月12日'!$B:$E,4,0),0) | T84: =S84-Q84 | U84: =_xlfn.IFNA(VLOOKUP($B84,'2026年1月13日'!$B:$E,4,0),0) | V84: =U84-S84 | W84: =_xlfn.IFNA(VLOOKUP($B84,'2026年1月14日'!$B:$E,4,0),0) | X84: =W84-U84 | Y84: =_xlfn.IFNA(VLOOKUP($B84,'2026年1月15日'!$B:$E,4,0),0) | Z84: =Y84-W84 | AA84: =_xlfn.IFNA(VLOOKUP($B84,'2026年1月16日'!$B:$E,4,0),0) | AB84: =AA84-W84 | AC84: =_xlfn.IFNA(VLOOKUP($B84,'2026年1月17日'!$B:$E,4,0),0) | AD84: =AC84-AA84 | AE84: =_xlfn.IFNA(VLOOKUP($B84,'2026年1月19日'!$B:$E,4,0),0) | AF84: =AE84-AC84 | AG84: =_xlfn.IFNA(VLOOKUP($B84,'2026年1月20日'!$B:$E,4,0),0) | AH84: =AG84-AE84 | AI84: =_xlfn.IFNA(VLOOKUP($B84,'2026年1月21日'!$B:$E,4,0),0) | AJ84: =AI84-AG84 | AK84: =_xlfn.IFNA(VLOOKUP($B84,'2026年1月22日'!$B:$E,4,0),0) | AL84: =AK84-AI84 | AM84: =_xlfn.IFNA(VLOOKUP($B84,'2026年1月23日'!$B:$E,4,0),0) | AN84: =AM84-AK84 | AO84: =_xlfn.IFNA(VLOOKUP($B84,'2026年1月24日'!$B:$E,4,0),0) | AP84: =AO84-AM84 | AQ84: =_xlfn.IFNA(VLOOKUP($B84,'2026年1月26日'!$B:$E,4,0),0) | AR84: =AQ84-AO84 | AS84: 161000 | AU84: 161000 | AV84: 0 | AW84: 160700 | AX84: -300 | AY84: 162700 | AZ84: 2000 | BA84: 160400 | BB84: -2300 | BE84: 173100 | BG84: 208100 | BH84: 35000 | BI84: 173100 | BJ84: -35000 | BK84: 162700 | BL84: -10400 | BM84: 182100 | BN84: 19400 | BO84: 142300 | BP84: -39800 | BQ84: 142300 | BR84: 0 | BS84: 209300 | BT84: 67000 | BU84: 160400 | BV84: -48900 | BW84: 160400 | BX84: 0
B85: C00074 | C85: 德意志銀行 | D85: =_xlfn.IFNA(VLOOKUP($B85,'2026年1月2日'!$B:$E,4,0),0) | E85: =_xlfn.IFNA(VLOOKUP($B85,'2026年1月2日'!$B:$E,4,0),0) | F85: =E85-D85 | G85: =_xlfn.IFNA(VLOOKUP($B85,'2026年1月5日'!$B:$E,4,0),0) | H85: =G85-E85 | I85: =_xlfn.IFNA(VLOOKUP($B85,'2026年1月6日'!$B:$E,4,0),0) | J85: =I85-G85 | K85: =_xlfn.IFNA(VLOOKUP($B85,'2026年1月7日'!$B:$E,4,0),0) | L85: =K85-I85 | M85: =_xlfn.IFNA(VLOOKUP($B85,'2026年1月8日'!$B:$E,4,0),0) | N85: =M85-K85 | O85: =_xlfn.IFNA(VLOOKUP($B85,'2026年1月9日'!$B:$E,4,0),0) | P85: =O85-M85 | Q85: =_xlfn.IFNA(VLOOKUP($B85,'2026年1月10日'!$B:$E,4,0),0) | R85: =Q85-O85 | S85: =_xlfn.IFNA(VLOOKUP($B85,'2026年1月12日'!$B:$E,4,0),0) | T85: =S85-Q85 | U85: =_xlfn.IFNA(VLOOKUP($B85,'2026年1月13日'!$B:$E,4,0),0) | V85: =U85-S85 | W85: =_xlfn.IFNA(VLOOKUP($B85,'2026年1月14日'!$B:$E,4,0),0) | X85: =W85-U85 | Y85: =_xlfn.IFNA(VLOOKUP($B85,'2026年1月15日'!$B:$E,4,0),0) | Z85: =Y85-W85 | AA85: =_xlfn.IFNA(VLOOKUP($B85,'2026年1月16日'!$B:$E,4,0),0) | AB85: =AA85-W85 | AC85: =_xlfn.IFNA(VLOOKUP($B85,'2026年1月17日'!$B:$E,4,0),0) | AD85: =AC85-AA85 | AE85: =_xlfn.IFNA(VLOOKUP($B85,'2026年1月19日'!$B:$E,4,0),0) | AF85: =AE85-AC85 | AG85: =_xlfn.IFNA(VLOOKUP($B85,'2026年1月20日'!$B:$E,4,0),0) | AH85: =AG85-AE85 | AI85: =_xlfn.IFNA(VLOOKUP($B85,'2026年1月21日'!$B:$E,4,0),0) | AJ85: =AI85-AG85 | AK85: =_xlfn.IFNA(VLOOKUP($B85,'2026年1月22日'!$B:$E,4,0),0) | AL85: =AK85-AI85 | AM85: =_xlfn.IFNA(VLOOKUP($B85,'2026年1月23日'!$B:$E,4,0),0) | AN85: =AM85-AK85 | AO85: =_xlfn.IFNA(VLOOKUP($B85,'2026年1月24日'!$B:$E,4,0),0) | AP85: =AO85-AM85 | AQ85: =_xlfn.IFNA(VLOOKUP($B85,'2026年1月26日'!$B:$E,4,0),0) | AR85: =AQ85-AO85
B86: B01341 | C86: 東泰證券有限公司 | D86: =_xlfn.IFNA(VLOOKUP($B86,'2026年1月2日'!$B:$E,4,0),0) | E86: =_xlfn.IFNA(VLOOKUP($B86,'2026年1月2日'!$B:$E,4,0),0) | F86: =E86-D86 | G86: =_xlfn.IFNA(VLOOKUP($B86,'2026年1月5日'!$B:$E,4,0),0) | H86: =G86-E86 | I86: =_xlfn.IFNA(VLOOKUP($B86,'2026年1月6日'!$B:$E,4,0),0) | J86: =I86-G86 | K86: =_xlfn.IFNA(VLOOKUP($B86,'2026年1月7日'!$B:$E,4,0),0) | L86: =K86-I86 | M86: =_xlfn.IFNA(VLOOKUP($B86,'2026年1月8日'!$B:$E,4,0),0) | N86: =M86-K86 | O86: =_xlfn.IFNA(VLOOKUP($B86,'2026年1月9日'!$B:$E,4,0),0) | P86: =O86-M86 | Q86: =_xlfn.IFNA(VLOOKUP($B86,'2026年1月10日'!$B:$E,4,0),0) | R86: =Q86-O86 | S86: =_xlfn.IFNA(VLOOKUP($B86,'2026年1月12日'!$B:$E,4,0),0) | T86: =S86-Q86 | U86: =_xlfn.IFNA(VLOOKUP($B86,'2026年1月13日'!$B:$E,4,0),0) | V86: =U86-S86 | W86: =_xlfn.IFNA(VLOOKUP($B86,'2026年1月14日'!$B:$E,4,0),0) | X86: =W86-U86 | Y86: =_xlfn.IFNA(VLOOKUP($B86,'2026年1月15日'!$B:$E,4,0),0) | Z86: =Y86-W86 | AA86: =_xlfn.IFNA(VLOOKUP($B86,'2026年1月16日'!$B:$E,4,0),0) | AB86: =AA86-W86 | AC86: =_xlfn.IFNA(VLOOKUP($B86,'2026年1月17日'!$B:$E,4,0),0) | AD86: =AC86-AA86 | AE86: =_xlfn.IFNA(VLOOKUP($B86,'2026年1月19日'!$B:$E,4,0),0) | AF86: =AE86-AC86 | AG86: =_xlfn.IFNA(VLOOKUP($B86,'2026年1月20日'!$B:$E,4,0),0) | AH86: =AG86-AE86 | AI86: =_xlfn.IFNA(VLOOKUP($B86,'2026年1月21日'!$B:$E,4,0),0) | AJ86: =AI86-AG86 | AK86: =_xlfn.IFNA(VLOOKUP($B86,'2026年1月22日'!$B:$E,4,0),0) | AL86: =AK86-AI86 | AM86: =_xlfn.IFNA(VLOOKUP($B86,'2026年1月23日'!$B:$E,4,0),0) | AN86: =AM86-AK86 | AO86: =_xlfn.IFNA(VLOOKUP($B86,'2026年1月24日'!$B:$E,4,0),0) | AP86: =AO86-AM86 | AQ86: =_xlfn.IFNA(VLOOKUP($B86,'2026年1月26日'!$B:$E,4,0),0) | AR86: =AQ86-AO86 | AS86: 30000 | AU86: 30000 | AV86: 0 | AW86: 30000 | AX86: 0 | AY86: 30000 | AZ86: 0 | BA86: 30000 | BB86: 0 | BE86: 30000 | BG86: 30000 | BH86: 0 | BI86: 30000 | BJ86: 0 | BK86: 30000 | BL86: 0 | BM86: 30000 | BN86: 0 | BO86: 30000 | BP86: 0 | BQ86: 30000 | BR86: 0 | BS86: 30000 | BT86: 0 | BU86: 30000 | BV86: 0 | BW86: 30000 | BX86: 0
B87: B01976 | C87: 方達資本管理有限公司 | D87: =_xlfn.IFNA(VLOOKUP($B87,'2026年1月2日'!$B:$E,4,0),0) | E87: =_xlfn.IFNA(VLOOKUP($B87,'2026年1月2日'!$B:$E,4,0),0) | F87: =E87-D87 | G87: =_xlfn.IFNA(VLOOKUP($B87,'2026年1月5日'!$B:$E,4,0),0) | H87: =G87-E87 | I87: =_xlfn.IFNA(VLOOKUP($B87,'2026年1月6日'!$B:$E,4,0),0) | J87: =I87-G87 | K87: =_xlfn.IFNA(VLOOKUP($B87,'2026年1月7日'!$B:$E,4,0),0) | L87: =K87-I87 | M87: =_xlfn.IFNA(VLOOKUP($B87,'2026年1月8日'!$B:$E,4,0),0) | N87: =M87-K87 | O87: =_xlfn.IFNA(VLOOKUP($B87,'2026年1月9日'!$B:$E,4,0),0) | P87: =O87-M87 | Q87: =_xlfn.IFNA(VLOOKUP($B87,'2026年1月10日'!$B:$E,4,0),0) | R87: =Q87-O87 | S87: =_xlfn.IFNA(VLOOKUP($B87,'2026年1月12日'!$B:$E,4,0),0) | T87: =S87-Q87 | U87: =_xlfn.IFNA(VLOOKUP($B87,'2026年1月13日'!$B:$E,4,0),0) | V87: =U87-S87 | W87: =_xlfn.IFNA(VLOOKUP($B87,'2026年1月14日'!$B:$E,4,0),0) | X87: =W87-U87 | Y87: =_xlfn.IFNA(VLOOKUP($B87,'2026年1月15日'!$B:$E,4,0),0) | Z87: =Y87-W87 | AA87: =_xlfn.IFNA(VLOOKUP($B87,'2026年1月16日'!$B:$E,4,0),0) | AB87: =AA87-W87 | AC87: =_xlfn.IFNA(VLOOKUP($B87,'2026年1月17日'!$B:$E,4,0),0) | AD87: =AC87-AA87 | AE87: =_xlfn.IFNA(VLOOKUP($B87,'2026年1月19日'!$B:$E,4,0),0) | AF87: =AE87-AC87 | AG87: =_xlfn.IFNA(VLOOKUP($B87,'2026年1月20日'!$B:$E,4,0),0) | AH87: =AG87-AE87 | AI87: =_xlfn.IFNA(VLOOKUP($B87,'2026年1月21日'!$B:$E,4,0),0) | AJ87: =AI87-AG87 | AK87: =_xlfn.IFNA(VLOOKUP($B87,'2026年1月22日'!$B:$E,4,0),0) | AL87: =AK87-AI87 | AM87: =_xlfn.IFNA(VLOOKUP($B87,'2026年1月23日'!$B:$E,4,0),0) | AN87: =AM87-AK87 | AO87: =_xlfn.IFNA(VLOOKUP($B87,'2026年1月24日'!$B:$E,4,0),0) | AP87: =AO87-AM87 | AQ87: =_xlfn.IFNA(VLOOKUP($B87,'2026年1月26日'!$B:$E,4,0),0) | AR87: =AQ87-AO87 | AS87: 23000 | AU87: 23000 | AV87: 0 | AW87: 23000 | AX87: 0 | AY87: 23000 | AZ87: 0 | BA87: 23000 | BB87: 0 | BE87: 299600 | BG87: 825600 | BH87: 526000 | BI87: 299600 | BJ87: -526000 | BK87: 23000 | BL87: -276600 | BM87: 1699200 | BN87: 1676200 | BU87: 23000 | BW87: 23000 | BX87: 0
B88: B01938 | C88: 興證國際證券有限公司 | D88: =_xlfn.IFNA(VLOOKUP($B88,'2026年1月2日'!$B:$E,4,0),0) | E88: =_xlfn.IFNA(VLOOKUP($B88,'2026年1月2日'!$B:$E,4,0),0) | F88: =E88-D88 | G88: =_xlfn.IFNA(VLOOKUP($B88,'2026年1月5日'!$B:$E,4,0),0) | H88: =G88-E88 | I88: =_xlfn.IFNA(VLOOKUP($B88,'2026年1月6日'!$B:$E,4,0),0) | J88: =I88-G88 | K88: =_xlfn.IFNA(VLOOKUP($B88,'2026年1月7日'!$B:$E,4,0),0) | L88: =K88-I88 | M88: =_xlfn.IFNA(VLOOKUP($B88,'2026年1月8日'!$B:$E,4,0),0) | N88: =M88-K88 | O88: =_xlfn.IFNA(VLOOKUP($B88,'2026年1月9日'!$B:$E,4,0),0) | P88: =O88-M88 | Q88: =_xlfn.IFNA(VLOOKUP($B88,'2026年1月10日'!$B:$E,4,0),0) | R88: =Q88-O88 | S88: =_xlfn.IFNA(VLOOKUP($B88,'2026年1月12日'!$B:$E,4,0),0) | T88: =S88-Q88 | U88: =_xlfn.IFNA(VLOOKUP($B88,'2026年1月13日'!$B:$E,4,0),0) | V88: =U88-S88 | W88: =_xlfn.IFNA(VLOOKUP($B88,'2026年1月14日'!$B:$E,4,0),0) | X88: =W88-U88 | Y88: =_xlfn.IFNA(VLOOKUP($B88,'2026年1月15日'!$B:$E,4,0),0) | Z88: =Y88-W88 | AA88: =_xlfn.IFNA(VLOOKUP($B88,'2026年1月16日'!$B:$E,4,0),0) | AB88: =AA88-W88 | AC88: =_xlfn.IFNA(VLOOKUP($B88,'2026年1月17日'!$B:$E,4,0),0) | AD88: =AC88-AA88 | AE88: =_xlfn.IFNA(VLOOKUP($B88,'2026年1月19日'!$B:$E,4,0),0) | AF88: =AE88-AC88 | AG88: =_xlfn.IFNA(VLOOKUP($B88,'2026年1月20日'!$B:$E,4,0),0) | AH88: =AG88-AE88 | AI88: =_xlfn.IFNA(VLOOKUP($B88,'2026年1月21日'!$B:$E,4,0),0) | AJ88: =AI88-AG88 | AK88: =_xlfn.IFNA(VLOOKUP($B88,'2026年1月22日'!$B:$E,4,0),0) | AL88: =AK88-AI88 | AM88: =_xlfn.IFNA(VLOOKUP($B88,'2026年1月23日'!$B:$E,4,0),0) | AN88: =AM88-AK88 | AO88: =_xlfn.IFNA(VLOOKUP($B88,'2026年1月24日'!$B:$E,4,0),0) | AP88: =AO88-AM88 | AQ88: =_xlfn.IFNA(VLOOKUP($B88,'2026年1月26日'!$B:$E,4,0),0) | AR88: =AQ88-AO88 | AS88: 234300 | AU88: 234300 | AV88: 0 | AW88: 234300 | AX88: 0 | AY88: 234300 | AZ88: 0 | BA88: 234300 | BB88: 0 | BE88: 291600 | BG88: 150500 | BH88: -141100 | BI88: 291600 | BJ88: 141100 | BK88: 234300 | BL88: -57300 | BM88: 231600 | BN88: -2700 | BO88: 195000 | BP88: -36600 | BQ88: 195000 | BR88: 0 | BS88: 165500 | BT88: -29500 | BU88: 234300 | BV88: 68800 | BW88: 234300 | BX88: 0
B89: B01413 | C89: 京華山一國際(香港)有限公司 | D89: =_xlfn.IFNA(VLOOKUP($B89,'2026年1月2日'!$B:$E,4,0),0) | E89: =_xlfn.IFNA(VLOOKUP($B89,'2026年1月2日'!$B:$E,4,0),0) | F89: =E89-D89 | G89: =_xlfn.IFNA(VLOOKUP($B89,'2026年1月5日'!$B:$E,4,0),0) | H89: =G89-E89 | I89: =_xlfn.IFNA(VLOOKUP($B89,'2026年1月6日'!$B:$E,4,0),0) | J89: =I89-G89 | K89: =_xlfn.IFNA(VLOOKUP($B89,'2026年1月7日'!$B:$E,4,0),0) | L89: =K89-I89 | M89: =_xlfn.IFNA(VLOOKUP($B89,'2026年1月8日'!$B:$E,4,0),0) | N89: =M89-K89 | O89: =_xlfn.IFNA(VLOOKUP($B89,'2026年1月9日'!$B:$E,4,0),0) | P89: =O89-M89 | Q89: =_xlfn.IFNA(VLOOKUP($B89,'2026年1月10日'!$B:$E,4,0),0) | R89: =Q89-O89 | S89: =_xlfn.IFNA(VLOOKUP($B89,'2026年1月12日'!$B:$E,4,0),0) | T89: =S89-Q89 | U89: =_xlfn.IFNA(VLOOKUP($B89,'2026年1月13日'!$B:$E,4,0),0) | V89: =U89-S89 | W89: =_xlfn.IFNA(VLOOKUP($B89,'2026年1月14日'!$B:$E,4,0),0) | X89: =W89-U89 | Y89: =_xlfn.IFNA(VLOOKUP($B89,'2026年1月15日'!$B:$E,4,0),0) | Z89: =Y89-W89 | AA89: =_xlfn.IFNA(VLOOKUP($B89,'2026年1月16日'!$B:$E,4,0),0) | AB89: =AA89-W89 | AC89: =_xlfn.IFNA(VLOOKUP($B89,'2026年1月17日'!$B:$E,4,0),0) | AD89: =AC89-AA89 | AE89: =_xlfn.IFNA(VLOOKUP($B89,'2026年1月19日'!$B:$E,4,0),0) | AF89: =AE89-AC89 | AG89: =_xlfn.IFNA(VLOOKUP($B89,'2026年1月20日'!$B:$E,4,0),0) | AH89: =AG89-AE89 | AI89: =_xlfn.IFNA(VLOOKUP($B89,'2026年1月21日'!$B:$E,4,0),0) | AJ89: =AI89-AG89 | AK89: =_xlfn.IFNA(VLOOKUP($B89,'2026年1月22日'!$B:$E,4,0),0) | AL89: =AK89-AI89 | AM89: =_xlfn.IFNA(VLOOKUP($B89,'2026年1月23日'!$B:$E,4,0),0) | AN89: =AM89-AK89 | AO89: =_xlfn.IFNA(VLOOKUP($B89,'2026年1月24日'!$B:$E,4,0),0) | AP89: =AO89-AM89 | AQ89: =_xlfn.IFNA(VLOOKUP($B89,'2026年1月26日'!$B:$E,4,0),0) | AR89: =AQ89-AO89 | AS89: 61900 | AU89: 61900 | AV89: 0 | AW89: 61900 | AX89: 0 | AY89: 61900 | AZ89: 0 | BA89: 61900 | BB89: 0 | BE89: 67900 | BG89: 86900 | BH89: 19000 | BI89: 67900 | BJ89: -19000 | BK89: 61900 | BL89: -6000 | BM89: 64900 | BN89: 3000 | BO89: 68900 | BP89: 4000 | BQ89: 68900 | BR89: 0 | BS89: 68900 | BT89: 0 | BU89: 61900 | BV89: -7000 | BW89: 61900 | BX89: 0
B90: B01181 | C90: 復星恆利證券有限公司 | D90: =_xlfn.IFNA(VLOOKUP($B90,'2026年1月2日'!$B:$E,4,0),0) | E90: =_xlfn.IFNA(VLOOKUP($B90,'2026年1月2日'!$B:$E,4,0),0) | F90: =E90-D90 | G90: =_xlfn.IFNA(VLOOKUP($B90,'2026年1月5日'!$B:$E,4,0),0) | H90: =G90-E90 | I90: =_xlfn.IFNA(VLOOKUP($B90,'2026年1月6日'!$B:$E,4,0),0) | J90: =I90-G90 | K90: =_xlfn.IFNA(VLOOKUP($B90,'2026年1月7日'!$B:$E,4,0),0) | L90: =K90-I90 | M90: =_xlfn.IFNA(VLOOKUP($B90,'2026年1月8日'!$B:$E,4,0),0) | N90: =M90-K90 | O90: =_xlfn.IFNA(VLOOKUP($B90,'2026年1月9日'!$B:$E,4,0),0) | P90: =O90-M90 | Q90: =_xlfn.IFNA(VLOOKUP($B90,'2026年1月10日'!$B:$E,4,0),0) | R90: =Q90-O90 | S90: =_xlfn.IFNA(VLOOKUP($B90,'2026年1月12日'!$B:$E,4,0),0) | T90: =S90-Q90 | U90: =_xlfn.IFNA(VLOOKUP($B90,'2026年1月13日'!$B:$E,4,0),0) | V90: =U90-S90 | W90: =_xlfn.IFNA(VLOOKUP($B90,'2026年1月14日'!$B:$E,4,0),0) | X90: =W90-U90 | Y90: =_xlfn.IFNA(VLOOKUP($B90,'2026年1月15日'!$B:$E,4,0),0) | Z90: =Y90-W90 | AA90: =_xlfn.IFNA(VLOOKUP($B90,'2026年1月16日'!$B:$E,4,0),0) | AB90: =AA90-W90 | AC90: =_xlfn.IFNA(VLOOKUP($B90,'2026年1月17日'!$B:$E,4,0),0) | AD90: =AC90-AA90 | AE90: =_xlfn.IFNA(VLOOKUP($B90,'2026年1月19日'!$B:$E,4,0),0) | AF90: =AE90-AC90 | AG90: =_xlfn.IFNA(VLOOKUP($B90,'2026年1月20日'!$B:$E,4,0),0) | AH90: =AG90-AE90 | AI90: =_xlfn.IFNA(VLOOKUP($B90,'2026年1月21日'!$B:$E,4,0),0) | AJ90: =AI90-AG90 | AK90: =_xlfn.IFNA(VLOOKUP($B90,'2026年1月22日'!$B:$E,4,0),0) | AL90: =AK90-AI90 | AM90: =_xlfn.IFNA(VLOOKUP($B90,'2026年1月23日'!$B:$E,4,0),0) | AN90: =AM90-AK90 | AO90: =_xlfn.IFNA(VLOOKUP($B90,'2026年1月24日'!$B:$E,4,0),0) | AP90: =AO90-AM90 | AQ90: =_xlfn.IFNA(VLOOKUP($B90,'2026年1月26日'!$B:$E,4,0),0) | AR90: =AQ90-AO90 | AS90: 207800 | AU90: 204500 | AV90: -3300 | AW90: 204500 | AX90: 0 | AY90: 204500 | AZ90: 0 | BA90: 204500 | BB90: 0 | BE90: 243800 | BG90: 316000 | BH90: 72200 | BI90: 243800 | BJ90: -72200 | BK90: 204500 | BL90: -39300 | BM90: 382800 | BN90: 178300 | BO90: 486400 | BP90: 103600 | BQ90: 486400 | BR90: 0 | BS90: 443700 | BT90: -42700 | BU90: 204500 | BV90: -239200 | BW90: 204500 | BX90: 0
B91: B01433 | C91: 興偉聯合證券有限公司 | D91: =_xlfn.IFNA(VLOOKUP($B91,'2026年1月2日'!$B:$E,4,0),0) | E91: =_xlfn.IFNA(VLOOKUP($B91,'2026年1月2日'!$B:$E,4,0),0) | F91: =E91-D91 | G91: =_xlfn.IFNA(VLOOKUP($B91,'2026年1月5日'!$B:$E,4,0),0) | H91: =G91-E91 | I91: =_xlfn.IFNA(VLOOKUP($B91,'2026年1月6日'!$B:$E,4,0),0) | J91: =I91-G91 | K91: =_xlfn.IFNA(VLOOKUP($B91,'2026年1月7日'!$B:$E,4,0),0) | L91: =K91-I91 | M91: =_xlfn.IFNA(VLOOKUP($B91,'2026年1月8日'!$B:$E,4,0),0) | N91: =M91-K91 | O91: =_xlfn.IFNA(VLOOKUP($B91,'2026年1月9日'!$B:$E,4,0),0) | P91: =O91-M91 | Q91: =_xlfn.IFNA(VLOOKUP($B91,'2026年1月10日'!$B:$E,4,0),0) | R91: =Q91-O91 | S91: =_xlfn.IFNA(VLOOKUP($B91,'2026年1月12日'!$B:$E,4,0),0) | T91: =S91-Q91 | U91: =_xlfn.IFNA(VLOOKUP($B91,'2026年1月13日'!$B:$E,4,0),0) | V91: =U91-S91 | W91: =_xlfn.IFNA(VLOOKUP($B91,'2026年1月14日'!$B:$E,4,0),0) | X91: =W91-U91 | Y91: =_xlfn.IFNA(VLOOKUP($B91,'2026年1月15日'!$B:$E,4,0),0) | Z91: =Y91-W91 | AA91: =_xlfn.IFNA(VLOOKUP($B91,'2026年1月16日'!$B:$E,4,0),0) | AB91: =AA91-W91 | AC91: =_xlfn.IFNA(VLOOKUP($B91,'2026年1月17日'!$B:$E,4,0),0) | AD91: =AC91-AA91 | AE91: =_xlfn.IFNA(VLOOKUP($B91,'2026年1月19日'!$B:$E,4,0),0) | AF91: =AE91-AC91 | AG91: =_xlfn.IFNA(VLOOKUP($B91,'2026年1月20日'!$B:$E,4,0),0) | AH91: =AG91-AE91 | AI91: =_xlfn.IFNA(VLOOKUP($B91,'2026年1月21日'!$B:$E,4,0),0) | AJ91: =AI91-AG91 | AK91: =_xlfn.IFNA(VLOOKUP($B91,'2026年1月22日'!$B:$E,4,0),0) | AL91: =AK91-AI91 | AM91: =_xlfn.IFNA(VLOOKUP($B91,'2026年1月23日'!$B:$E,4,0),0) | AN91: =AM91-AK91 | AO91: =_xlfn.IFNA(VLOOKUP($B91,'2026年1月24日'!$B:$E,4,0),0) | AP91: =AO91-AM91 | AQ91: =_xlfn.IFNA(VLOOKUP($B91,'2026年1月26日'!$B:$E,4,0),0) | AR91: =AQ91-AO91 | AS91: 14400 | AU91: 14400 | AV91: 0 | AW91: 14400 | AX91: 0 | AY91: 14400 | AZ91: 0 | BA91: 14400 | BB91: 0 | BE91: 15000 | BG91: 17800 | BH91: 2800 | BI91: 15000 | BJ91: -2800 | BK91: 14400 | BL91: -600 | BM91: 22600 | BN91: 8200 | BO91: 17800 | BP91: -4800 | BQ91: 17800 | BR91: 0 | BS91: 17800 | BT91: 0 | BU91: 14400 | BV91: -3400 | BW91: 14400 | BX91: 0
B92: B01700 | C92: 滙信理財有限公司 | D92: =_xlfn.IFNA(VLOOKUP($B92,'2026年1月2日'!$B:$E,4,0),0) | E92: =_xlfn.IFNA(VLOOKUP($B92,'2026年1月2日'!$B:$E,4,0),0) | F92: =E92-D92 | G92: =_xlfn.IFNA(VLOOKUP($B92,'2026年1月5日'!$B:$E,4,0),0) | H92: =G92-E92 | I92: =_xlfn.IFNA(VLOOKUP($B92,'2026年1月6日'!$B:$E,4,0),0) | J92: =I92-G92 | K92: =_xlfn.IFNA(VLOOKUP($B92,'2026年1月7日'!$B:$E,4,0),0) | L92: =K92-I92 | M92: =_xlfn.IFNA(VLOOKUP($B92,'2026年1月8日'!$B:$E,4,0),0) | N92: =M92-K92 | O92: =_xlfn.IFNA(VLOOKUP($B92,'2026年1月9日'!$B:$E,4,0),0) | P92: =O92-M92 | Q92: =_xlfn.IFNA(VLOOKUP($B92,'2026年1月10日'!$B:$E,4,0),0) | R92: =Q92-O92 | S92: =_xlfn.IFNA(VLOOKUP($B92,'2026年1月12日'!$B:$E,4,0),0) | T92: =S92-Q92 | U92: =_xlfn.IFNA(VLOOKUP($B92,'2026年1月13日'!$B:$E,4,0),0) | V92: =U92-S92 | W92: =_xlfn.IFNA(VLOOKUP($B92,'2026年1月14日'!$B:$E,4,0),0) | X92: =W92-U92 | Y92: =_xlfn.IFNA(VLOOKUP($B92,'2026年1月15日'!$B:$E,4,0),0) | Z92: =Y92-W92 | AA92: =_xlfn.IFNA(VLOOKUP($B92,'2026年1月16日'!$B:$E,4,0),0) | AB92: =AA92-W92 | AC92: =_xlfn.IFNA(VLOOKUP($B92,'2026年1月17日'!$B:$E,4,0),0) | AD92: =AC92-AA92 | AE92: =_xlfn.IFNA(VLOOKUP($B92,'2026年1月19日'!$B:$E,4,0),0) | AF92: =AE92-AC92 | AG92: =_xlfn.IFNA(VLOOKUP($B92,'2026年1月20日'!$B:$E,4,0),0) | AH92: =AG92-AE92 | AI92: =_xlfn.IFNA(VLOOKUP($B92,'2026年1月21日'!$B:$E,4,0),0) | AJ92: =AI92-AG92 | AK92: =_xlfn.IFNA(VLOOKUP($B92,'2026年1月22日'!$B:$E,4,0),0) | AL92: =AK92-AI92 | AM92: =_xlfn.IFNA(VLOOKUP($B92,'2026年1月23日'!$B:$E,4,0),0) | AN92: =AM92-AK92 | AO92: =_xlfn.IFNA(VLOOKUP($B92,'2026年1月24日'!$B:$E,4,0),0) | AP92: =AO92-AM92 | AQ92: =_xlfn.IFNA(VLOOKUP($B92,'2026年1月26日'!$B:$E,4,0),0) | AR92: =AQ92-AO92 | AS92: 126400 | AU92: 126400 | AV92: 0 | AW92: 126400 | AX92: 0 | AY92: 126400 | AZ92: 0 | BA92: 126400 | BB92: 0 | BE92: 131400 | BG92: 126500 | BH92: -4900 | BI92: 131400 | BJ92: 4900 | BK92: 126400 | BL92: -5000 | BM92: 126500 | BN92: 100 | BO92: 131500 | BP92: 5000 | BQ92: 131500 | BR92: 0 | BS92: 131500 | BT92: 0 | BU92: 126400 | BV92: -5100 | BW92: 126400 | BX92: 0
B93: B01915 | C93: 以太證券有限公司 | D93: =_xlfn.IFNA(VLOOKUP($B93,'2026年1月2日'!$B:$E,4,0),0) | E93: =_xlfn.IFNA(VLOOKUP($B93,'2026年1月2日'!$B:$E,4,0),0) | F93: =E93-D93 | G93: =_xlfn.IFNA(VLOOKUP($B93,'2026年1月5日'!$B:$E,4,0),0) | H93: =G93-E93 | I93: =_xlfn.IFNA(VLOOKUP($B93,'2026年1月6日'!$B:$E,4,0),0) | J93: =I93-G93 | K93: =_xlfn.IFNA(VLOOKUP($B93,'2026年1月7日'!$B:$E,4,0),0) | L93: =K93-I93 | M93: =_xlfn.IFNA(VLOOKUP($B93,'2026年1月8日'!$B:$E,4,0),0) | N93: =M93-K93 | O93: =_xlfn.IFNA(VLOOKUP($B93,'2026年1月9日'!$B:$E,4,0),0) | P93: =O93-M93 | Q93: =_xlfn.IFNA(VLOOKUP($B93,'2026年1月10日'!$B:$E,4,0),0) | R93: =Q93-O93 | S93: =_xlfn.IFNA(VLOOKUP($B93,'2026年1月12日'!$B:$E,4,0),0) | T93: =S93-Q93 | U93: =_xlfn.IFNA(VLOOKUP($B93,'2026年1月13日'!$B:$E,4,0),0) | V93: =U93-S93 | W93: =_xlfn.IFNA(VLOOKUP($B93,'2026年1月14日'!$B:$E,4,0),0) | X93: =W93-U93 | Y93: =_xlfn.IFNA(VLOOKUP($B93,'2026年1月15日'!$B:$E,4,0),0) | Z93: =Y93-W93 | AA93: =_xlfn.IFNA(VLOOKUP($B93,'2026年1月16日'!$B:$E,4,0),0) | AB93: =AA93-W93 | AC93: =_xlfn.IFNA(VLOOKUP($B93,'2026年1月17日'!$B:$E,4,0),0) | AD93: =AC93-AA93 | AE93: =_xlfn.IFNA(VLOOKUP($B93,'2026年1月19日'!$B:$E,4,0),0) | AF93: =AE93-AC93 | AG93: =_xlfn.IFNA(VLOOKUP($B93,'2026年1月20日'!$B:$E,4,0),0) | AH93: =AG93-AE93 | AI93: =_xlfn.IFNA(VLOOKUP($B93,'2026年1月21日'!$B:$E,4,0),0) | AJ93: =AI93-AG93 | AK93: =_xlfn.IFNA(VLOOKUP($B93,'2026年1月22日'!$B:$E,4,0),0) | AL93: =AK93-AI93 | AM93: =_xlfn.IFNA(VLOOKUP($B93,'2026年1月23日'!$B:$E,4,0),0) | AN93: =AM93-AK93 | AO93: =_xlfn.IFNA(VLOOKUP($B93,'2026年1月24日'!$B:$E,4,0),0) | AP93: =AO93-AM93 | AQ93: =_xlfn.IFNA(VLOOKUP($B93,'2026年1月26日'!$B:$E,4,0),0) | AR93: =AQ93-AO93 | AS93: 74300 | AU93: 74300 | AV93: 0 | AW93: 79300 | AX93: 5000 | AY93: 79300 | AZ93: 0 | BA93: 79300 | BB93: 0 | BE93: 91100 | BG93: 59400 | BH93: -31700 | BI93: 91100 | BJ93: 31700 | BK93: 79300 | BL93: -11800 | BM93: 71100 | BN93: -8200 | BO93: 61600 | BP93: -9500 | BQ93: 61600 | BR93: 0 | BS93: 60500 | BT93: -1100 | BU93: 79300 | BV93: 18800 | BW93: 79300 | BX93: 0
B94: B01298 | C94: 結好證券有限公司 | D94: =_xlfn.IFNA(VLOOKUP($B94,'2026年1月2日'!$B:$E,4,0),0) | E94: =_xlfn.IFNA(VLOOKUP($B94,'2026年1月2日'!$B:$E,4,0),0) | F94: =E94-D94 | G94: =_xlfn.IFNA(VLOOKUP($B94,'2026年1月5日'!$B:$E,4,0),0) | H94: =G94-E94 | I94: =_xlfn.IFNA(VLOOKUP($B94,'2026年1月6日'!$B:$E,4,0),0) | J94: =I94-G94 | K94: =_xlfn.IFNA(VLOOKUP($B94,'2026年1月7日'!$B:$E,4,0),0) | L94: =K94-I94 | M94: =_xlfn.IFNA(VLOOKUP($B94,'2026年1月8日'!$B:$E,4,0),0) | N94: =M94-K94 | O94: =_xlfn.IFNA(VLOOKUP($B94,'2026年1月9日'!$B:$E,4,0),0) | P94: =O94-M94 | Q94: =_xlfn.IFNA(VLOOKUP($B94,'2026年1月10日'!$B:$E,4,0),0) | R94: =Q94-O94 | S94: =_xlfn.IFNA(VLOOKUP($B94,'2026年1月12日'!$B:$E,4,0),0) | T94: =S94-Q94 | U94: =_xlfn.IFNA(VLOOKUP($B94,'2026年1月13日'!$B:$E,4,0),0) | V94: =U94-S94 | W94: =_xlfn.IFNA(VLOOKUP($B94,'2026年1月14日'!$B:$E,4,0),0) | X94: =W94-U94 | Y94: =_xlfn.IFNA(VLOOKUP($B94,'2026年1月15日'!$B:$E,4,0),0) | Z94: =Y94-W94 | AA94: =_xlfn.IFNA(VLOOKUP($B94,'2026年1月16日'!$B:$E,4,0),0) | AB94: =AA94-W94 | AC94: =_xlfn.IFNA(VLOOKUP($B94,'2026年1月17日'!$B:$E,4,0),0) | AD94: =AC94-AA94 | AE94: =_xlfn.IFNA(VLOOKUP($B94,'2026年1月19日'!$B:$E,4,0),0) | AF94: =AE94-AC94 | AG94: =_xlfn.IFNA(VLOOKUP($B94,'2026年1月20日'!$B:$E,4,0),0) | AH94: =AG94-AE94 | AI94: =_xlfn.IFNA(VLOOKUP($B94,'2026年1月21日'!$B:$E,4,0),0) | AJ94: =AI94-AG94 | AK94: =_xlfn.IFNA(VLOOKUP($B94,'2026年1月22日'!$B:$E,4,0),0) | AL94: =AK94-AI94 | AM94: =_xlfn.IFNA(VLOOKUP($B94,'2026年1月23日'!$B:$E,4,0),0) | AN94: =AM94-AK94 | AO94: =_xlfn.IFNA(VLOOKUP($B94,'2026年1月24日'!$B:$E,4,0),0) | AP94: =AO94-AM94 | AQ94: =_xlfn.IFNA(VLOOKUP($B94,'2026年1月26日'!$B:$E,4,0),0) | AR94: =AQ94-AO94 | AS94: 81000 | AU94: 78000 | AV94: -3000 | AW94: 78000 | AX94: 0 | AY94: 81400 | AZ94: 3400 | BA94: 86000 | BB94: 4600 | BE94: 78000 | BG94: 78000 | BH94: 0 | BI94: 78000 | BJ94: 0 | BK94: 81400 | BL94: 3400 | BM94: 84000 | BN94: 2600 | BO94: 58000 | BP94: -26000 | BQ94: 58000 | BR94: 0 | BS94: 63000 | BT94: 5000 | BU94: 86000 | BV94: 23000 | BW94: 86000 | BX94: 0
B95: B01169 | C95: 大眾金融証券有限公司 | D95: =_xlfn.IFNA(VLOOKUP($B95,'2026年1月2日'!$B:$E,4,0),0) | E95: =_xlfn.IFNA(VLOOKUP($B95,'2026年1月2日'!$B:$E,4,0),0) | F95: =E95-D95 | G95: =_xlfn.IFNA(VLOOKUP($B95,'2026年1月5日'!$B:$E,4,0),0) | H95: =G95-E95 | I95: =_xlfn.IFNA(VLOOKUP($B95,'2026年1月6日'!$B:$E,4,0),0) | J95: =I95-G95 | K95: =_xlfn.IFNA(VLOOKUP($B95,'2026年1月7日'!$B:$E,4,0),0) | L95: =K95-I95 | M95: =_xlfn.IFNA(VLOOKUP($B95,'2026年1月8日'!$B:$E,4,0),0) | N95: =M95-K95 | O95: =_xlfn.IFNA(VLOOKUP($B95,'2026年1月9日'!$B:$E,4,0),0) | P95: =O95-M95 | Q95: =_xlfn.IFNA(VLOOKUP($B95,'2026年1月10日'!$B:$E,4,0),0) | R95: =Q95-O95 | S95: =_xlfn.IFNA(VLOOKUP($B95,'2026年1月12日'!$B:$E,4,0),0) | T95: =S95-Q95 | U95: =_xlfn.IFNA(VLOOKUP($B95,'2026年1月13日'!$B:$E,4,0),0) | V95: =U95-S95 | W95: =_xlfn.IFNA(VLOOKUP($B95,'2026年1月14日'!$B:$E,4,0),0) | X95: =W95-U95 | Y95: =_xlfn.IFNA(VLOOKUP($B95,'2026年1月15日'!$B:$E,4,0),0) | Z95: =Y95-W95 | AA95: =_xlfn.IFNA(VLOOKUP($B95,'2026年1月16日'!$B:$E,4,0),0) | AB95: =AA95-W95 | AC95: =_xlfn.IFNA(VLOOKUP($B95,'2026年1月17日'!$B:$E,4,0),0) | AD95: =AC95-AA95 | AE95: =_xlfn.IFNA(VLOOKUP($B95,'2026年1月19日'!$B:$E,4,0),0) | AF95: =AE95-AC95 | AG95: =_xlfn.IFNA(VLOOKUP($B95,'2026年1月20日'!$B:$E,4,0),0) | AH95: =AG95-AE95 | AI95: =_xlfn.IFNA(VLOOKUP($B95,'2026年1月21日'!$B:$E,4,0),0) | AJ95: =AI95-AG95 | AK95: =_xlfn.IFNA(VLOOKUP($B95,'2026年1月22日'!$B:$E,4,0),0) | AL95: =AK95-AI95 | AM95: =_xlfn.IFNA(VLOOKUP($B95,'2026年1月23日'!$B:$E,4,0),0) | AN95: =AM95-AK95 | AO95: =_xlfn.IFNA(VLOOKUP($B95,'2026年1月24日'!$B:$E,4,0),0) | AP95: =AO95-AM95 | AQ95: =_xlfn.IFNA(VLOOKUP($B95,'2026年1月26日'!$B:$E,4,0),0) | AR95: =AQ95-AO95 | AS95: 108600 | AU95: 108600 | AV95: 0 | AW95: 108600 | AX95: 0 | AY95: 108600 | AZ95: 0 | BA95: 98700 | BB95: -9900 | BE95: 113700 | BG95: 95000 | BH95: -18700 | BI95: 113700 | BJ95: 18700 | BK95: 108600 | BL95: -5100 | BM95: 97200 | BN95: -11400 | BO95: 106300 | BP95: 9100 | BQ95: 106300 | BR95: 0 | BS95: 107100 | BT95: 800 | BU95: 98700 | BV95: -8400 | BW95: 98700 | BX95: 0
B96: B01940 | C96: SOFI SECURITIES (HONG KONG) LTD | D96: =_xlfn.IFNA(VLOOKUP($B96,'2026年1月2日'!$B:$E,4,0),0) | E96: =_xlfn.IFNA(VLOOKUP($B96,'2026年1月2日'!$B:$E,4,0),0) | F96: =E96-D96 | G96: =_xlfn.IFNA(VLOOKUP($B96,'2026年1月5日'!$B:$E,4,0),0) | H96: =G96-E96 | I96: =_xlfn.IFNA(VLOOKUP($B96,'2026年1月6日'!$B:$E,4,0),0) | J96: =I96-G96 | K96: =_xlfn.IFNA(VLOOKUP($B96,'2026年1月7日'!$B:$E,4,0),0) | L96: =K96-I96 | M96: =_xlfn.IFNA(VLOOKUP($B96,'2026年1月8日'!$B:$E,4,0),0) | N96: =M96-K96 | O96: =_xlfn.IFNA(VLOOKUP($B96,'2026年1月9日'!$B:$E,4,0),0) | P96: =O96-M96 | Q96: =_xlfn.IFNA(VLOOKUP($B96,'2026年1月10日'!$B:$E,4,0),0) | R96: =Q96-O96 | S96: =_xlfn.IFNA(VLOOKUP($B96,'2026年1月12日'!$B:$E,4,0),0) | T96: =S96-Q96 | U96: =_xlfn.IFNA(VLOOKUP($B96,'2026年1月13日'!$B:$E,4,0),0) | V96: =U96-S96 | W96: =_xlfn.IFNA(VLOOKUP($B96,'2026年1月14日'!$B:$E,4,0),0) | X96: =W96-U96 | Y96: =_xlfn.IFNA(VLOOKUP($B96,'2026年1月15日'!$B:$E,4,0),0) | Z96: =Y96-W96 | AA96: =_xlfn.IFNA(VLOOKUP($B96,'2026年1月16日'!$B:$E,4,0),0) | AB96: =AA96-W96 | AC96: =_xlfn.IFNA(VLOOKUP($B96,'2026年1月17日'!$B:$E,4,0),0) | AD96: =AC96-AA96 | AE96: =_xlfn.IFNA(VLOOKUP($B96,'2026年1月19日'!$B:$E,4,0),0) | AF96: =AE96-AC96 | AG96: =_xlfn.IFNA(VLOOKUP($B96,'2026年1月20日'!$B:$E,4,0),0) | AH96: =AG96-AE96 | AI96: =_xlfn.IFNA(VLOOKUP($B96,'2026年1月21日'!$B:$E,4,0),0) | AJ96: =AI96-AG96 | AK96: =_xlfn.IFNA(VLOOKUP($B96,'2026年1月22日'!$B:$E,4,0),0) | AL96: =AK96-AI96 | AM96: =_xlfn.IFNA(VLOOKUP($B96,'2026年1月23日'!$B:$E,4,0),0) | AN96: =AM96-AK96 | AO96: =_xlfn.IFNA(VLOOKUP($B96,'2026年1月24日'!$B:$E,4,0),0) | AP96: =AO96-AM96 | AQ96: =_xlfn.IFNA(VLOOKUP($B96,'2026年1月26日'!$B:$E,4,0),0) | AR96: =AQ96-AO96 | AS96: 116500 | AU96: 116500 | AV96: 0 | AW96: 116500 | AX96: 0 | AY96: 116500 | AZ96: 0 | BA96: 115800 | BB96: -700 | BE96: 108200 | BG96: 88000 | BH96: -20200 | BI96: 108200 | BJ96: 20200 | BK96: 116500 | BL96: 8300 | BM96: 83200 | BN96: -33300 | BO96: 88000 | BP96: 4800 | BQ96: 88000 | BR96: 0 | BS96: 110100 | BT96: 22100 | BU96: 115800 | BV96: 5700 | BW96: 115800 | BX96: 0
B97: B01858 | C97: 元大證券(香港)有限公司 | D97: =_xlfn.IFNA(VLOOKUP($B97,'2026年1月2日'!$B:$E,4,0),0) | E97: =_xlfn.IFNA(VLOOKUP($B97,'2026年1月2日'!$B:$E,4,0),0) | F97: =E97-D97 | G97: =_xlfn.IFNA(VLOOKUP($B97,'2026年1月5日'!$B:$E,4,0),0) | H97: =G97-E97 | I97: =_xlfn.IFNA(VLOOKUP($B97,'2026年1月6日'!$B:$E,4,0),0) | J97: =I97-G97 | K97: =_xlfn.IFNA(VLOOKUP($B97,'2026年1月7日'!$B:$E,4,0),0) | L97: =K97-I97 | M97: =_xlfn.IFNA(VLOOKUP($B97,'2026年1月8日'!$B:$E,4,0),0) | N97: =M97-K97 | O97: =_xlfn.IFNA(VLOOKUP($B97,'2026年1月9日'!$B:$E,4,0),0) | P97: =O97-M97 | Q97: =_xlfn.IFNA(VLOOKUP($B97,'2026年1月10日'!$B:$E,4,0),0) | R97: =Q97-O97 | S97: =_xlfn.IFNA(VLOOKUP($B97,'2026年1月12日'!$B:$E,4,0),0) | T97: =S97-Q97 | U97: =_xlfn.IFNA(VLOOKUP($B97,'2026年1月13日'!$B:$E,4,0),0) | V97: =U97-S97 | W97: =_xlfn.IFNA(VLOOKUP($B97,'2026年1月14日'!$B:$E,4,0),0) | X97: =W97-U97 | Y97: =_xlfn.IFNA(VLOOKUP($B97,'2026年1月15日'!$B:$E,4,0),0) | Z97: =Y97-W97 | AA97: =_xlfn.IFNA(VLOOKUP($B97,'2026年1月16日'!$B:$E,4,0),0) | AB97: =AA97-W97 | AC97: =_xlfn.IFNA(VLOOKUP($B97,'2026年1月17日'!$B:$E,4,0),0) | AD97: =AC97-AA97 | AE97: =_xlfn.IFNA(VLOOKUP($B97,'2026年1月19日'!$B:$E,4,0),0) | AF97: =AE97-AC97 | AG97: =_xlfn.IFNA(VLOOKUP($B97,'2026年1月20日'!$B:$E,4,0),0) | AH97: =AG97-AE97 | AI97: =_xlfn.IFNA(VLOOKUP($B97,'2026年1月21日'!$B:$E,4,0),0) | AJ97: =AI97-AG97 | AK97: =_xlfn.IFNA(VLOOKUP($B97,'2026年1月22日'!$B:$E,4,0),0) | AL97: =AK97-AI97 | AM97: =_xlfn.IFNA(VLOOKUP($B97,'2026年1月23日'!$B:$E,4,0),0) | AN97: =AM97-AK97 | AO97: =_xlfn.IFNA(VLOOKUP($B97,'2026年1月24日'!$B:$E,4,0),0) | AP97: =AO97-AM97 | AQ97: =_xlfn.IFNA(VLOOKUP($B97,'2026年1月26日'!$B:$E,4,0),0) | AR97: =AQ97-AO97 | AS97: 935000 | AU97: 935000 | AV97: 0 | AW97: 935000 | AX97: 0 | AY97: 935000 | AZ97: 0 | BA97: 935500 | BB97: 500 | BE97: 944100 | BG97: 1804900 | BH97: 860800 | BI97: 944100 | BJ97: -860800 | BK97: 935000 | BL97: -9100 | BM97: 1815900 | BN97: 880900 | BO97: 1781300 | BP97: -34600 | BQ97: 1781300 | BR97: 0 | BS97: 1802200 | BT97: 20900 | BU97: 935500 | BV97: -866700 | BW97: 935500 | BX97: 0
B98: B01546 | C98: 和豐證券有限公司 | D98: =_xlfn.IFNA(VLOOKUP($B98,'2026年1月2日'!$B:$E,4,0),0) | E98: =_xlfn.IFNA(VLOOKUP($B98,'2026年1月2日'!$B:$E,4,0),0) | F98: =E98-D98 | G98: =_xlfn.IFNA(VLOOKUP($B98,'2026年1月5日'!$B:$E,4,0),0) | H98: =G98-E98 | I98: =_xlfn.IFNA(VLOOKUP($B98,'2026年1月6日'!$B:$E,4,0),0) | J98: =I98-G98 | K98: =_xlfn.IFNA(VLOOKUP($B98,'2026年1月7日'!$B:$E,4,0),0) | L98: =K98-I98 | M98: =_xlfn.IFNA(VLOOKUP($B98,'2026年1月8日'!$B:$E,4,0),0) | N98: =M98-K98 | O98: =_xlfn.IFNA(VLOOKUP($B98,'2026年1月9日'!$B:$E,4,0),0) | P98: =O98-M98 | Q98: =_xlfn.IFNA(VLOOKUP($B98,'2026年1月10日'!$B:$E,4,0),0) | R98: =Q98-O98 | S98: =_xlfn.IFNA(VLOOKUP($B98,'2026年1月12日'!$B:$E,4,0),0) | T98: =S98-Q98 | U98: =_xlfn.IFNA(VLOOKUP($B98,'2026年1月13日'!$B:$E,4,0),0) | V98: =U98-S98 | W98: =_xlfn.IFNA(VLOOKUP($B98,'2026年1月14日'!$B:$E,4,0),0) | X98: =W98-U98 | Y98: =_xlfn.IFNA(VLOOKUP($B98,'2026年1月15日'!$B:$E,4,0),0) | Z98: =Y98-W98 | AA98: =_xlfn.IFNA(VLOOKUP($B98,'2026年1月16日'!$B:$E,4,0),0) | AB98: =AA98-W98 | AC98: =_xlfn.IFNA(VLOOKUP($B98,'2026年1月17日'!$B:$E,4,0),0) | AD98: =AC98-AA98 | AE98: =_xlfn.IFNA(VLOOKUP($B98,'2026年1月19日'!$B:$E,4,0),0) | AF98: =AE98-AC98 | AG98: =_xlfn.IFNA(VLOOKUP($B98,'2026年1月20日'!$B:$E,4,0),0) | AH98: =AG98-AE98 | AI98: =_xlfn.IFNA(VLOOKUP($B98,'2026年1月21日'!$B:$E,4,0),0) | AJ98: =AI98-AG98 | AK98: =_xlfn.IFNA(VLOOKUP($B98,'2026年1月22日'!$B:$E,4,0),0) | AL98: =AK98-AI98 | AM98: =_xlfn.IFNA(VLOOKUP($B98,'2026年1月23日'!$B:$E,4,0),0) | AN98: =AM98-AK98 | AO98: =_xlfn.IFNA(VLOOKUP($B98,'2026年1月24日'!$B:$E,4,0),0) | AP98: =AO98-AM98 | AQ98: =_xlfn.IFNA(VLOOKUP($B98,'2026年1月26日'!$B:$E,4,0),0) | AR98: =AQ98-AO98 | AS98: 52400 | AU98: 52400 | AV98: 0 | AW98: 52400 | AX98: 0 | AY98: 55400 | AZ98: 3000 | BA98: 55400 | BB98: 0 | BE98: 62400 | BG98: 64600 | BH98: 2200 | BI98: 62400 | BJ98: -2200 | BK98: 55400 | BL98: -7000 | BM98: 164400 | BN98: 109000 | BO98: 64600 | BP98: -99800 | BQ98: 64600 | BR98: 0 | BS98: 64600 | BT98: 0 | BU98: 55400 | BV98: -9200 | BW98: 55400 | BX98: 0
B99: B01275 | C99: 新富證券有限公司 | D99: =_xlfn.IFNA(VLOOKUP($B99,'2026年1月2日'!$B:$E,4,0),0) | E99: =_xlfn.IFNA(VLOOKUP($B99,'2026年1月2日'!$B:$E,4,0),0) | F99: =E99-D99 | G99: =_xlfn.IFNA(VLOOKUP($B99,'2026年1月5日'!$B:$E,4,0),0) | H99: =G99-E99 | I99: =_xlfn.IFNA(VLOOKUP($B99,'2026年1月6日'!$B:$E,4,0),0) | J99: =I99-G99 | K99: =_xlfn.IFNA(VLOOKUP($B99,'2026年1月7日'!$B:$E,4,0),0) | L99: =K99-I99 | M99: =_xlfn.IFNA(VLOOKUP($B99,'2026年1月8日'!$B:$E,4,0),0) | N99: =M99-K99 | O99: =_xlfn.IFNA(VLOOKUP($B99,'2026年1月9日'!$B:$E,4,0),0) | P99: =O99-M99 | Q99: =_xlfn.IFNA(VLOOKUP($B99,'2026年1月10日'!$B:$E,4,0),0) | R99: =Q99-O99 | S99: =_xlfn.IFNA(VLOOKUP($B99,'2026年1月12日'!$B:$E,4,0),0) | T99: =S99-Q99 | U99: =_xlfn.IFNA(VLOOKUP($B99,'2026年1月13日'!$B:$E,4,0),0) | V99: =U99-S99 | W99: =_xlfn.IFNA(VLOOKUP($B99,'2026年1月14日'!$B:$E,4,0),0) | X99: =W99-U99 | Y99: =_xlfn.IFNA(VLOOKUP($B99,'2026年1月15日'!$B:$E,4,0),0) | Z99: =Y99-W99 | AA99: =_xlfn.IFNA(VLOOKUP($B99,'2026年1月16日'!$B:$E,4,0),0) | AB99: =AA99-W99 | AC99: =_xlfn.IFNA(VLOOKUP($B99,'2026年1月17日'!$B:$E,4,0),0) | AD99: =AC99-AA99 | AE99: =_xlfn.IFNA(VLOOKUP($B99,'2026年1月19日'!$B:$E,4,0),0) | AF99: =AE99-AC99 | AG99: =_xlfn.IFNA(VLOOKUP($B99,'2026年1月20日'!$B:$E,4,0),0) | AH99: =AG99-AE99 | AI99: =_xlfn.IFNA(VLOOKUP($B99,'2026年1月21日'!$B:$E,4,0),0) | AJ99: =AI99-AG99 | AK99: =_xlfn.IFNA(VLOOKUP($B99,'2026年1月22日'!$B:$E,4,0),0) | AL99: =AK99-AI99 | AM99: =_xlfn.IFNA(VLOOKUP($B99,'2026年1月23日'!$B:$E,4,0),0) | AN99: =AM99-AK99 | AO99: =_xlfn.IFNA(VLOOKUP($B99,'2026年1月24日'!$B:$E,4,0),0) | AP99: =AO99-AM99 | AQ99: =_xlfn.IFNA(VLOOKUP($B99,'2026年1月26日'!$B:$E,4,0),0) | AR99: =AQ99-AO99 | AS99: 331700 | AU99: 331700 | AV99: 0 | AW99: 331700 | AX99: 0 | AY99: 331700 | AZ99: 0 | BA99: 331700 | BB99: 0 | BE99: 331700 | BG99: 347200 | BH99: 15500 | BI99: 331700 | BJ99: -15500 | BK99: 331700 | BL99: 0 | BM99: 316700 | BN99: -15000 | BO99: 173200 | BP99: -143500 | BQ99: 173200 | BR99: 0 | BS99: 293200 | BT99: 120000 | BU99: 331700 | BV99: 38500 | BW99: 331700 | BX99: 0
... B106: B01425 | C106: 偉富證券有限公司 | D106: =_xlfn.IFNA(VLOOKUP($B106,'2026年1月2日'!$B:$E,4,0),0) | E106: =_xlfn.IFNA(VLOOKUP($B106,'2026年1月2日'!$B:$E,4,0),0) | F106: =E106-D106 | G106: =_xlfn.IFNA(VLOOKUP($B106,'2026年1月5日'!$B:$E,4,0),0) | H106: =G106-E106 | I106: =_xlfn.IFNA(VLOOKUP($B106,'2026年1月6日'!$B:$E,4,0),0) | J106: =I106-G106 | K106: =_xlfn.IFNA(VLOOKUP($B106,'2026年1月7日'!$B:$E,4,0),0) | L106: =K106-I106 | M106: =_xlfn.IFNA(VLOOKUP($B106,'2026年1月8日'!$B:$E,4,0),0) | N106: =M106-K106 | O106: =_xlfn.IFNA(VLOOKUP($B106,'2026年1月9日'!$B:$E,4,0),0) | P106: =O106-M106 | Q106: =_xlfn.IFNA(VLOOKUP($B106,'2026年1月10日'!$B:$E,4,0),0) | R106: =Q106-O106 | S106: =_xlfn.IFNA(VLOOKUP($B106,'2026年1月12日'!$B:$E,4,0),0) | T106: =S106-Q106 | U106: =_xlfn.IFNA(VLOOKUP($B106,'2026年1月13日'!$B:$E,4,0),0) | V106: =U106-S106 | W106: =_xlfn.IFNA(VLOOKUP($B106,'2026年1月14日'!$B:$E,4,0),0) | X106: =W106-U106 | Y106: =_xlfn.IFNA(VLOOKUP($B106,'2026年1月15日'!$B:$E,4,0),0) | Z106: =Y106-W106 | AA106: =_xlfn.IFNA(VLOOKUP($B106,'2026年1月16日'!$B:$E,4,0),0) | AB106: =AA106-W106 | AC106: =_xlfn.IFNA(VLOOKUP($B106,'2026年1月17日'!$B:$E,4,0),0) | AD106: =AC106-AA106 | AE106: =_xlfn.IFNA(VLOOKUP($B106,'2026年1月19日'!$B:$E,4,0),0) | AF106: =AE106-AC106 | AG106: =_xlfn.IFNA(VLOOKUP($B106,'2026年1月20日'!$B:$E,4,0),0) | AH106: =AG106-AE106 | AI106: =_xlfn.IFNA(VLOOKUP($B106,'2026年1月21日'!$B:$E,4,0),0) | AJ106: =AI106-AG106 | AK106: =_xlfn.IFNA(VLOOKUP($B106,'2026年1月22日'!$B:$E,4,0),0) | AL106: =AK106-AI106 | AM106: =_xlfn.IFNA(VLOOKUP($B106,'2026年1月23日'!$B:$E,4,0),0) | AN106: =AM106-AK106 | AO106: =_xlfn.IFNA(VLOOKUP($B106,'2026年1月24日'!$B:$E,4,0),0) | AP106: =AO106-AM106 | AQ106: =_xlfn.IFNA(VLOOKUP($B106,'2026年1月26日'!$B:$E,4,0),0) | AR106: =AQ106-AO106 | AS106: 1700 | AU106: 1700 | AV106: 0 | AW106: 1700 | AX106: 0 | AY106: 1700 | AZ106: 0 | BA106: 1700 | BB106: 0 | BE106: 51700 | BG106: 51700 | BH106: 0 | BI106: 51700 | BJ106: 0 | BK106: 1700 | BL106: -50000 | BM106: 51700 | BN106: 50000 | BO106: 51700 | BP106: 0 | BQ106: 51700 | BR106: 0 | BS106: 51700 | BT106: 0 | BU106: 1700 | BV106: -50000 | BW106: 1700 | BX106: 0
B107: B01259 | C107: 天發證券有限公司 | D107: =_xlfn.IFNA(VLOOKUP($B107,'2026年1月2日'!$B:$E,4,0),0) | E107: =_xlfn.IFNA(VLOOKUP($B107,'2026年1月2日'!$B:$E,4,0),0) | F107: =E107-D107 | G107: =_xlfn.IFNA(VLOOKUP($B107,'2026年1月5日'!$B:$E,4,0),0) | H107: =G107-E107 | I107: =_xlfn.IFNA(VLOOKUP($B107,'2026年1月6日'!$B:$E,4,0),0) | J107: =I107-G107 | K107: =_xlfn.IFNA(VLOOKUP($B107,'2026年1月7日'!$B:$E,4,0),0) | L107: =K107-I107 | M107: =_xlfn.IFNA(VLOOKUP($B107,'2026年1月8日'!$B:$E,4,0),0) | N107: =M107-K107 | O107: =_xlfn.IFNA(VLOOKUP($B107,'2026年1月9日'!$B:$E,4,0),0) | P107: =O107-M107 | Q107: =_xlfn.IFNA(VLOOKUP($B107,'2026年1月10日'!$B:$E,4,0),0) | R107: =Q107-O107 | S107: =_xlfn.IFNA(VLOOKUP($B107,'2026年1月12日'!$B:$E,4,0),0) | T107: =S107-Q107 | U107: =_xlfn.IFNA(VLOOKUP($B107,'2026年1月13日'!$B:$E,4,0),0) | V107: =U107-S107 | W107: =_xlfn.IFNA(VLOOKUP($B107,'2026年1月14日'!$B:$E,4,0),0) | X107: =W107-U107 | Y107: =_xlfn.IFNA(VLOOKUP($B107,'2026年1月15日'!$B:$E,4,0),0) | Z107: =Y107-W107 | AA107: =_xlfn.IFNA(VLOOKUP($B107,'2026年1月16日'!$B:$E,4,0),0) | AB107: =AA107-W107 | AC107: =_xlfn.IFNA(VLOOKUP($B107,'2026年1月17日'!$B:$E,4,0),0) | AD107: =AC107-AA107 | AE107: =_xlfn.IFNA(VLOOKUP($B107,'2026年1月19日'!$B:$E,4,0),0) | AF107: =AE107-AC107 | AG107: =_xlfn.IFNA(VLOOKUP($B107,'2026年1月20日'!$B:$E,4,0),0) | AH107: =AG107-AE107 | AI107: =_xlfn.IFNA(VLOOKUP($B107,'2026年1月21日'!$B:$E,4,0),0) | AJ107: =AI107-AG107 | AK107: =_xlfn.IFNA(VLOOKUP($B107,'2026年1月22日'!$B:$E,4,0),0) | AL107: =AK107-AI107 | AM107: =_xlfn.IFNA(VLOOKUP($B107,'2026年1月23日'!$B:$E,4,0),0) | AN107: =AM107-AK107 | AO107: =_xlfn.IFNA(VLOOKUP($B107,'2026年1月24日'!$B:$E,4,0),0) | AP107: =AO107-AM107 | AQ107: =_xlfn.IFNA(VLOOKUP($B107,'2026年1月26日'!$B:$E,4,0),0) | AR107: =AQ107-AO107
B108: B01224 | C108: MLFE LTD | D108: =_xlfn.IFNA(VLOOKUP($B108,'2026年1月2日'!$B:$E,4,0),0) | E108: =_xlfn.IFNA(VLOOKUP($B108,'2026年1月2日'!$B:$E,4,0),0) | F108: =E108-D108 | G108: =_xlfn.IFNA(VLOOKUP($B108,'2026年1月5日'!$B:$E,4,0),0) | H108: =G108-E108 | I108: =_xlfn.IFNA(VLOOKUP($B108,'2026年1月6日'!$B:$E,4,0),0) | J108: =I108-G108 | K108: =_xlfn.IFNA(VLOOKUP($B108,'2026年1月7日'!$B:$E,4,0),0) | L108: =K108-I108 | M108: =_xlfn.IFNA(VLOOKUP($B108,'2026年1月8日'!$B:$E,4,0),0) | N108: =M108-K108 | O108: =_xlfn.IFNA(VLOOKUP($B108,'2026年1月9日'!$B:$E,4,0),0) | P108: =O108-M108 | Q108: =_xlfn.IFNA(VLOOKUP($B108,'2026年1月10日'!$B:$E,4,0),0) | R108: =Q108-O108 | S108: =_xlfn.IFNA(VLOOKUP($B108,'2026年1月12日'!$B:$E,4,0),0) | T108: =S108-Q108 | U108: =_xlfn.IFNA(VLOOKUP($B108,'2026年1月13日'!$B:$E,4,0),0) | V108: =U108-S108 | W108: =_xlfn.IFNA(VLOOKUP($B108,'2026年1月14日'!$B:$E,4,0),0) | X108: =W108-U108 | Y108: =_xlfn.IFNA(VLOOKUP($B108,'2026年1月15日'!$B:$E,4,0),0) | Z108: =Y108-W108 | AA108: =_xlfn.IFNA(VLOOKUP($B108,'2026年1月16日'!$B:$E,4,0),0) | AB108: =AA108-W108 | AC108: =_xlfn.IFNA(VLOOKUP($B108,'2026年1月17日'!$B:$E,4,0),0) | AD108: =AC108-AA108 | AE108: =_xlfn.IFNA(VLOOKUP($B108,'2026年1月19日'!$B:$E,4,0),0) | AF108: =AE108-AC108 | AG108: =_xlfn.IFNA(VLOOKUP($B108,'2026年1月20日'!$B:$E,4,0),0) | AH108: =AG108-AE108 | AI108: =_xlfn.IFNA(VLOOKUP($B108,'2026年1月21日'!$B:$E,4,0),0) | AJ108: =AI108-AG108 | AK108: =_xlfn.IFNA(VLOOKUP($B108,'2026年1月22日'!$B:$E,4,0),0) | AL108: =AK108-AI108 | AM108: =_xlfn.IFNA(VLOOKUP($B108,'2026年1月23日'!$B:$E,4,0),0) | AN108: =AM108-AK108 | AO108: =_xlfn.IFNA(VLOOKUP($B108,'2026年1月24日'!$B:$E,4,0),0) | AP108: =AO108-AM108 | AQ108: =_xlfn.IFNA(VLOOKUP($B108,'2026年1月26日'!$B:$E,4,0),0) | AR108: =AQ108-AO108 | AS108: 268733 | AU108: 37900 | AV108: -230833 | AW108: 490500 | AX108: 452600 | AY108: 106700 | AZ108: -383800 | BA108: 57600 | BB108: -49100 | BE108: 1047512 | BG108: 84200 | BH108: -963312 | BI108: 1047512 | BJ108: 963312 | BK108: 106700 | BL108: -940812 | BM108: 1128872 | BN108: 1022172 | BO108: 379600 | BP108: -749272 | BQ108: 379600 | BR108: 0 | BS108: 546800 | BT108: 167200 | BU108: 57600 | BV108: -489200 | BW108: 57600 | BX108: 0
B109: B01523 | C109: 長雄證券有限公司 | D109: =_xlfn.IFNA(VLOOKUP($B109,'2026年1月2日'!$B:$E,4,0),0) | E109: =_xlfn.IFNA(VLOOKUP($B109,'2026年1月2日'!$B:$E,4,0),0) | F109: =E109-D109 | G109: =_xlfn.IFNA(VLOOKUP($B109,'2026年1月5日'!$B:$E,4,0),0) | H109: =G109-E109 | I109: =_xlfn.IFNA(VLOOKUP($B109,'2026年1月6日'!$B:$E,4,0),0) | J109: =I109-G109 | K109: =_xlfn.IFNA(VLOOKUP($B109,'2026年1月7日'!$B:$E,4,0),0) | L109: =K109-I109 | M109: =_xlfn.IFNA(VLOOKUP($B109,'2026年1月8日'!$B:$E,4,0),0) | N109: =M109-K109 | O109: =_xlfn.IFNA(VLOOKUP($B109,'2026年1月9日'!$B:$E,4,0),0) | P109: =O109-M109 | Q109: =_xlfn.IFNA(VLOOKUP($B109,'2026年1月10日'!$B:$E,4,0),0) | R109: =Q109-O109 | S109: =_xlfn.IFNA(VLOOKUP($B109,'2026年1月12日'!$B:$E,4,0),0) | T109: =S109-Q109 | U109: =_xlfn.IFNA(VLOOKUP($B109,'2026年1月13日'!$B:$E,4,0),0) | V109: =U109-S109 | W109: =_xlfn.IFNA(VLOOKUP($B109,'2026年1月14日'!$B:$E,4,0),0) | X109: =W109-U109 | Y109: =_xlfn.IFNA(VLOOKUP($B109,'2026年1月15日'!$B:$E,4,0),0) | Z109: =Y109-W109 | AA109: =_xlfn.IFNA(VLOOKUP($B109,'2026年1月16日'!$B:$E,4,0),0) | AB109: =AA109-W109 | AC109: =_xlfn.IFNA(VLOOKUP($B109,'2026年1月17日'!$B:$E,4,0),0) | AD109: =AC109-AA109 | AE109: =_xlfn.IFNA(VLOOKUP($B109,'2026年1月19日'!$B:$E,4,0),0) | AF109: =AE109-AC109 | AG109: =_xlfn.IFNA(VLOOKUP($B109,'2026年1月20日'!$B:$E,4,0),0) | AH109: =AG109-AE109 | AI109: =_xlfn.IFNA(VLOOKUP($B109,'2026年1月21日'!$B:$E,4,0),0) | AJ109: =AI109-AG109 | AK109: =_xlfn.IFNA(VLOOKUP($B109,'2026年1月22日'!$B:$E,4,0),0) | AL109: =AK109-AI109 | AM109: =_xlfn.IFNA(VLOOKUP($B109,'2026年1月23日'!$B:$E,4,0),0) | AN109: =AM109-AK109 | AO109: =_xlfn.IFNA(VLOOKUP($B109,'2026年1月24日'!$B:$E,4,0),0) | AP109: =AO109-AM109 | AQ109: =_xlfn.IFNA(VLOOKUP($B109,'2026年1月26日'!$B:$E,4,0),0) | AR109: =AQ109-AO109 | AS109: 126900 | AU109: 126900 | AV109: 0 | AW109: 126900 | AX109: 0 | AY109: 126900 | AZ109: 0 | BA109: 126900 | BB109: 0 | BE109: 166900 | BG109: 146900 | BH109: -20000 | BI109: 166900 | BJ109: 20000 | BK109: 126900 | BL109: -40000 | BM109: 162900 | BN109: 36000 | BO109: 126900 | BP109: -36000 | BQ109: 126900 | BR109: 0 | BS109: 141900 | BT109: 15000 | BU109: 126900 | BV109: -15000 | BW109: 126900 | BX109: 0
B110: B01843 | C110: 電訊濎匯證券有限公司 | D110: =_xlfn.IFNA(VLOOKUP($B110,'2026年1月2日'!$B:$E,4,0),0) | E110: =_xlfn.IFNA(VLOOKUP($B110,'2026年1月2日'!$B:$E,4,0),0) | F110: =E110-D110 | G110: =_xlfn.IFNA(VLOOKUP($B110,'2026年1月5日'!$B:$E,4,0),0) | H110: =G110-E110 | I110: =_xlfn.IFNA(VLOOKUP($B110,'2026年1月6日'!$B:$E,4,0),0) | J110: =I110-G110 | K110: =_xlfn.IFNA(VLOOKUP($B110,'2026年1月7日'!$B:$E,4,0),0) | L110: =K110-I110 | M110: =_xlfn.IFNA(VLOOKUP($B110,'2026年1月8日'!$B:$E,4,0),0) | N110: =M110-K110 | O110: =_xlfn.IFNA(VLOOKUP($B110,'2026年1月9日'!$B:$E,4,0),0) | P110: =O110-M110 | Q110: =_xlfn.IFNA(VLOOKUP($B110,'2026年1月10日'!$B:$E,4,0),0) | R110: =Q110-O110 | S110: =_xlfn.IFNA(VLOOKUP($B110,'2026年1月12日'!$B:$E,4,0),0) | T110: =S110-Q110 | U110: =_xlfn.IFNA(VLOOKUP($B110,'2026年1月13日'!$B:$E,4,0),0) | V110: =U110-S110 | W110: =_xlfn.IFNA(VLOOKUP($B110,'2026年1月14日'!$B:$E,4,0),0) | X110: =W110-U110 | Y110: =_xlfn.IFNA(VLOOKUP($B110,'2026年1月15日'!$B:$E,4,0),0) | Z110: =Y110-W110 | AA110: =_xlfn.IFNA(VLOOKUP($B110,'2026年1月16日'!$B:$E,4,0),0) | AB110: =AA110-W110 | AC110: =_xlfn.IFNA(VLOOKUP($B110,'2026年1月17日'!$B:$E,4,0),0) | AD110: =AC110-AA110 | AE110: =_xlfn.IFNA(VLOOKUP($B110,'2026年1月19日'!$B:$E,4,0),0) | AF110: =AE110-AC110 | AG110: =_xlfn.IFNA(VLOOKUP($B110,'2026年1月20日'!$B:$E,4,0),0) | AH110: =AG110-AE110 | AI110: =_xlfn.IFNA(VLOOKUP($B110,'2026年1月21日'!$B:$E,4,0),0) | AJ110: =AI110-AG110 | AK110: =_xlfn.IFNA(VLOOKUP($B110,'2026年1月22日'!$B:$E,4,0),0) | AL110: =AK110-AI110 | AM110: =_xlfn.IFNA(VLOOKUP($B110,'2026年1月23日'!$B:$E,4,0),0) | AN110: =AM110-AK110 | AO110: =_xlfn.IFNA(VLOOKUP($B110,'2026年1月24日'!$B:$E,4,0),0) | AP110: =AO110-AM110 | AQ110: =_xlfn.IFNA(VLOOKUP($B110,'2026年1月26日'!$B:$E,4,0),0) | AR110: =AQ110-AO110 | AS110: 115900 | AU110: 115900 | AV110: 0 | AW110: 115900 | AX110: 0 | AY110: 65300 | AZ110: -50600 | BA110: 45300 | BB110: -20000 | BE110: 100800 | BG110: 81200 | BH110: -19600 | BI110: 100800 | BJ110: 19600 | BK110: 65300 | BL110: -35500 | BM110: 28000 | BN110: -37300 | BO110: 33800 | BP110: 5800 | BQ110: 33800 | BR110: 0 | BS110: 92600 | BT110: 58800 | BU110: 45300 | BV110: -47300 | BW110: 45300 | BX110: 0
B111: B02175 | C111: 微牛證券有限公司 | D111: =_xlfn.IFNA(VLOOKUP($B111,'2026年1月2日'!$B:$E,4,0),0) | E111: =_xlfn.IFNA(VLOOKUP($B111,'2026年1月2日'!$B:$E,4,0),0) | F111: =E111-D111 | G111: =_xlfn.IFNA(VLOOKUP($B111,'2026年1月5日'!$B:$E,4,0),0) | H111: =G111-E111 | I111: =_xlfn.IFNA(VLOOKUP($B111,'2026年1月6日'!$B:$E,4,0),0) | J111: =I111-G111 | K111: =_xlfn.IFNA(VLOOKUP($B111,'2026年1月7日'!$B:$E,4,0),0) | L111: =K111-I111 | M111: =_xlfn.IFNA(VLOOKUP($B111,'2026年1月8日'!$B:$E,4,0),0) | N111: =M111-K111 | O111: =_xlfn.IFNA(VLOOKUP($B111,'2026年1月9日'!$B:$E,4,0),0) | P111: =O111-M111 | Q111: =_xlfn.IFNA(VLOOKUP($B111,'2026年1月10日'!$B:$E,4,0),0) | R111: =Q111-O111 | S111: =_xlfn.IFNA(VLOOKUP($B111,'2026年1月12日'!$B:$E,4,0),0) | T111: =S111-Q111 | U111: =_xlfn.IFNA(VLOOKUP($B111,'2026年1月13日'!$B:$E,4,0),0) | V111: =U111-S111 | W111: =_xlfn.IFNA(VLOOKUP($B111,'2026年1月14日'!$B:$E,4,0),0) | X111: =W111-U111 | Y111: =_xlfn.IFNA(VLOOKUP($B111,'2026年1月15日'!$B:$E,4,0),0) | Z111: =Y111-W111 | AA111: =_xlfn.IFNA(VLOOKUP($B111,'2026年1月16日'!$B:$E,4,0),0) | AB111: =AA111-W111 | AC111: =_xlfn.IFNA(VLOOKUP($B111,'2026年1月17日'!$B:$E,4,0),0) | AD111: =AC111-AA111 | AE111: =_xlfn.IFNA(VLOOKUP($B111,'2026年1月19日'!$B:$E,4,0),0) | AF111: =AE111-AC111 | AG111: =_xlfn.IFNA(VLOOKUP($B111,'2026年1月20日'!$B:$E,4,0),0) | AH111: =AG111-AE111 | AI111: =_xlfn.IFNA(VLOOKUP($B111,'2026年1月21日'!$B:$E,4,0),0) | AJ111: =AI111-AG111 | AK111: =_xlfn.IFNA(VLOOKUP($B111,'2026年1月22日'!$B:$E,4,0),0) | AL111: =AK111-AI111 | AM111: =_xlfn.IFNA(VLOOKUP($B111,'2026年1月23日'!$B:$E,4,0),0) | AN111: =AM111-AK111 | AO111: =_xlfn.IFNA(VLOOKUP($B111,'2026年1月24日'!$B:$E,4,0),0) | AP111: =AO111-AM111 | AQ111: =_xlfn.IFNA(VLOOKUP($B111,'2026年1月26日'!$B:$E,4,0),0) | AR111: =AQ111-AO111 | AS111: 97900 | AU111: 87900 | AV111: -10000 | AW111: 87900 | AX111: 0 | AY111: 87900 | AZ111: 0 | BA111: 88400 | BB111: 500 | BE111: 162000 | BG111: 114000 | BH111: -48000 | BI111: 162000 | BJ111: 48000 | BK111: 87900 | BL111: -74100 | BM111: 83900 | BN111: -4000 | BO111: 100900 | BP111: 17000 | BQ111: 100900 | BR111: 0 | BS111: 107200 | BT111: 6300 | BU111: 88400 | BV111: -18800 | BW111: 88400 | BX111: 0
B112: B01592 | C112: 百德能經紀有限公司 | D112: =_xlfn.IFNA(VLOOKUP($B112,'2026年1月2日'!$B:$E,4,0),0) | E112: =_xlfn.IFNA(VLOOKUP($B112,'2026年1月2日'!$B:$E,4,0),0) | F112: =E112-D112 | G112: =_xlfn.IFNA(VLOOKUP($B112,'2026年1月5日'!$B:$E,4,0),0) | H112: =G112-E112 | I112: =_xlfn.IFNA(VLOOKUP($B112,'2026年1月6日'!$B:$E,4,0),0) | J112: =I112-G112 | K112: =_xlfn.IFNA(VLOOKUP($B112,'2026年1月7日'!$B:$E,4,0),0) | L112: =K112-I112 | M112: =_xlfn.IFNA(VLOOKUP($B112,'2026年1月8日'!$B:$E,4,0),0) | N112: =M112-K112 | O112: =_xlfn.IFNA(VLOOKUP($B112,'2026年1月9日'!$B:$E,4,0),0) | P112: =O112-M112 | Q112: =_xlfn.IFNA(VLOOKUP($B112,'2026年1月10日'!$B:$E,4,0),0) | R112: =Q112-O112 | S112: =_xlfn.IFNA(VLOOKUP($B112,'2026年1月12日'!$B:$E,4,0),0) | T112: =S112-Q112 | U112: =_xlfn.IFNA(VLOOKUP($B112,'2026年1月13日'!$B:$E,4,0),0) | V112: =U112-S112 | W112: =_xlfn.IFNA(VLOOKUP($B112,'2026年1月14日'!$B:$E,4,0),0) | X112: =W112-U112 | Y112: =_xlfn.IFNA(VLOOKUP($B112,'2026年1月15日'!$B:$E,4,0),0) | Z112: =Y112-W112 | AA112: =_xlfn.IFNA(VLOOKUP($B112,'2026年1月16日'!$B:$E,4,0),0) | AB112: =AA112-W112 | AC112: =_xlfn.IFNA(VLOOKUP($B112,'2026年1月17日'!$B:$E,4,0),0) | AD112: =AC112-AA112 | AE112: =_xlfn.IFNA(VLOOKUP($B112,'2026年1月19日'!$B:$E,4,0),0) | AF112: =AE112-AC112 | AG112: =_xlfn.IFNA(VLOOKUP($B112,'2026年1月20日'!$B:$E,4,0),0) | AH112: =AG112-AE112 | AI112: =_xlfn.IFNA(VLOOKUP($B112,'2026年1月21日'!$B:$E,4,0),0) | AJ112: =AI112-AG112 | AK112: =_xlfn.IFNA(VLOOKUP($B112,'2026年1月22日'!$B:$E,4,0),0) | AL112: =AK112-AI112 | AM112: =_xlfn.IFNA(VLOOKUP($B112,'2026年1月23日'!$B:$E,4,0),0) | AN112: =AM112-AK112 | AO112: =_xlfn.IFNA(VLOOKUP($B112,'2026年1月24日'!$B:$E,4,0),0) | AP112: =AO112-AM112 | AQ112: =_xlfn.IFNA(VLOOKUP($B112,'2026年1月26日'!$B:$E,4,0),0) | AR112: =AQ112-AO112 | AS112: 18500 | AU112: 18500 | AV112: 0 | AW112: 18500 | AX112: 0 | AY112: 18500 | AZ112: 0 | BA112: 18500 | BB112: 0 | BE112: 18500 | BG112: 18500 | BH112: 0 | BI112: 18500 | BJ112: 0 | BK112: 18500 | BL112: 0 | BM112: 18500 | BN112: 0 | BO112: 18500 | BP112: 0 | BQ112: 18500 | BR112: 0 | BS112: 18500 | BT112: 0 | BU112: 18500 | BV112: 0 | BW112: 18500 | BX112: 0
B113: B02032 | C113: 方德證券有限公司 | D113: =_xlfn.IFNA(VLOOKUP($B113,'2026年1月2日'!$B:$E,4,0),0) | E113: =_xlfn.IFNA(VLOOKUP($B113,'2026年1月2日'!$B:$E,4,0),0) | F113: =E113-D113 | G113: =_xlfn.IFNA(VLOOKUP($B113,'2026年1月5日'!$B:$E,4,0),0) | H113: =G113-E113 | I113: =_xlfn.IFNA(VLOOKUP($B113,'2026年1月6日'!$B:$E,4,0),0) | J113: =I113-G113 | K113: =_xlfn.IFNA(VLOOKUP($B113,'2026年1月7日'!$B:$E,4,0),0) | L113: =K113-I113 | M113: =_xlfn.IFNA(VLOOKUP($B113,'2026年1月8日'!$B:$E,4,0),0) | N113: =M113-K113 | O113: =_xlfn.IFNA(VLOOKUP($B113,'2026年1月9日'!$B:$E,4,0),0) | P113: =O113-M113 | Q113: =_xlfn.IFNA(VLOOKUP($B113,'2026年1月10日'!$B:$E,4,0),0) | R113: =Q113-O113 | S113: =_xlfn.IFNA(VLOOKUP($B113,'2026年1月12日'!$B:$E,4,0),0) | T113: =S113-Q113 | U113: =_xlfn.IFNA(VLOOKUP($B113,'2026年1月13日'!$B:$E,4,0),0) | V113: =U113-S113 | W113: =_xlfn.IFNA(VLOOKUP($B113,'2026年1月14日'!$B:$E,4,0),0) | X113: =W113-U113 | Y113: =_xlfn.IFNA(VLOOKUP($B113,'2026年1月15日'!$B:$E,4,0),0) | Z113: =Y113-W113 | AA113: =_xlfn.IFNA(VLOOKUP($B113,'2026年1月16日'!$B:$E,4,0),0) | AB113: =AA113-W113 | AC113: =_xlfn.IFNA(VLOOKUP($B113,'2026年1月17日'!$B:$E,4,0),0) | AD113: =AC113-AA113 | AE113: =_xlfn.IFNA(VLOOKUP($B113,'2026年1月19日'!$B:$E,4,0),0) | AF113: =AE113-AC113 | AG113: =_xlfn.IFNA(VLOOKUP($B113,'2026年1月20日'!$B:$E,4,0),0) | AH113: =AG113-AE113 | AI113: =_xlfn.IFNA(VLOOKUP($B113,'2026年1月21日'!$B:$E,4,0),0) | AJ113: =AI113-AG113 | AK113: =_xlfn.IFNA(VLOOKUP($B113,'2026年1月22日'!$B:$E,4,0),0) | AL113: =AK113-AI113 | AM113: =_xlfn.IFNA(VLOOKUP($B113,'2026年1月23日'!$B:$E,4,0),0) | AN113: =AM113-AK113 | AO113: =_xlfn.IFNA(VLOOKUP($B113,'2026年1月24日'!$B:$E,4,0),0) | AP113: =AO113-AM113 | AQ113: =_xlfn.IFNA(VLOOKUP($B113,'2026年1月26日'!$B:$E,4,0),0) | AR113: =AQ113-AO113 | AS113: 163700 | AU113: 163700 | AV113: 0 | AW113: 166200 | AX113: 2500 | AY113: 166200 | AZ113: 0 | BA113: 168200 | BB113: 2000 | BE113: 175400 | BG113: 106100 | BH113: -69300 | BI113: 175400 | BJ113: 69300 | BK113: 166200 | BL113: -9200 | BM113: 146300 | BN113: -19900 | BO113: 120200 | BP113: -26100 | BQ113: 120200 | BR113: 0 | BS113: 236100 | BT113: 115900 | BU113: 168200 | BV113: -67900 | BW113: 168200 | BX113: 0
B114: B02022 | C114: 潮商證券有限公司 | D114: =_xlfn.IFNA(VLOOKUP($B114,'2026年1月2日'!$B:$E,4,0),0) | E114: =_xlfn.IFNA(VLOOKUP($B114,'2026年1月2日'!$B:$E,4,0),0) | F114: =E114-D114 | G114: =_xlfn.IFNA(VLOOKUP($B114,'2026年1月5日'!$B:$E,4,0),0) | H114: =G114-E114 | I114: =_xlfn.IFNA(VLOOKUP($B114,'2026年1月6日'!$B:$E,4,0),0) | J114: =I114-G114 | K114: =_xlfn.IFNA(VLOOKUP($B114,'2026年1月7日'!$B:$E,4,0),0) | L114: =K114-I114 | M114: =_xlfn.IFNA(VLOOKUP($B114,'2026年1月8日'!$B:$E,4,0),0) | N114: =M114-K114 | O114: =_xlfn.IFNA(VLOOKUP($B114,'2026年1月9日'!$B:$E,4,0),0) | P114: =O114-M114 | Q114: =_xlfn.IFNA(VLOOKUP($B114,'2026年1月10日'!$B:$E,4,0),0) | R114: =Q114-O114 | S114: =_xlfn.IFNA(VLOOKUP($B114,'2026年1月12日'!$B:$E,4,0),0) | T114: =S114-Q114 | U114: =_xlfn.IFNA(VLOOKUP($B114,'2026年1月13日'!$B:$E,4,0),0) | V114: =U114-S114 | W114: =_xlfn.IFNA(VLOOKUP($B114,'2026年1月14日'!$B:$E,4,0),0) | X114: =W114-U114 | Y114: =_xlfn.IFNA(VLOOKUP($B114,'2026年1月15日'!$B:$E,4,0),0) | Z114: =Y114-W114 | AA114: =_xlfn.IFNA(VLOOKUP($B114,'2026年1月16日'!$B:$E,4,0),0) | AB114: =AA114-W114 | AC114: =_xlfn.IFNA(VLOOKUP($B114,'2026年1月17日'!$B:$E,4,0),0) | AD114: =AC114-AA114 | AE114: =_xlfn.IFNA(VLOOKUP($B114,'2026年1月19日'!$B:$E,4,0),0) | AF114: =AE114-AC114 | AG114: =_xlfn.IFNA(VLOOKUP($B114,'2026年1月20日'!$B:$E,4,0),0) | AH114: =AG114-AE114 | AI114: =_xlfn.IFNA(VLOOKUP($B114,'2026年1月21日'!$B:$E,4,0),0) | AJ114: =AI114-AG114 | AK114: =_xlfn.IFNA(VLOOKUP($B114,'2026年1月22日'!$B:$E,4,0),0) | AL114: =AK114-AI114 | AM114: =_xlfn.IFNA(VLOOKUP($B114,'2026年1月23日'!$B:$E,4,0),0) | AN114: =AM114-AK114 | AO114: =_xlfn.IFNA(VLOOKUP($B114,'2026年1月24日'!$B:$E,4,0),0) | AP114: =AO114-AM114 | AQ114: =_xlfn.IFNA(VLOOKUP($B114,'2026年1月26日'!$B:$E,4,0),0) | AR114: =AQ114-AO114 | AS114: 49400 | AU114: 49400 | AV114: 0 | AW114: 49400 | AX114: 0 | AY114: 49400 | AZ114: 0 | BA114: 49400 | BB114: 0 | BE114: 49400 | BG114: 49400 | BH114: 0 | BI114: 49400 | BJ114: 0 | BK114: 49400 | BL114: 0 | BM114: 49400 | BN114: 0 | BO114: 49400 | BP114: 0 | BQ114: 49400 | BR114: 0 | BS114: 49400 | BT114: 0 | BU114: 49400 | BV114: 0 | BW114: 49400 | BX114: 0
B115: B01290 | C115: 新寶城證券有限公司 | D115: =_xlfn.IFNA(VLOOKUP($B115,'2026年1月2日'!$B:$E,4,0),0) | E115: =_xlfn.IFNA(VLOOKUP($B115,'2026年1月2日'!$B:$E,4,0),0) | F115: =E115-D115 | G115: =_xlfn.IFNA(VLOOKUP($B115,'2026年1月5日'!$B:$E,4,0),0) | H115: =G115-E115 | I115: =_xlfn.IFNA(VLOOKUP($B115,'2026年1月6日'!$B:$E,4,0),0) | J115: =I115-G115 | K115: =_xlfn.IFNA(VLOOKUP($B115,'2026年1月7日'!$B:$E,4,0),0) | L115: =K115-I115 | M115: =_xlfn.IFNA(VLOOKUP($B115,'2026年1月8日'!$B:$E,4,0),0) | N115: =M115-K115 | O115: =_xlfn.IFNA(VLOOKUP($B115,'2026年1月9日'!$B:$E,4,0),0) | P115: =O115-M115 | Q115: =_xlfn.IFNA(VLOOKUP($B115,'2026年1月10日'!$B:$E,4,0),0) | R115: =Q115-O115 | S115: =_xlfn.IFNA(VLOOKUP($B115,'2026年1月12日'!$B:$E,4,0),0) | T115: =S115-Q115 | U115: =_xlfn.IFNA(VLOOKUP($B115,'2026年1月13日'!$B:$E,4,0),0) | V115: =U115-S115 | W115: =_xlfn.IFNA(VLOOKUP($B115,'2026年1月14日'!$B:$E,4,0),0) | X115: =W115-U115 | Y115: =_xlfn.IFNA(VLOOKUP($B115,'2026年1月15日'!$B:$E,4,0),0) | Z115: =Y115-W115 | AA115: =_xlfn.IFNA(VLOOKUP($B115,'2026年1月16日'!$B:$E,4,0),0) | AB115: =AA115-W115 | AC115: =_xlfn.IFNA(VLOOKUP($B115,'2026年1月17日'!$B:$E,4,0),0) | AD115: =AC115-AA115 | AE115: =_xlfn.IFNA(VLOOKUP($B115,'2026年1月19日'!$B:$E,4,0),0) | AF115: =AE115-AC115 | AG115: =_xlfn.IFNA(VLOOKUP($B115,'2026年1月20日'!$B:$E,4,0),0) | AH115: =AG115-AE115 | AI115: =_xlfn.IFNA(VLOOKUP($B115,'2026年1月21日'!$B:$E,4,0),0) | AJ115: =AI115-AG115 | AK115: =_xlfn.IFNA(VLOOKUP($B115,'2026年1月22日'!$B:$E,4,0),0) | AL115: =AK115-AI115 | AM115: =_xlfn.IFNA(VLOOKUP($B115,'2026年1月23日'!$B:$E,4,0),0) | AN115: =AM115-AK115 | AO115: =_xlfn.IFNA(VLOOKUP($B115,'2026年1月24日'!$B:$E,4,0),0) | AP115: =AO115-AM115 | AQ115: =_xlfn.IFNA(VLOOKUP($B115,'2026年1月26日'!$B:$E,4,0),0) | AR115: =AQ115-AO115
B116: B01256 | C116: 國金證券(香港)有限公司 | D116: =_xlfn.IFNA(VLOOKUP($B116,'2026年1月2日'!$B:$E,4,0),0) | E116: =_xlfn.IFNA(VLOOKUP($B116,'2026年1月2日'!$B:$E,4,0),0) | F116: =E116-D116 | G116: =_xlfn.IFNA(VLOOKUP($B116,'2026年1月5日'!$B:$E,4,0),0) | H116: =G116-E116 | I116: =_xlfn.IFNA(VLOOKUP($B116,'2026年1月6日'!$B:$E,4,0),0) | J116: =I116-G116 | K116: =_xlfn.IFNA(VLOOKUP($B116,'2026年1月7日'!$B:$E,4,0),0) | L116: =K116-I116 | M116: =_xlfn.IFNA(VLOOKUP($B116,'2026年1月8日'!$B:$E,4,0),0) | N116: =M116-K116 | O116: =_xlfn.IFNA(VLOOKUP($B116,'2026年1月9日'!$B:$E,4,0),0) | P116: =O116-M116 | Q116: =_xlfn.IFNA(VLOOKUP($B116,'2026年1月10日'!$B:$E,4,0),0) | R116: =Q116-O116 | S116: =_xlfn.IFNA(VLOOKUP($B116,'2026年1月12日'!$B:$E,4,0),0) | T116: =S116-Q116 | U116: =_xlfn.IFNA(VLOOKUP($B116,'2026年1月13日'!$B:$E,4,0),0) | V116: =U116-S116 | W116: =_xlfn.IFNA(VLOOKUP($B116,'2026年1月14日'!$B:$E,4,0),0) | X116: =W116-U116 | Y116: =_xlfn.IFNA(VLOOKUP($B116,'2026年1月15日'!$B:$E,4,0),0) | Z116: =Y116-W116 | AA116: =_xlfn.IFNA(VLOOKUP($B116,'2026年1月16日'!$B:$E,4,0),0) | AB116: =AA116-W116 | AC116: =_xlfn.IFNA(VLOOKUP($B116,'2026年1月17日'!$B:$E,4,0),0) | AD116: =AC116-AA116 | AE116: =_xlfn.IFNA(VLOOKUP($B116,'2026年1月19日'!$B:$E,4,0),0) | AF116: =AE116-AC116 | AG116: =_xlfn.IFNA(VLOOKUP($B116,'2026年1月20日'!$B:$E,4,0),0) | AH116: =AG116-AE116 | AI116: =_xlfn.IFNA(VLOOKUP($B116,'2026年1月21日'!$B:$E,4,0),0) | AJ116: =AI116-AG116 | AK116: =_xlfn.IFNA(VLOOKUP($B116,'2026年1月22日'!$B:$E,4,0),0) | AL116: =AK116-AI116 | AM116: =_xlfn.IFNA(VLOOKUP($B116,'2026年1月23日'!$B:$E,4,0),0) | AN116: =AM116-AK116 | AO116: =_xlfn.IFNA(VLOOKUP($B116,'2026年1月24日'!$B:$E,4,0),0) | AP116: =AO116-AM116 | AQ116: =_xlfn.IFNA(VLOOKUP($B116,'2026年1月26日'!$B:$E,4,0),0) | AR116: =AQ116-AO116 | AS116: 35200 | AU116: 35200 | AV116: 0 | AW116: 35200 | AX116: 0 | AY116: 35200 | AZ116: 0 | BA116: 35200 | BB116: 0 | BE116: 35200 | BG116: 65200 | BH116: 30000 | BI116: 35200 | BJ116: -30000 | BK116: 35200 | BL116: 0 | BM116: 15200 | BN116: -20000 | BO116: 15200 | BP116: 0 | BQ116: 15200 | BR116: 0 | BS116: 15200 | BT116: 0 | BU116: 35200 | BV116: 20000 | BW116: 35200 | BX116: 0
B117: B02120 | C117: 利弗莫爾證券有限公司 | D117: =_xlfn.IFNA(VLOOKUP($B117,'2026年1月2日'!$B:$E,4,0),0) | E117: =_xlfn.IFNA(VLOOKUP($B117,'2026年1月2日'!$B:$E,4,0),0) | F117: =E117-D117 | G117: =_xlfn.IFNA(VLOOKUP($B117,'2026年1月5日'!$B:$E,4,0),0) | H117: =G117-E117 | I117: =_xlfn.IFNA(VLOOKUP($B117,'2026年1月6日'!$B:$E,4,0),0) | J117: =I117-G117 | K117: =_xlfn.IFNA(VLOOKUP($B117,'2026年1月7日'!$B:$E,4,0),0) | L117: =K117-I117 | M117: =_xlfn.IFNA(VLOOKUP($B117,'2026年1月8日'!$B:$E,4,0),0) | N117: =M117-K117 | O117: =_xlfn.IFNA(VLOOKUP($B117,'2026年1月9日'!$B:$E,4,0),0) | P117: =O117-M117 | Q117: =_xlfn.IFNA(VLOOKUP($B117,'2026年1月10日'!$B:$E,4,0),0) | R117: =Q117-O117 | S117: =_xlfn.IFNA(VLOOKUP($B117,'2026年1月12日'!$B:$E,4,0),0) | T117: =S117-Q117 | U117: =_xlfn.IFNA(VLOOKUP($B117,'2026年1月13日'!$B:$E,4,0),0) | V117: =U117-S117 | W117: =_xlfn.IFNA(VLOOKUP($B117,'2026年1月14日'!$B:$E,4,0),0) | X117: =W117-U117 | Y117: =_xlfn.IFNA(VLOOKUP($B117,'2026年1月15日'!$B:$E,4,0),0) | Z117: =Y117-W117 | AA117: =_xlfn.IFNA(VLOOKUP($B117,'2026年1月16日'!$B:$E,4,0),0) | AB117: =AA117-W117 | AC117: =_xlfn.IFNA(VLOOKUP($B117,'2026年1月17日'!$B:$E,4,0),0) | AD117: =AC117-AA117 | AE117: =_xlfn.IFNA(VLOOKUP($B117,'2026年1月19日'!$B:$E,4,0),0) | AF117: =AE117-AC117 | AG117: =_xlfn.IFNA(VLOOKUP($B117,'2026年1月20日'!$B:$E,4,0),0) | AH117: =AG117-AE117 | AI117: =_xlfn.IFNA(VLOOKUP($B117,'2026年1月21日'!$B:$E,4,0),0) | AJ117: =AI117-AG117 | AK117: =_xlfn.IFNA(VLOOKUP($B117,'2026年1月22日'!$B:$E,4,0),0) | AL117: =AK117-AI117 | AM117: =_xlfn.IFNA(VLOOKUP($B117,'2026年1月23日'!$B:$E,4,0),0) | AN117: =AM117-AK117 | AO117: =_xlfn.IFNA(VLOOKUP($B117,'2026年1月24日'!$B:$E,4,0),0) | AP117: =AO117-AM117 | AQ117: =_xlfn.IFNA(VLOOKUP($B117,'2026年1月26日'!$B:$E,4,0),0) | AR117: =AQ117-AO117 | AS117: 177400 | AU117: 177400 | AV117: 0 | AW117: 177400 | AX117: 0 | AY117: 177400 | AZ117: 0 | BA117: 177400 | BB117: 0 | BE117: 189100 | BG117: 195900 | BH117: 6800 | BI117: 189100 | BJ117: -6800 | BK117: 177400 | BL117: -11700 | BM117: 254100 | BN117: 76700 | BO117: 182100 | BP117: -72000 | BQ117: 182100 | BR117: 0 | BS117: 182700 | BT117: 600 | BU117: 177400 | BV117: -5300 | BW117: 177400 | BX117: 0
B118: B01252 | C118: 協聯證券有限公司 | D118: =_xlfn.IFNA(VLOOKUP($B118,'2026年1月2日'!$B:$E,4,0),0) | E118: =_xlfn.IFNA(VLOOKUP($B118,'2026年1月2日'!$B:$E,4,0),0) | F118: =E118-D118 | G118: =_xlfn.IFNA(VLOOKUP($B118,'2026年1月5日'!$B:$E,4,0),0) | H118: =G118-E118 | I118: =_xlfn.IFNA(VLOOKUP($B118,'2026年1月6日'!$B:$E,4,0),0) | J118: =I118-G118 | K118: =_xlfn.IFNA(VLOOKUP($B118,'2026年1月7日'!$B:$E,4,0),0) | L118: =K118-I118 | M118: =_xlfn.IFNA(VLOOKUP($B118,'2026年1月8日'!$B:$E,4,0),0) | N118: =M118-K118 | O118: =_xlfn.IFNA(VLOOKUP($B118,'2026年1月9日'!$B:$E,4,0),0) | P118: =O118-M118 | Q118: =_xlfn.IFNA(VLOOKUP($B118,'2026年1月10日'!$B:$E,4,0),0) | R118: =Q118-O118 | S118: =_xlfn.IFNA(VLOOKUP($B118,'2026年1月12日'!$B:$E,4,0),0) | T118: =S118-Q118 | U118: =_xlfn.IFNA(VLOOKUP($B118,'2026年1月13日'!$B:$E,4,0),0) | V118: =U118-S118 | W118: =_xlfn.IFNA(VLOOKUP($B118,'2026年1月14日'!$B:$E,4,0),0) | X118: =W118-U118 | Y118: =_xlfn.IFNA(VLOOKUP($B118,'2026年1月15日'!$B:$E,4,0),0) | Z118: =Y118-W118 | AA118: =_xlfn.IFNA(VLOOKUP($B118,'2026年1月16日'!$B:$E,4,0),0) | AB118: =AA118-W118 | AC118: =_xlfn.IFNA(VLOOKUP($B118,'2026年1月17日'!$B:$E,4,0),0) | AD118: =AC118-AA118 | AE118: =_xlfn.IFNA(VLOOKUP($B118,'2026年1月19日'!$B:$E,4,0),0) | AF118: =AE118-AC118 | AG118: =_xlfn.IFNA(VLOOKUP($B118,'2026年1月20日'!$B:$E,4,0),0) | AH118: =AG118-AE118 | AI118: =_xlfn.IFNA(VLOOKUP($B118,'2026年1月21日'!$B:$E,4,0),0) | AJ118: =AI118-AG118 | AK118: =_xlfn.IFNA(VLOOKUP($B118,'2026年1月22日'!$B:$E,4,0),0) | AL118: =AK118-AI118 | AM118: =_xlfn.IFNA(VLOOKUP($B118,'2026年1月23日'!$B:$E,4,0),0) | AN118: =AM118-AK118 | AO118: =_xlfn.IFNA(VLOOKUP($B118,'2026年1月24日'!$B:$E,4,0),0) | AP118: =AO118-AM118 | AQ118: =_xlfn.IFNA(VLOOKUP($B118,'2026年1月26日'!$B:$E,4,0),0) | AR118: =AQ118-AO118 | AS118: 102800 | AU118: 102800 | AV118: 0 | AW118: 102800 | AX118: 0 | AY118: 102800 | AZ118: 0 | BA118: 102800 | BB118: 0 | BE118: 105100 | BG118: 96200 | BH118: -8900 | BI118: 105100 | BJ118: 8900 | BK118: 102800 | BL118: -2300 | BM118: 98100 | BN118: -4700 | BO118: 94200 | BP118: -3900 | BQ118: 94200 | BR118: 0 | BS118: 97200 | BT118: 3000 | BU118: 102800 | BV118: 5600 | BW118: 102800 | BX118: 0
B119: B02195 | C119: 長橋證券(香港)有限公司 | D119: =_xlfn.IFNA(VLOOKUP($B119,'2026年1月2日'!$B:$E,4,0),0) | E119: =_xlfn.IFNA(VLOOKUP($B119,'2026年1月2日'!$B:$E,4,0),0) | F119: =E119-D119 | G119: =_xlfn.IFNA(VLOOKUP($B119,'2026年1月5日'!$B:$E,4,0),0) | H119: =G119-E119 | I119: =_xlfn.IFNA(VLOOKUP($B119,'2026年1月6日'!$B:$E,4,0),0) | J119: =I119-G119 | K119: =_xlfn.IFNA(VLOOKUP($B119,'2026年1月7日'!$B:$E,4,0),0) | L119: =K119-I119 | M119: =_xlfn.IFNA(VLOOKUP($B119,'2026年1月8日'!$B:$E,4,0),0) | N119: =M119-K119 | O119: =_xlfn.IFNA(VLOOKUP($B119,'2026年1月9日'!$B:$E,4,0),0) | P119: =O119-M119 | Q119: =_xlfn.IFNA(VLOOKUP($B119,'2026年1月10日'!$B:$E,4,0),0) | R119: =Q119-O119 | S119: =_xlfn.IFNA(VLOOKUP($B119,'2026年1月12日'!$B:$E,4,0),0) | T119: =S119-Q119 | U119: =_xlfn.IFNA(VLOOKUP($B119,'2026年1月13日'!$B:$E,4,0),0) | V119: =U119-S119 | W119: =_xlfn.IFNA(VLOOKUP($B119,'2026年1月14日'!$B:$E,4,0),0) | X119: =W119-U119 | Y119: =_xlfn.IFNA(VLOOKUP($B119,'2026年1月15日'!$B:$E,4,0),0) | Z119: =Y119-W119 | AA119: =_xlfn.IFNA(VLOOKUP($B119,'2026年1月16日'!$B:$E,4,0),0) | AB119: =AA119-W119 | AC119: =_xlfn.IFNA(VLOOKUP($B119,'2026年1月17日'!$B:$E,4,0),0) | AD119: =AC119-AA119 | AE119: =_xlfn.IFNA(VLOOKUP($B119,'2026年1月19日'!$B:$E,4,0),0) | AF119: =AE119-AC119 | AG119: =_xlfn.IFNA(VLOOKUP($B119,'2026年1月20日'!$B:$E,4,0),0) | AH119: =AG119-AE119 | AI119: =_xlfn.IFNA(VLOOKUP($B119,'2026年1月21日'!$B:$E,4,0),0) | AJ119: =AI119-AG119 | AK119: =_xlfn.IFNA(VLOOKUP($B119,'2026年1月22日'!$B:$E,4,0),0) | AL119: =AK119-AI119 | AM119: =_xlfn.IFNA(VLOOKUP($B119,'2026年1月23日'!$B:$E,4,0),0) | AN119: =AM119-AK119 | AO119: =_xlfn.IFNA(VLOOKUP($B119,'2026年1月24日'!$B:$E,4,0),0) | AP119: =AO119-AM119 | AQ119: =_xlfn.IFNA(VLOOKUP($B119,'2026年1月26日'!$B:$E,4,0),0) | AR119: =AQ119-AO119 | AS119: 1223600 | AU119: 1207400 | AV119: -16200 | AW119: 1234400 | AX119: 27000 | AY119: 1239000 | AZ119: 4600 | BA119: 1234700 | BB119: -4300 | BE119: 1269700 | BG119: 878300 | BH119: -391400 | BI119: 1269700 | BJ119: 391400 | BK119: 1239000 | BL119: -30700 | BM119: 1084400 | BN119: -154600 | BO119: 942000 | BP119: -142400 | BQ119: 942000 | BR119: 0 | BS119: 978100 | BT119: 36100 | BU119: 1234700 | BV119: 256600 | BW119: 1234700 | BX119: 0
B120: B01939 | C120: 東吳證券國際經紀有限公司 | D120: =_xlfn.IFNA(VLOOKUP($B120,'2026年1月2日'!$B:$E,4,0),0) | E120: =_xlfn.IFNA(VLOOKUP($B120,'2026年1月2日'!$B:$E,4,0),0) | F120: =E120-D120 | G120: =_xlfn.IFNA(VLOOKUP($B120,'2026年1月5日'!$B:$E,4,0),0) | H120: =G120-E120 | I120: =_xlfn.IFNA(VLOOKUP($B120,'2026年1月6日'!$B:$E,4,0),0) | J120: =I120-G120 | K120: =_xlfn.IFNA(VLOOKUP($B120,'2026年1月7日'!$B:$E,4,0),0) | L120: =K120-I120 | M120: =_xlfn.IFNA(VLOOKUP($B120,'2026年1月8日'!$B:$E,4,0),0) | N120: =M120-K120 | O120: =_xlfn.IFNA(VLOOKUP($B120,'2026年1月9日'!$B:$E,4,0),0) | P120: =O120-M120 | Q120: =_xlfn.IFNA(VLOOKUP($B120,'2026年1月10日'!$B:$E,4,0),0) | R120: =Q120-O120 | S120: =_xlfn.IFNA(VLOOKUP($B120,'2026年1月12日'!$B:$E,4,0),0) | T120: =S120-Q120 | U120: =_xlfn.IFNA(VLOOKUP($B120,'2026年1月13日'!$B:$E,4,0),0) | V120: =U120-S120 | W120: =_xlfn.IFNA(VLOOKUP($B120,'2026年1月14日'!$B:$E,4,0),0) | X120: =W120-U120 | Y120: =_xlfn.IFNA(VLOOKUP($B120,'2026年1月15日'!$B:$E,4,0),0) | Z120: =Y120-W120 | AA120: =_xlfn.IFNA(VLOOKUP($B120,'2026年1月16日'!$B:$E,4,0),0) | AB120: =AA120-W120 | AC120: =_xlfn.IFNA(VLOOKUP($B120,'2026年1月17日'!$B:$E,4,0),0) | AD120: =AC120-AA120 | AE120: =_xlfn.IFNA(VLOOKUP($B120,'2026年1月19日'!$B:$E,4,0),0) | AF120: =AE120-AC120 | AG120: =_xlfn.IFNA(VLOOKUP($B120,'2026年1月20日'!$B:$E,4,0),0) | AH120: =AG120-AE120 | AI120: =_xlfn.IFNA(VLOOKUP($B120,'2026年1月21日'!$B:$E,4,0),0) | AJ120: =AI120-AG120 | AK120: =_xlfn.IFNA(VLOOKUP($B120,'2026年1月22日'!$B:$E,4,0),0) | AL120: =AK120-AI120 | AM120: =_xlfn.IFNA(VLOOKUP($B120,'2026年1月23日'!$B:$E,4,0),0) | AN120: =AM120-AK120 | AO120: =_xlfn.IFNA(VLOOKUP($B120,'2026年1月24日'!$B:$E,4,0),0) | AP120: =AO120-AM120 | AQ120: =_xlfn.IFNA(VLOOKUP($B120,'2026年1月26日'!$B:$E,4,0),0) | AR120: =AQ120-AO120 | AS120: 22100 | AU120: 22100 | AV120: 0 | AW120: 22100 | AX120: 0 | AY120: 22100 | AZ120: 0 | BA120: 22100 | BB120: 0 | BE120: 23100 | BG120: 24000 | BH120: 900 | BI120: 23100 | BJ120: -900 | BK120: 22100 | BL120: -1000 | BM120: 24100 | BN120: 2000 | BO120: 229700 | BP120: 205600 | BQ120: 229700 | BR120: 0 | BS120: 413500 | BT120: 183800 | BU120: 22100 | BV120: -391400 | BW120: 22100 | BX120: 0
B121: B01173 | C121: 日發證券有限公司 | D121: =_xlfn.IFNA(VLOOKUP($B121,'2026年1月2日'!$B:$E,4,0),0) | E121: =_xlfn.IFNA(VLOOKUP($B121,'2026年1月2日'!$B:$E,4,0),0) | F121: =E121-D121 | G121: =_xlfn.IFNA(VLOOKUP($B121,'2026年1月5日'!$B:$E,4,0),0) | H121: =G121-E121 | I121: =_xlfn.IFNA(VLOOKUP($B121,'2026年1月6日'!$B:$E,4,0),0) | J121: =I121-G121 | K121: =_xlfn.IFNA(VLOOKUP($B121,'2026年1月7日'!$B:$E,4,0),0) | L121: =K121-I121 | M121: =_xlfn.IFNA(VLOOKUP($B121,'2026年1月8日'!$B:$E,4,0),0) | N121: =M121-K121 | O121: =_xlfn.IFNA(VLOOKUP($B121,'2026年1月9日'!$B:$E,4,0),0) | P121: =O121-M121 | Q121: =_xlfn.IFNA(VLOOKUP($B121,'2026年1月10日'!$B:$E,4,0),0) | R121: =Q121-O121 | S121: =_xlfn.IFNA(VLOOKUP($B121,'2026年1月12日'!$B:$E,4,0),0) | T121: =S121-Q121 | U121: =_xlfn.IFNA(VLOOKUP($B121,'2026年1月13日'!$B:$E,4,0),0) | V121: =U121-S121 | W121: =_xlfn.IFNA(VLOOKUP($B121,'2026年1月14日'!$B:$E,4,0),0) | X121: =W121-U121 | Y121: =_xlfn.IFNA(VLOOKUP($B121,'2026年1月15日'!$B:$E,4,0),0) | Z121: =Y121-W121 | AA121: =_xlfn.IFNA(VLOOKUP($B121,'2026年1月16日'!$B:$E,4,0),0) | AB121: =AA121-W121 | AC121: =_xlfn.IFNA(VLOOKUP($B121,'2026年1月17日'!$B:$E,4,0),0) | AD121: =AC121-AA121 | AE121: =_xlfn.IFNA(VLOOKUP($B121,'2026年1月19日'!$B:$E,4,0),0) | AF121: =AE121-AC121 | AG121: =_xlfn.IFNA(VLOOKUP($B121,'2026年1月20日'!$B:$E,4,0),0) | AH121: =AG121-AE121 | AI121: =_xlfn.IFNA(VLOOKUP($B121,'2026年1月21日'!$B:$E,4,0),0) | AJ121: =AI121-AG121 | AK121: =_xlfn.IFNA(VLOOKUP($B121,'2026年1月22日'!$B:$E,4,0),0) | AL121: =AK121-AI121 | AM121: =_xlfn.IFNA(VLOOKUP($B121,'2026年1月23日'!$B:$E,4,0),0) | AN121: =AM121-AK121 | AO121: =_xlfn.IFNA(VLOOKUP($B121,'2026年1月24日'!$B:$E,4,0),0) | AP121: =AO121-AM121 | AQ121: =_xlfn.IFNA(VLOOKUP($B121,'2026年1月26日'!$B:$E,4,0),0) | AR121: =AQ121-AO121 | AS121: 127100 | AU121: 127100 | AV121: 0 | AW121: 127100 | AX121: 0 | AY121: 127100 | AZ121: 0 | BA121: 127100 | BB121: 0 | BE121: 211100 | BG121: 171100 | BH121: -40000 | BI121: 211100 | BJ121: 40000 | BK121: 127100 | BL121: -84000 | BM121: 201100 | BN121: 74000 | BO121: 171100 | BP121: -30000 | BQ121: 171100 | BR121: 0 | BS121: 171100 | BT121: 0 | BU121: 127100 | BV121: -44000 | BW121: 127100 | BX121: 0
B122: B01866 | C122: 工銀國際證券有限公司 | D122: =_xlfn.IFNA(VLOOKUP($B122,'2026年1月2日'!$B:$E,4,0),0) | E122: =_xlfn.IFNA(VLOOKUP($B122,'2026年1月2日'!$B:$E,4,0),0) | F122: =E122-D122 | G122: =_xlfn.IFNA(VLOOKUP($B122,'2026年1月5日'!$B:$E,4,0),0) | H122: =G122-E122 | I122: =_xlfn.IFNA(VLOOKUP($B122,'2026年1月6日'!$B:$E,4,0),0) | J122: =I122-G122 | K122: =_xlfn.IFNA(VLOOKUP($B122,'2026年1月7日'!$B:$E,4,0),0) | L122: =K122-I122 | M122: =_xlfn.IFNA(VLOOKUP($B122,'2026年1月8日'!$B:$E,4,0),0) | N122: =M122-K122 | O122: =_xlfn.IFNA(VLOOKUP($B122,'2026年1月9日'!$B:$E,4,0),0) | P122: =O122-M122 | Q122: =_xlfn.IFNA(VLOOKUP($B122,'2026年1月10日'!$B:$E,4,0),0) | R122: =Q122-O122 | S122: =_xlfn.IFNA(VLOOKUP($B122,'2026年1月12日'!$B:$E,4,0),0) | T122: =S122-Q122 | U122: =_xlfn.IFNA(VLOOKUP($B122,'2026年1月13日'!$B:$E,4,0),0) | V122: =U122-S122 | W122: =_xlfn.IFNA(VLOOKUP($B122,'2026年1月14日'!$B:$E,4,0),0) | X122: =W122-U122 | Y122: =_xlfn.IFNA(VLOOKUP($B122,'2026年1月15日'!$B:$E,4,0),0) | Z122: =Y122-W122 | AA122: =_xlfn.IFNA(VLOOKUP($B122,'2026年1月16日'!$B:$E,4,0),0) | AB122: =AA122-W122 | AC122: =_xlfn.IFNA(VLOOKUP($B122,'2026年1月17日'!$B:$E,4,0),0) | AD122: =AC122-AA122 | AE122: =_xlfn.IFNA(VLOOKUP($B122,'2026年1月19日'!$B:$E,4,0),0) | AF122: =AE122-AC122 | AG122: =_xlfn.IFNA(VLOOKUP($B122,'2026年1月20日'!$B:$E,4,0),0) | AH122: =AG122-AE122 | AI122: =_xlfn.IFNA(VLOOKUP($B122,'2026年1月21日'!$B:$E,4,0),0) | AJ122: =AI122-AG122 | AK122: =_xlfn.IFNA(VLOOKUP($B122,'2026年1月22日'!$B:$E,4,0),0) | AL122: =AK122-AI122 | AM122: =_xlfn.IFNA(VLOOKUP($B122,'2026年1月23日'!$B:$E,4,0),0) | AN122: =AM122-AK122 | AO122: =_xlfn.IFNA(VLOOKUP($B122,'2026年1月24日'!$B:$E,4,0),0) | AP122: =AO122-AM122 | AQ122: =_xlfn.IFNA(VLOOKUP($B122,'2026年1月26日'!$B:$E,4,0),0) | AR122: =AQ122-AO122 | AS122: 48800 | AU122: 48800 | AV122: 0 | AW122: 48800 | AX122: 0 | AY122: 48800 | AZ122: 0 | BA122: 48800 | BB122: 0 | BE122: 48800 | BG122: 47500 | BH122: -1300 | BI122: 48800 | BJ122: 1300 | BK122: 48800 | BL122: 0 | BM122: 48800 | BN122: 0 | BO122: 42400 | BP122: -6400 | BQ122: 42400 | BR122: 0 | BS122: 47500 | BT122: 5100 | BU122: 48800 | BV122: 1300 | BW122: 48800 | BX122: 0
B123: B01552 | C123: 嘉利證券投資有限公司 | D123: =_xlfn.IFNA(VLOOKUP($B123,'2026年1月2日'!$B:$E,4,0),0) | E123: =_xlfn.IFNA(VLOOKUP($B123,'2026年1月2日'!$B:$E,4,0),0) | F123: =E123-D123 | G123: =_xlfn.IFNA(VLOOKUP($B123,'2026年1月5日'!$B:$E,4,0),0) | H123: =G123-E123 | I123: =_xlfn.IFNA(VLOOKUP($B123,'2026年1月6日'!$B:$E,4,0),0) | J123: =I123-G123 | K123: =_xlfn.IFNA(VLOOKUP($B123,'2026年1月7日'!$B:$E,4,0),0) | L123: =K123-I123 | M123: =_xlfn.IFNA(VLOOKUP($B123,'2026年1月8日'!$B:$E,4,0),0) | N123: =M123-K123 | O123: =_xlfn.IFNA(VLOOKUP($B123,'2026年1月9日'!$B:$E,4,0),0) | P123: =O123-M123 | Q123: =_xlfn.IFNA(VLOOKUP($B123,'2026年1月10日'!$B:$E,4,0),0) | R123: =Q123-O123 | S123: =_xlfn.IFNA(VLOOKUP($B123,'2026年1月12日'!$B:$E,4,0),0) | T123: =S123-Q123 | U123: =_xlfn.IFNA(VLOOKUP($B123,'2026年1月13日'!$B:$E,4,0),0) | V123: =U123-S123 | W123: =_xlfn.IFNA(VLOOKUP($B123,'2026年1月14日'!$B:$E,4,0),0) | X123: =W123-U123 | Y123: =_xlfn.IFNA(VLOOKUP($B123,'2026年1月15日'!$B:$E,4,0),0) | Z123: =Y123-W123 | AA123: =_xlfn.IFNA(VLOOKUP($B123,'2026年1月16日'!$B:$E,4,0),0) | AB123: =AA123-W123 | AC123: =_xlfn.IFNA(VLOOKUP($B123,'2026年1月17日'!$B:$E,4,0),0) | AD123: =AC123-AA123 | AE123: =_xlfn.IFNA(VLOOKUP($B123,'2026年1月19日'!$B:$E,4,0),0) | AF123: =AE123-AC123 | AG123: =_xlfn.IFNA(VLOOKUP($B123,'2026年1月20日'!$B:$E,4,0),0) | AH123: =AG123-AE123 | AI123: =_xlfn.IFNA(VLOOKUP($B123,'2026年1月21日'!$B:$E,4,0),0) | AJ123: =AI123-AG123 | AK123: =_xlfn.IFNA(VLOOKUP($B123,'2026年1月22日'!$B:$E,4,0),0) | AL123: =AK123-AI123 | AM123: =_xlfn.IFNA(VLOOKUP($B123,'2026年1月23日'!$B:$E,4,0),0) | AN123: =AM123-AK123 | AO123: =_xlfn.IFNA(VLOOKUP($B123,'2026年1月24日'!$B:$E,4,0),0) | AP123: =AO123-AM123 | AQ123: =_xlfn.IFNA(VLOOKUP($B123,'2026年1月26日'!$B:$E,4,0),0) | AR123: =AQ123-AO123 | AS123: 29600 | AU123: 29600 | AV123: 0 | AW123: 29600 | AX123: 0 | AY123: 29600 | AZ123: 0 | BA123: 29600 | BB123: 0 | BE123: 29600 | BG123: 34600 | BH123: 5000 | BI123: 29600 | BJ123: -5000 | BK123: 29600 | BL123: 0 | BM123: 34600 | BN123: 5000 | BO123: 34600 | BP123: 0 | BQ123: 34600 | BR123: 0 | BS123: 34600 | BT123: 0 | BU123: 29600 | BV123: -5000 | BW123: 29600 | BX123: 0
B124: B01119 | C124: 時富證券有限公司 | D124: =_xlfn.IFNA(VLOOKUP($B124,'2026年1月2日'!$B:$E,4,0),0) | E124: =_xlfn.IFNA(VLOOKUP($B124,'2026年1月2日'!$B:$E,4,0),0) | F124: =E124-D124 | G124: =_xlfn.IFNA(VLOOKUP($B124,'2026年1月5日'!$B:$E,4,0),0) | H124: =G124-E124 | I124: =_xlfn.IFNA(VLOOKUP($B124,'2026年1月6日'!$B:$E,4,0),0) | J124: =I124-G124 | K124: =_xlfn.IFNA(VLOOKUP($B124,'2026年1月7日'!$B:$E,4,0),0) | L124: =K124-I124 | M124: =_xlfn.IFNA(VLOOKUP($B124,'2026年1月8日'!$B:$E,4,0),0) | N124: =M124-K124 | O124: =_xlfn.IFNA(VLOOKUP($B124,'2026年1月9日'!$B:$E,4,0),0) | P124: =O124-M124 | Q124: =_xlfn.IFNA(VLOOKUP($B124,'2026年1月10日'!$B:$E,4,0),0) | R124: =Q124-O124 | S124: =_xlfn.IFNA(VLOOKUP($B124,'2026年1月12日'!$B:$E,4,0),0) | T124: =S124-Q124 | U124: =_xlfn.IFNA(VLOOKUP($B124,'2026年1月13日'!$B:$E,4,0),0) | V124: =U124-S124 | W124: =_xlfn.IFNA(VLOOKUP($B124,'2026年1月14日'!$B:$E,4,0),0) | X124: =W124-U124 | Y124: =_xlfn.IFNA(VLOOKUP($B124,'2026年1月15日'!$B:$E,4,0),0) | Z124: =Y124-W124 | AA124: =_xlfn.IFNA(VLOOKUP($B124,'2026年1月16日'!$B:$E,4,0),0) | AB124: =AA124-W124 | AC124: =_xlfn.IFNA(VLOOKUP($B124,'2026年1月17日'!$B:$E,4,0),0) | AD124: =AC124-AA124 | AE124: =_xlfn.IFNA(VLOOKUP($B124,'2026年1月19日'!$B:$E,4,0),0) | AF124: =AE124-AC124 | AG124: =_xlfn.IFNA(VLOOKUP($B124,'2026年1月20日'!$B:$E,4,0),0) | AH124: =AG124-AE124 | AI124: =_xlfn.IFNA(VLOOKUP($B124,'2026年1月21日'!$B:$E,4,0),0) | AJ124: =AI124-AG124 | AK124: =_xlfn.IFNA(VLOOKUP($B124,'2026年1月22日'!$B:$E,4,0),0) | AL124: =AK124-AI124 | AM124: =_xlfn.IFNA(VLOOKUP($B124,'2026年1月23日'!$B:$E,4,0),0) | AN124: =AM124-AK124 | AO124: =_xlfn.IFNA(VLOOKUP($B124,'2026年1月24日'!$B:$E,4,0),0) | AP124: =AO124-AM124 | AQ124: =_xlfn.IFNA(VLOOKUP($B124,'2026年1月26日'!$B:$E,4,0),0) | AR124: =AQ124-AO124 | AS124: 54300 | AU124: 54300 | AV124: 0 | AW124: 54300 | AX124: 0 | AY124: 53700 | AZ124: -600 | BA124: 53700 | BB124: 0 | BE124: 49300 | BG124: 46000 | BH124: -3300 | BI124: 49300 | BJ124: 3300 | BK124: 53700 | BL124: 4400 | BM124: 49000 | BN124: -4700 | BO124: 47000 | BP124: -2000 | BQ124: 47000 | BR124: 0 | BS124: 48000 | BT124: 1000 | BU124: 53700 | BV124: 5700 | BW124: 53700 | BX124: 0
B125: B01714 | C125: 聯合證券有限公司 | D125: =_xlfn.IFNA(VLOOKUP($B125,'2026年1月2日'!$B:$E,4,0),0) | E125: =_xlfn.IFNA(VLOOKUP($B125,'2026年1月2日'!$B:$E,4,0),0) | F125: =E125-D125 | G125: =_xlfn.IFNA(VLOOKUP($B125,'2026年1月5日'!$B:$E,4,0),0) | H125: =G125-E125 | I125: =_xlfn.IFNA(VLOOKUP($B125,'2026年1月6日'!$B:$E,4,0),0) | J125: =I125-G125 | K125: =_xlfn.IFNA(VLOOKUP($B125,'2026年1月7日'!$B:$E,4,0),0) | L125: =K125-I125 | M125: =_xlfn.IFNA(VLOOKUP($B125,'2026年1月8日'!$B:$E,4,0),0) | N125: =M125-K125 | O125: =_xlfn.IFNA(VLOOKUP($B125,'2026年1月9日'!$B:$E,4,0),0) | P125: =O125-M125 | Q125: =_xlfn.IFNA(VLOOKUP($B125,'2026年1月10日'!$B:$E,4,0),0) | R125: =Q125-O125 | S125: =_xlfn.IFNA(VLOOKUP($B125,'2026年1月12日'!$B:$E,4,0),0) | T125: =S125-Q125 | U125: =_xlfn.IFNA(VLOOKUP($B125,'2026年1月13日'!$B:$E,4,0),0) | V125: =U125-S125 | W125: =_xlfn.IFNA(VLOOKUP($B125,'2026年1月14日'!$B:$E,4,0),0) | X125: =W125-U125 | Y125: =_xlfn.IFNA(VLOOKUP($B125,'2026年1月15日'!$B:$E,4,0),0) | Z125: =Y125-W125 | AA125: =_xlfn.IFNA(VLOOKUP($B125,'2026年1月16日'!$B:$E,4,0),0) | AB125: =AA125-W125 | AC125: =_xlfn.IFNA(VLOOKUP($B125,'2026年1月17日'!$B:$E,4,0),0) | AD125: =AC125-AA125 | AE125: =_xlfn.IFNA(VLOOKUP($B125,'2026年1月19日'!$B:$E,4,0),0) | AF125: =AE125-AC125 | AG125: =_xlfn.IFNA(VLOOKUP($B125,'2026年1月20日'!$B:$E,4,0),0) | AH125: =AG125-AE125 | AI125: =_xlfn.IFNA(VLOOKUP($B125,'2026年1月21日'!$B:$E,4,0),0) | AJ125: =AI125-AG125 | AK125: =_xlfn.IFNA(VLOOKUP($B125,'2026年1月22日'!$B:$E,4,0),0) | AL125: =AK125-AI125 | AM125: =_xlfn.IFNA(VLOOKUP($B125,'2026年1月23日'!$B:$E,4,0),0) | AN125: =AM125-AK125 | AO125: =_xlfn.IFNA(VLOOKUP($B125,'2026年1月24日'!$B:$E,4,0),0) | AP125: =AO125-AM125 | AQ125: =_xlfn.IFNA(VLOOKUP($B125,'2026年1月26日'!$B:$E,4,0),0) | AR125: =AQ125-AO125 | AS125: 30100 | AU125: 30100 | AV125: 0 | AW125: 30100 | AX125: 0 | AY125: 30100 | AZ125: 0 | BA125: 30100 | BB125: 0 | BE125: 30100 | BG125: 30300 | BH125: 200 | BI125: 30100 | BJ125: -200 | BK125: 30100 | BL125: 0 | BM125: 30100 | BN125: 0 | BO125: 30300 | BP125: 200 | BQ125: 30300 | BR125: 0 | BS125: 30300 | BT125: 0 | BU125: 30100 | BV125: -200 | BW125: 30100 | BX125: 0
B126: B01158 | C126: 堅固證券有限公司 | D126: =_xlfn.IFNA(VLOOKUP($B126,'2026年1月2日'!$B:$E,4,0),0) | E126: =_xlfn.IFNA(VLOOKUP($B126,'2026年1月2日'!$B:$E,4,0),0) | F126: =E126-D126 | G126: =_xlfn.IFNA(VLOOKUP($B126,'2026年1月5日'!$B:$E,4,0),0) | H126: =G126-E126 | I126: =_xlfn.IFNA(VLOOKUP($B126,'2026年1月6日'!$B:$E,4,0),0) | J126: =I126-G126 | K126: =_xlfn.IFNA(VLOOKUP($B126,'2026年1月7日'!$B:$E,4,0),0) | L126: =K126-I126 | M126: =_xlfn.IFNA(VLOOKUP($B126,'2026年1月8日'!$B:$E,4,0),0) | N126: =M126-K126 | O126: =_xlfn.IFNA(VLOOKUP($B126,'2026年1月9日'!$B:$E,4,0),0) | P126: =O126-M126 | Q126: =_xlfn.IFNA(VLOOKUP($B126,'2026年1月10日'!$B:$E,4,0),0) | R126: =Q126-O126 | S126: =_xlfn.IFNA(VLOOKUP($B126,'2026年1月12日'!$B:$E,4,0),0) | T126: =S126-Q126 | U126: =_xlfn.IFNA(VLOOKUP($B126,'2026年1月13日'!$B:$E,4,0),0) | V126: =U126-S126 | W126: =_xlfn.IFNA(VLOOKUP($B126,'2026年1月14日'!$B:$E,4,0),0) | X126: =W126-U126 | Y126: =_xlfn.IFNA(VLOOKUP($B126,'2026年1月15日'!$B:$E,4,0),0) | Z126: =Y126-W126 | AA126: =_xlfn.IFNA(VLOOKUP($B126,'2026年1月16日'!$B:$E,4,0),0) | AB126: =AA126-W126 | AC126: =_xlfn.IFNA(VLOOKUP($B126,'2026年1月17日'!$B:$E,4,0),0) | AD126: =AC126-AA126 | AE126: =_xlfn.IFNA(VLOOKUP($B126,'2026年1月19日'!$B:$E,4,0),0) | AF126: =AE126-AC126 | AG126: =_xlfn.IFNA(VLOOKUP($B126,'2026年1月20日'!$B:$E,4,0),0) | AH126: =AG126-AE126 | AI126: =_xlfn.IFNA(VLOOKUP($B126,'2026年1月21日'!$B:$E,4,0),0) | AJ126: =AI126-AG126 | AK126: =_xlfn.IFNA(VLOOKUP($B126,'2026年1月22日'!$B:$E,4,0),0) | AL126: =AK126-AI126 | AM126: =_xlfn.IFNA(VLOOKUP($B126,'2026年1月23日'!$B:$E,4,0),0) | AN126: =AM126-AK126 | AO126: =_xlfn.IFNA(VLOOKUP($B126,'2026年1月24日'!$B:$E,4,0),0) | AP126: =AO126-AM126 | AQ126: =_xlfn.IFNA(VLOOKUP($B126,'2026年1月26日'!$B:$E,4,0),0) | AR126: =AQ126-AO126 | AS126: 24800 | AU126: 24800 | AV126: 0 | AW126: 24800 | AX126: 0 | AY126: 24800 | AZ126: 0 | BA126: 24800 | BB126: 0 | BE126: 25300 | BG126: 28800 | BH126: 3500 | BI126: 25300 | BJ126: -3500 | BK126: 24800 | BL126: -500 | BM126: 29300 | BN126: 4500 | BO126: 38300 | BP126: 9000 | BQ126: 38300 | BR126: 0 | BS126: 38300 | BT126: 0 | BU126: 24800 | BV126: -13500 | BW126: 24800 | BX126: 0
B127: B01978 | C127: 方正證券(香港)有限公司 | D127: =_xlfn.IFNA(VLOOKUP($B127,'2026年1月2日'!$B:$E,4,0),0) | E127: =_xlfn.IFNA(VLOOKUP($B127,'2026年1月2日'!$B:$E,4,0),0) | F127: =E127-D127 | G127: =_xlfn.IFNA(VLOOKUP($B127,'2026年1月5日'!$B:$E,4,0),0) | H127: =G127-E127 | I127: =_xlfn.IFNA(VLOOKUP($B127,'2026年1月6日'!$B:$E,4,0),0) | J127: =I127-G127 | K127: =_xlfn.IFNA(VLOOKUP($B127,'2026年1月7日'!$B:$E,4,0),0) | L127: =K127-I127 | M127: =_xlfn.IFNA(VLOOKUP($B127,'2026年1月8日'!$B:$E,4,0),0) | N127: =M127-K127 | O127: =_xlfn.IFNA(VLOOKUP($B127,'2026年1月9日'!$B:$E,4,0),0) | P127: =O127-M127 | Q127: =_xlfn.IFNA(VLOOKUP($B127,'2026年1月10日'!$B:$E,4,0),0) | R127: =Q127-O127 | S127: =_xlfn.IFNA(VLOOKUP($B127,'2026年1月12日'!$B:$E,4,0),0) | T127: =S127-Q127 | U127: =_xlfn.IFNA(VLOOKUP($B127,'2026年1月13日'!$B:$E,4,0),0) | V127: =U127-S127 | W127: =_xlfn.IFNA(VLOOKUP($B127,'2026年1月14日'!$B:$E,4,0),0) | X127: =W127-U127 | Y127: =_xlfn.IFNA(VLOOKUP($B127,'2026年1月15日'!$B:$E,4,0),0) | Z127: =Y127-W127 | AA127: =_xlfn.IFNA(VLOOKUP($B127,'2026年1月16日'!$B:$E,4,0),0) | AB127: =AA127-W127 | AC127: =_xlfn.IFNA(VLOOKUP($B127,'2026年1月17日'!$B:$E,4,0),0) | AD127: =AC127-AA127 | AE127: =_xlfn.IFNA(VLOOKUP($B127,'2026年1月19日'!$B:$E,4,0),0) | AF127: =AE127-AC127 | AG127: =_xlfn.IFNA(VLOOKUP($B127,'2026年1月20日'!$B:$E,4,0),0) | AH127: =AG127-AE127 | AI127: =_xlfn.IFNA(VLOOKUP($B127,'2026年1月21日'!$B:$E,4,0),0) | AJ127: =AI127-AG127 | AK127: =_xlfn.IFNA(VLOOKUP($B127,'2026年1月22日'!$B:$E,4,0),0) | AL127: =AK127-AI127 | AM127: =_xlfn.IFNA(VLOOKUP($B127,'2026年1月23日'!$B:$E,4,0),0) | AN127: =AM127-AK127 | AO127: =_xlfn.IFNA(VLOOKUP($B127,'2026年1月24日'!$B:$E,4,0),0) | AP127: =AO127-AM127 | AQ127: =_xlfn.IFNA(VLOOKUP($B127,'2026年1月26日'!$B:$E,4,0),0) | AR127: =AQ127-AO127 | AS127: 16100 | AU127: 16100 | AV127: 0 | AW127: 16100 | AX127: 0 | AY127: 16100 | AZ127: 0 | BA127: 16100 | BB127: 0 | BE127: 35100 | BG127: 126600 | BH127: 91500 | BI127: 35100 | BJ127: -91500 | BK127: 16100 | BL127: -19000 | BM127: 45100 | BN127: 29000 | BO127: 132700 | BP127: 87600 | BQ127: 132700 | BR127: 0 | BS127: 132700 | BT127: 0 | BU127: 16100 | BV127: -116600 | BW127: 16100 | BX127: 0
... B165: B01696 | C165: 亨達証券有限公司 | D165: =_xlfn.IFNA(VLOOKUP($B165,'2026年1月2日'!$B:$E,4,0),0) | E165: =_xlfn.IFNA(VLOOKUP($B165,'2026年1月2日'!$B:$E,4,0),0) | F165: =E165-D165 | G165: =_xlfn.IFNA(VLOOKUP($B165,'2026年1月5日'!$B:$E,4,0),0) | H165: =G165-E165 | I165: =_xlfn.IFNA(VLOOKUP($B165,'2026年1月6日'!$B:$E,4,0),0) | J165: =I165-G165 | K165: =_xlfn.IFNA(VLOOKUP($B165,'2026年1月7日'!$B:$E,4,0),0) | L165: =K165-I165 | M165: =_xlfn.IFNA(VLOOKUP($B165,'2026年1月8日'!$B:$E,4,0),0) | N165: =M165-K165 | O165: =_xlfn.IFNA(VLOOKUP($B165,'2026年1月9日'!$B:$E,4,0),0) | P165: =O165-M165 | Q165: =_xlfn.IFNA(VLOOKUP($B165,'2026年1月10日'!$B:$E,4,0),0) | R165: =Q165-O165 | S165: =_xlfn.IFNA(VLOOKUP($B165,'2026年1月12日'!$B:$E,4,0),0) | T165: =S165-Q165 | U165: =_xlfn.IFNA(VLOOKUP($B165,'2026年1月13日'!$B:$E,4,0),0) | V165: =U165-S165 | W165: =_xlfn.IFNA(VLOOKUP($B165,'2026年1月14日'!$B:$E,4,0),0) | X165: =W165-U165 | Y165: =_xlfn.IFNA(VLOOKUP($B165,'2026年1月15日'!$B:$E,4,0),0) | Z165: =Y165-W165 | AA165: =_xlfn.IFNA(VLOOKUP($B165,'2026年1月16日'!$B:$E,4,0),0) | AB165: =AA165-W165 | AC165: =_xlfn.IFNA(VLOOKUP($B165,'2026年1月17日'!$B:$E,4,0),0) | AD165: =AC165-AA165 | AE165: =_xlfn.IFNA(VLOOKUP($B165,'2026年1月19日'!$B:$E,4,0),0) | AF165: =AE165-AC165 | AG165: =_xlfn.IFNA(VLOOKUP($B165,'2026年1月20日'!$B:$E,4,0),0) | AH165: =AG165-AE165 | AI165: =_xlfn.IFNA(VLOOKUP($B165,'2026年1月21日'!$B:$E,4,0),0) | AJ165: =AI165-AG165 | AK165: =_xlfn.IFNA(VLOOKUP($B165,'2026年1月22日'!$B:$E,4,0),0) | AL165: =AK165-AI165 | AM165: =_xlfn.IFNA(VLOOKUP($B165,'2026年1月23日'!$B:$E,4,0),0) | AN165: =AM165-AK165 | AO165: =_xlfn.IFNA(VLOOKUP($B165,'2026年1月24日'!$B:$E,4,0),0) | AP165: =AO165-AM165 | AQ165: =_xlfn.IFNA(VLOOKUP($B165,'2026年1月26日'!$B:$E,4,0),0) | AR165: =AQ165-AO165 | AS165: 12200 | AU165: 12200 | AV165: 0 | AW165: 12200 | AX165: 0 | AY165: 12200 | AZ165: 0 | BA165: 12200 | BB165: 0 | BE165: 12200 | BG165: 12600 | BH165: 400 | BI165: 12200 | BJ165: -400 | BK165: 12200 | BL165: 0 | BM165: 12200 | BN165: 0 | BO165: 12600 | BP165: 400 | BQ165: 12600 | BR165: 0 | BS165: 12600 | BT165: 0 | BU165: 12200 | BV165: -400 | BW165: 12200 | BX165: 0
B166: B01789 | C166: 浩豐證券投資有限公司 | D166: =_xlfn.IFNA(VLOOKUP($B166,'2026年1月2日'!$B:$E,4,0),0) | E166: =_xlfn.IFNA(VLOOKUP($B166,'2026年1月2日'!$B:$E,4,0),0) | F166: =E166-D166 | G166: =_xlfn.IFNA(VLOOKUP($B166,'2026年1月5日'!$B:$E,4,0),0) | H166: =G166-E166 | I166: =_xlfn.IFNA(VLOOKUP($B166,'2026年1月6日'!$B:$E,4,0),0) | J166: =I166-G166 | K166: =_xlfn.IFNA(VLOOKUP($B166,'2026年1月7日'!$B:$E,4,0),0) | L166: =K166-I166 | M166: =_xlfn.IFNA(VLOOKUP($B166,'2026年1月8日'!$B:$E,4,0),0) | N166: =M166-K166 | O166: =_xlfn.IFNA(VLOOKUP($B166,'2026年1月9日'!$B:$E,4,0),0) | P166: =O166-M166 | Q166: =_xlfn.IFNA(VLOOKUP($B166,'2026年1月10日'!$B:$E,4,0),0) | R166: =Q166-O166 | S166: =_xlfn.IFNA(VLOOKUP($B166,'2026年1月12日'!$B:$E,4,0),0) | T166: =S166-Q166 | U166: =_xlfn.IFNA(VLOOKUP($B166,'2026年1月13日'!$B:$E,4,0),0) | V166: =U166-S166 | W166: =_xlfn.IFNA(VLOOKUP($B166,'2026年1月14日'!$B:$E,4,0),0) | X166: =W166-U166 | Y166: =_xlfn.IFNA(VLOOKUP($B166,'2026年1月15日'!$B:$E,4,0),0) | Z166: =Y166-W166 | AA166: =_xlfn.IFNA(VLOOKUP($B166,'2026年1月16日'!$B:$E,4,0),0) | AB166: =AA166-W166 | AC166: =_xlfn.IFNA(VLOOKUP($B166,'2026年1月17日'!$B:$E,4,0),0) | AD166: =AC166-AA166 | AE166: =_xlfn.IFNA(VLOOKUP($B166,'2026年1月19日'!$B:$E,4,0),0) | AF166: =AE166-AC166 | AG166: =_xlfn.IFNA(VLOOKUP($B166,'2026年1月20日'!$B:$E,4,0),0) | AH166: =AG166-AE166 | AI166: =_xlfn.IFNA(VLOOKUP($B166,'2026年1月21日'!$B:$E,4,0),0) | AJ166: =AI166-AG166 | AK166: =_xlfn.IFNA(VLOOKUP($B166,'2026年1月22日'!$B:$E,4,0),0) | AL166: =AK166-AI166 | AM166: =_xlfn.IFNA(VLOOKUP($B166,'2026年1月23日'!$B:$E,4,0),0) | AN166: =AM166-AK166 | AO166: =_xlfn.IFNA(VLOOKUP($B166,'2026年1月24日'!$B:$E,4,0),0) | AP166: =AO166-AM166 | AQ166: =_xlfn.IFNA(VLOOKUP($B166,'2026年1月26日'!$B:$E,4,0),0) | AR166: =AQ166-AO166 | BG166: 10000 | BO166: 10000 | BQ166: 10000 | BR166: 0 | BS166: 10000 | BT166: 0
B167: B01213 | C167: 萬利豐證券有限公司 | D167: =_xlfn.IFNA(VLOOKUP($B167,'2026年1月2日'!$B:$E,4,0),0) | E167: =_xlfn.IFNA(VLOOKUP($B167,'2026年1月2日'!$B:$E,4,0),0) | F167: =E167-D167 | G167: =_xlfn.IFNA(VLOOKUP($B167,'2026年1月5日'!$B:$E,4,0),0) | H167: =G167-E167 | I167: =_xlfn.IFNA(VLOOKUP($B167,'2026年1月6日'!$B:$E,4,0),0) | J167: =I167-G167 | K167: =_xlfn.IFNA(VLOOKUP($B167,'2026年1月7日'!$B:$E,4,0),0) | L167: =K167-I167 | M167: =_xlfn.IFNA(VLOOKUP($B167,'2026年1月8日'!$B:$E,4,0),0) | N167: =M167-K167 | O167: =_xlfn.IFNA(VLOOKUP($B167,'2026年1月9日'!$B:$E,4,0),0) | P167: =O167-M167 | Q167: =_xlfn.IFNA(VLOOKUP($B167,'2026年1月10日'!$B:$E,4,0),0) | R167: =Q167-O167 | S167: =_xlfn.IFNA(VLOOKUP($B167,'2026年1月12日'!$B:$E,4,0),0) | T167: =S167-Q167 | U167: =_xlfn.IFNA(VLOOKUP($B167,'2026年1月13日'!$B:$E,4,0),0) | V167: =U167-S167 | W167: =_xlfn.IFNA(VLOOKUP($B167,'2026年1月14日'!$B:$E,4,0),0) | X167: =W167-U167 | Y167: =_xlfn.IFNA(VLOOKUP($B167,'2026年1月15日'!$B:$E,4,0),0) | Z167: =Y167-W167 | AA167: =_xlfn.IFNA(VLOOKUP($B167,'2026年1月16日'!$B:$E,4,0),0) | AB167: =AA167-W167 | AC167: =_xlfn.IFNA(VLOOKUP($B167,'2026年1月17日'!$B:$E,4,0),0) | AD167: =AC167-AA167 | AE167: =_xlfn.IFNA(VLOOKUP($B167,'2026年1月19日'!$B:$E,4,0),0) | AF167: =AE167-AC167 | AG167: =_xlfn.IFNA(VLOOKUP($B167,'2026年1月20日'!$B:$E,4,0),0) | AH167: =AG167-AE167 | AI167: =_xlfn.IFNA(VLOOKUP($B167,'2026年1月21日'!$B:$E,4,0),0) | AJ167: =AI167-AG167 | AK167: =_xlfn.IFNA(VLOOKUP($B167,'2026年1月22日'!$B:$E,4,0),0) | AL167: =AK167-AI167 | AM167: =_xlfn.IFNA(VLOOKUP($B167,'2026年1月23日'!$B:$E,4,0),0) | AN167: =AM167-AK167 | AO167: =_xlfn.IFNA(VLOOKUP($B167,'2026年1月24日'!$B:$E,4,0),0) | AP167: =AO167-AM167 | AQ167: =_xlfn.IFNA(VLOOKUP($B167,'2026年1月26日'!$B:$E,4,0),0) | AR167: =AQ167-AO167 | AS167: 24000 | AU167: 24000 | AV167: 0 | AW167: 24000 | AX167: 0 | AY167: 24000 | AZ167: 0 | BA167: 24000 | BB167: 0 | BE167: 24000 | BG167: 24000 | BH167: 0 | BI167: 24000 | BJ167: 0 | BK167: 24000 | BL167: 0 | BM167: 24000 | BN167: 0 | BO167: 24000 | BP167: 0 | BQ167: 24000 | BR167: 0 | BS167: 24000 | BT167: 0 | BU167: 24000 | BV167: 0 | BW167: 24000 | BX167: 0
B168: B01324 | C168: FUNDERSTONE SECURITIES LTD | D168: =_xlfn.IFNA(VLOOKUP($B168,'2026年1月2日'!$B:$E,4,0),0) | E168: =_xlfn.IFNA(VLOOKUP($B168,'2026年1月2日'!$B:$E,4,0),0) | F168: =E168-D168 | G168: =_xlfn.IFNA(VLOOKUP($B168,'2026年1月5日'!$B:$E,4,0),0) | H168: =G168-E168 | I168: =_xlfn.IFNA(VLOOKUP($B168,'2026年1月6日'!$B:$E,4,0),0) | J168: =I168-G168 | K168: =_xlfn.IFNA(VLOOKUP($B168,'2026年1月7日'!$B:$E,4,0),0) | L168: =K168-I168 | M168: =_xlfn.IFNA(VLOOKUP($B168,'2026年1月8日'!$B:$E,4,0),0) | N168: =M168-K168 | O168: =_xlfn.IFNA(VLOOKUP($B168,'2026年1月9日'!$B:$E,4,0),0) | P168: =O168-M168 | Q168: =_xlfn.IFNA(VLOOKUP($B168,'2026年1月10日'!$B:$E,4,0),0) | R168: =Q168-O168 | S168: =_xlfn.IFNA(VLOOKUP($B168,'2026年1月12日'!$B:$E,4,0),0) | T168: =S168-Q168 | U168: =_xlfn.IFNA(VLOOKUP($B168,'2026年1月13日'!$B:$E,4,0),0) | V168: =U168-S168 | W168: =_xlfn.IFNA(VLOOKUP($B168,'2026年1月14日'!$B:$E,4,0),0) | X168: =W168-U168 | Y168: =_xlfn.IFNA(VLOOKUP($B168,'2026年1月15日'!$B:$E,4,0),0) | Z168: =Y168-W168 | AA168: =_xlfn.IFNA(VLOOKUP($B168,'2026年1月16日'!$B:$E,4,0),0) | AB168: =AA168-W168 | AC168: =_xlfn.IFNA(VLOOKUP($B168,'2026年1月17日'!$B:$E,4,0),0) | AD168: =AC168-AA168 | AE168: =_xlfn.IFNA(VLOOKUP($B168,'2026年1月19日'!$B:$E,4,0),0) | AF168: =AE168-AC168 | AG168: =_xlfn.IFNA(VLOOKUP($B168,'2026年1月20日'!$B:$E,4,0),0) | AH168: =AG168-AE168 | AI168: =_xlfn.IFNA(VLOOKUP($B168,'2026年1月21日'!$B:$E,4,0),0) | AJ168: =AI168-AG168 | AK168: =_xlfn.IFNA(VLOOKUP($B168,'2026年1月22日'!$B:$E,4,0),0) | AL168: =AK168-AI168 | AM168: =_xlfn.IFNA(VLOOKUP($B168,'2026年1月23日'!$B:$E,4,0),0) | AN168: =AM168-AK168 | AO168: =_xlfn.IFNA(VLOOKUP($B168,'2026年1月24日'!$B:$E,4,0),0) | AP168: =AO168-AM168 | AQ168: =_xlfn.IFNA(VLOOKUP($B168,'2026年1月26日'!$B:$E,4,0),0) | AR168: =AQ168-AO168 | AS168: 80400 | AU168: 80400 | AV168: 0 | AW168: 80400 | AX168: 0 | AY168: 80400 | AZ168: 0 | BA168: 80400 | BB168: 0 | BE168: 20400 | BG168: 30500 | BH168: 10100 | BI168: 20400 | BJ168: -10100 | BK168: 80400 | BL168: 60000 | BM168: 20400 | BN168: -60000 | BO168: 20500 | BP168: 100 | BQ168: 20500 | BR168: 0 | BS168: 20500 | BT168: 0 | BU168: 80400 | BV168: 59900 | BW168: 80400 | BX168: 0
B169: B01373 | C169: 恆豐證券有限公司 | D169: =_xlfn.IFNA(VLOOKUP($B169,'2026年1月2日'!$B:$E,4,0),0) | E169: =_xlfn.IFNA(VLOOKUP($B169,'2026年1月2日'!$B:$E,4,0),0) | F169: =E169-D169 | G169: =_xlfn.IFNA(VLOOKUP($B169,'2026年1月5日'!$B:$E,4,0),0) | H169: =G169-E169 | I169: =_xlfn.IFNA(VLOOKUP($B169,'2026年1月6日'!$B:$E,4,0),0) | J169: =I169-G169 | K169: =_xlfn.IFNA(VLOOKUP($B169,'2026年1月7日'!$B:$E,4,0),0) | L169: =K169-I169 | M169: =_xlfn.IFNA(VLOOKUP($B169,'2026年1月8日'!$B:$E,4,0),0) | N169: =M169-K169 | O169: =_xlfn.IFNA(VLOOKUP($B169,'2026年1月9日'!$B:$E,4,0),0) | P169: =O169-M169 | Q169: =_xlfn.IFNA(VLOOKUP($B169,'2026年1月10日'!$B:$E,4,0),0) | R169: =Q169-O169 | S169: =_xlfn.IFNA(VLOOKUP($B169,'2026年1月12日'!$B:$E,4,0),0) | T169: =S169-Q169 | U169: =_xlfn.IFNA(VLOOKUP($B169,'2026年1月13日'!$B:$E,4,0),0) | V169: =U169-S169 | W169: =_xlfn.IFNA(VLOOKUP($B169,'2026年1月14日'!$B:$E,4,0),0) | X169: =W169-U169 | Y169: =_xlfn.IFNA(VLOOKUP($B169,'2026年1月15日'!$B:$E,4,0),0) | Z169: =Y169-W169 | AA169: =_xlfn.IFNA(VLOOKUP($B169,'2026年1月16日'!$B:$E,4,0),0) | AB169: =AA169-W169 | AC169: =_xlfn.IFNA(VLOOKUP($B169,'2026年1月17日'!$B:$E,4,0),0) | AD169: =AC169-AA169 | AE169: =_xlfn.IFNA(VLOOKUP($B169,'2026年1月19日'!$B:$E,4,0),0) | AF169: =AE169-AC169 | AG169: =_xlfn.IFNA(VLOOKUP($B169,'2026年1月20日'!$B:$E,4,0),0) | AH169: =AG169-AE169 | AI169: =_xlfn.IFNA(VLOOKUP($B169,'2026年1月21日'!$B:$E,4,0),0) | AJ169: =AI169-AG169 | AK169: =_xlfn.IFNA(VLOOKUP($B169,'2026年1月22日'!$B:$E,4,0),0) | AL169: =AK169-AI169 | AM169: =_xlfn.IFNA(VLOOKUP($B169,'2026年1月23日'!$B:$E,4,0),0) | AN169: =AM169-AK169 | AO169: =_xlfn.IFNA(VLOOKUP($B169,'2026年1月24日'!$B:$E,4,0),0) | AP169: =AO169-AM169 | AQ169: =_xlfn.IFNA(VLOOKUP($B169,'2026年1月26日'!$B:$E,4,0),0) | AR169: =AQ169-AO169 | AS169: 136000 | AU169: 136000 | AV169: 0 | AW169: 136000 | AX169: 0 | AY169: 136000 | AZ169: 0 | BA169: 136000 | BB169: 0 | BE169: 145900 | BG169: 20000 | BH169: -125900 | BI169: 145900 | BJ169: 125900 | BK169: 136000 | BL169: -9900 | BM169: 135000 | BN169: -1000 | BO169: 14100 | BP169: -120900 | BQ169: 14100 | BR169: 0 | BS169: 51800 | BT169: 37700 | BU169: 136000 | BV169: 84200 | BW169: 136000 | BX169: 0
B170: B01923 | C170: 易昇證券有限公司 | D170: =_xlfn.IFNA(VLOOKUP($B170,'2026年1月2日'!$B:$E,4,0),0) | E170: =_xlfn.IFNA(VLOOKUP($B170,'2026年1月2日'!$B:$E,4,0),0) | F170: =E170-D170 | G170: =_xlfn.IFNA(VLOOKUP($B170,'2026年1月5日'!$B:$E,4,0),0) | H170: =G170-E170 | I170: =_xlfn.IFNA(VLOOKUP($B170,'2026年1月6日'!$B:$E,4,0),0) | J170: =I170-G170 | K170: =_xlfn.IFNA(VLOOKUP($B170,'2026年1月7日'!$B:$E,4,0),0) | L170: =K170-I170 | M170: =_xlfn.IFNA(VLOOKUP($B170,'2026年1月8日'!$B:$E,4,0),0) | N170: =M170-K170 | O170: =_xlfn.IFNA(VLOOKUP($B170,'2026年1月9日'!$B:$E,4,0),0) | P170: =O170-M170 | Q170: =_xlfn.IFNA(VLOOKUP($B170,'2026年1月10日'!$B:$E,4,0),0) | R170: =Q170-O170 | S170: =_xlfn.IFNA(VLOOKUP($B170,'2026年1月12日'!$B:$E,4,0),0) | T170: =S170-Q170 | U170: =_xlfn.IFNA(VLOOKUP($B170,'2026年1月13日'!$B:$E,4,0),0) | V170: =U170-S170 | W170: =_xlfn.IFNA(VLOOKUP($B170,'2026年1月14日'!$B:$E,4,0),0) | X170: =W170-U170 | Y170: =_xlfn.IFNA(VLOOKUP($B170,'2026年1月15日'!$B:$E,4,0),0) | Z170: =Y170-W170 | AA170: =_xlfn.IFNA(VLOOKUP($B170,'2026年1月16日'!$B:$E,4,0),0) | AB170: =AA170-W170 | AC170: =_xlfn.IFNA(VLOOKUP($B170,'2026年1月17日'!$B:$E,4,0),0) | AD170: =AC170-AA170 | AE170: =_xlfn.IFNA(VLOOKUP($B170,'2026年1月19日'!$B:$E,4,0),0) | AF170: =AE170-AC170 | AG170: =_xlfn.IFNA(VLOOKUP($B170,'2026年1月20日'!$B:$E,4,0),0) | AH170: =AG170-AE170 | AI170: =_xlfn.IFNA(VLOOKUP($B170,'2026年1月21日'!$B:$E,4,0),0) | AJ170: =AI170-AG170 | AK170: =_xlfn.IFNA(VLOOKUP($B170,'2026年1月22日'!$B:$E,4,0),0) | AL170: =AK170-AI170 | AM170: =_xlfn.IFNA(VLOOKUP($B170,'2026年1月23日'!$B:$E,4,0),0) | AN170: =AM170-AK170 | AO170: =_xlfn.IFNA(VLOOKUP($B170,'2026年1月24日'!$B:$E,4,0),0) | AP170: =AO170-AM170 | AQ170: =_xlfn.IFNA(VLOOKUP($B170,'2026年1月26日'!$B:$E,4,0),0) | AR170: =AQ170-AO170 | AS170: 10200 | AU170: 10200 | AV170: 0 | AW170: 10200 | AX170: 0 | AY170: 10200 | AZ170: 0 | BA170: 10200 | BB170: 0 | BE170: 10300 | BG170: 10300 | BH170: 0 | BI170: 10300 | BJ170: 0 | BK170: 10200 | BL170: -100 | BM170: 10300 | BN170: 100 | BO170: 10300 | BP170: 0 | BQ170: 10300 | BR170: 0 | BS170: 10300 | BT170: 0 | BU170: 10200 | BV170: -100 | BW170: 10200 | BX170: 0
B171: B01788 | C171: 齊榮證券有限公司 | D171: =_xlfn.IFNA(VLOOKUP($B171,'2026年1月2日'!$B:$E,4,0),0) | E171: =_xlfn.IFNA(VLOOKUP($B171,'2026年1月2日'!$B:$E,4,0),0) | F171: =E171-D171 | G171: =_xlfn.IFNA(VLOOKUP($B171,'2026年1月5日'!$B:$E,4,0),0) | H171: =G171-E171 | I171: =_xlfn.IFNA(VLOOKUP($B171,'2026年1月6日'!$B:$E,4,0),0) | J171: =I171-G171 | K171: =_xlfn.IFNA(VLOOKUP($B171,'2026年1月7日'!$B:$E,4,0),0) | L171: =K171-I171 | M171: =_xlfn.IFNA(VLOOKUP($B171,'2026年1月8日'!$B:$E,4,0),0) | N171: =M171-K171 | O171: =_xlfn.IFNA(VLOOKUP($B171,'2026年1月9日'!$B:$E,4,0),0) | P171: =O171-M171 | Q171: =_xlfn.IFNA(VLOOKUP($B171,'2026年1月10日'!$B:$E,4,0),0) | R171: =Q171-O171 | S171: =_xlfn.IFNA(VLOOKUP($B171,'2026年1月12日'!$B:$E,4,0),0) | T171: =S171-Q171 | U171: =_xlfn.IFNA(VLOOKUP($B171,'2026年1月13日'!$B:$E,4,0),0) | V171: =U171-S171 | W171: =_xlfn.IFNA(VLOOKUP($B171,'2026年1月14日'!$B:$E,4,0),0) | X171: =W171-U171 | Y171: =_xlfn.IFNA(VLOOKUP($B171,'2026年1月15日'!$B:$E,4,0),0) | Z171: =Y171-W171 | AA171: =_xlfn.IFNA(VLOOKUP($B171,'2026年1月16日'!$B:$E,4,0),0) | AB171: =AA171-W171 | AC171: =_xlfn.IFNA(VLOOKUP($B171,'2026年1月17日'!$B:$E,4,0),0) | AD171: =AC171-AA171 | AE171: =_xlfn.IFNA(VLOOKUP($B171,'2026年1月19日'!$B:$E,4,0),0) | AF171: =AE171-AC171 | AG171: =_xlfn.IFNA(VLOOKUP($B171,'2026年1月20日'!$B:$E,4,0),0) | AH171: =AG171-AE171 | AI171: =_xlfn.IFNA(VLOOKUP($B171,'2026年1月21日'!$B:$E,4,0),0) | AJ171: =AI171-AG171 | AK171: =_xlfn.IFNA(VLOOKUP($B171,'2026年1月22日'!$B:$E,4,0),0) | AL171: =AK171-AI171 | AM171: =_xlfn.IFNA(VLOOKUP($B171,'2026年1月23日'!$B:$E,4,0),0) | AN171: =AM171-AK171 | AO171: =_xlfn.IFNA(VLOOKUP($B171,'2026年1月24日'!$B:$E,4,0),0) | AP171: =AO171-AM171 | AQ171: =_xlfn.IFNA(VLOOKUP($B171,'2026年1月26日'!$B:$E,4,0),0) | AR171: =AQ171-AO171 | AS171: 20400 | AU171: 20400 | AV171: 0 | AW171: 20400 | AX171: 0 | AY171: 20400 | AZ171: 0 | BA171: 20400 | BB171: 0 | BE171: 23400 | BG171: 23400 | BH171: 0 | BI171: 23400 | BJ171: 0 | BK171: 20400 | BL171: -3000 | BM171: 23400 | BN171: 3000 | BO171: 18400 | BP171: -5000 | BQ171: 18400 | BR171: 0 | BS171: 23400 | BT171: 5000 | BU171: 20400 | BV171: -3000 | BW171: 20400 | BX171: 0
B172: B01253 | C172: 常匯證券有限公司 | D172: =_xlfn.IFNA(VLOOKUP($B172,'2026年1月2日'!$B:$E,4,0),0) | E172: =_xlfn.IFNA(VLOOKUP($B172,'2026年1月2日'!$B:$E,4,0),0) | F172: =E172-D172 | G172: =_xlfn.IFNA(VLOOKUP($B172,'2026年1月5日'!$B:$E,4,0),0) | H172: =G172-E172 | I172: =_xlfn.IFNA(VLOOKUP($B172,'2026年1月6日'!$B:$E,4,0),0) | J172: =I172-G172 | K172: =_xlfn.IFNA(VLOOKUP($B172,'2026年1月7日'!$B:$E,4,0),0) | L172: =K172-I172 | M172: =_xlfn.IFNA(VLOOKUP($B172,'2026年1月8日'!$B:$E,4,0),0) | N172: =M172-K172 | O172: =_xlfn.IFNA(VLOOKUP($B172,'2026年1月9日'!$B:$E,4,0),0) | P172: =O172-M172 | Q172: =_xlfn.IFNA(VLOOKUP($B172,'2026年1月10日'!$B:$E,4,0),0) | R172: =Q172-O172 | S172: =_xlfn.IFNA(VLOOKUP($B172,'2026年1月12日'!$B:$E,4,0),0) | T172: =S172-Q172 | U172: =_xlfn.IFNA(VLOOKUP($B172,'2026年1月13日'!$B:$E,4,0),0) | V172: =U172-S172 | W172: =_xlfn.IFNA(VLOOKUP($B172,'2026年1月14日'!$B:$E,4,0),0) | X172: =W172-U172 | Y172: =_xlfn.IFNA(VLOOKUP($B172,'2026年1月15日'!$B:$E,4,0),0) | Z172: =Y172-W172 | AA172: =_xlfn.IFNA(VLOOKUP($B172,'2026年1月16日'!$B:$E,4,0),0) | AB172: =AA172-W172 | AC172: =_xlfn.IFNA(VLOOKUP($B172,'2026年1月17日'!$B:$E,4,0),0) | AD172: =AC172-AA172 | AE172: =_xlfn.IFNA(VLOOKUP($B172,'2026年1月19日'!$B:$E,4,0),0) | AF172: =AE172-AC172 | AG172: =_xlfn.IFNA(VLOOKUP($B172,'2026年1月20日'!$B:$E,4,0),0) | AH172: =AG172-AE172 | AI172: =_xlfn.IFNA(VLOOKUP($B172,'2026年1月21日'!$B:$E,4,0),0) | AJ172: =AI172-AG172 | AK172: =_xlfn.IFNA(VLOOKUP($B172,'2026年1月22日'!$B:$E,4,0),0) | AL172: =AK172-AI172 | AM172: =_xlfn.IFNA(VLOOKUP($B172,'2026年1月23日'!$B:$E,4,0),0) | AN172: =AM172-AK172 | AO172: =_xlfn.IFNA(VLOOKUP($B172,'2026年1月24日'!$B:$E,4,0),0) | AP172: =AO172-AM172 | AQ172: =_xlfn.IFNA(VLOOKUP($B172,'2026年1月26日'!$B:$E,4,0),0) | AR172: =AQ172-AO172 | AS172: 1500 | AU172: 1500 | AV172: 0 | AW172: 1500 | AX172: 0 | AY172: 1500 | AZ172: 0 | BA172: 1500 | BB172: 0 | BE172: 1500 | BG172: 2000 | BH172: 500 | BI172: 1500 | BJ172: -500 | BK172: 1500 | BL172: 0 | BM172: 1500 | BN172: 0 | BO172: 2000 | BP172: 500 | BQ172: 2000 | BR172: 0 | BS172: 2000 | BT172: 0 | BU172: 1500 | BV172: -500 | BW172: 1500 | BX172: 0
B173: B01601 | C173: 群益證券(香港)有限公司 | D173: =_xlfn.IFNA(VLOOKUP($B173,'2026年1月2日'!$B:$E,4,0),0) | E173: =_xlfn.IFNA(VLOOKUP($B173,'2026年1月2日'!$B:$E,4,0),0) | F173: =E173-D173 | G173: =_xlfn.IFNA(VLOOKUP($B173,'2026年1月5日'!$B:$E,4,0),0) | H173: =G173-E173 | I173: =_xlfn.IFNA(VLOOKUP($B173,'2026年1月6日'!$B:$E,4,0),0) | J173: =I173-G173 | K173: =_xlfn.IFNA(VLOOKUP($B173,'2026年1月7日'!$B:$E,4,0),0) | L173: =K173-I173 | M173: =_xlfn.IFNA(VLOOKUP($B173,'2026年1月8日'!$B:$E,4,0),0) | N173: =M173-K173 | O173: =_xlfn.IFNA(VLOOKUP($B173,'2026年1月9日'!$B:$E,4,0),0) | P173: =O173-M173 | Q173: =_xlfn.IFNA(VLOOKUP($B173,'2026年1月10日'!$B:$E,4,0),0) | R173: =Q173-O173 | S173: =_xlfn.IFNA(VLOOKUP($B173,'2026年1月12日'!$B:$E,4,0),0) | T173: =S173-Q173 | U173: =_xlfn.IFNA(VLOOKUP($B173,'2026年1月13日'!$B:$E,4,0),0) | V173: =U173-S173 | W173: =_xlfn.IFNA(VLOOKUP($B173,'2026年1月14日'!$B:$E,4,0),0) | X173: =W173-U173 | Y173: =_xlfn.IFNA(VLOOKUP($B173,'2026年1月15日'!$B:$E,4,0),0) | Z173: =Y173-W173 | AA173: =_xlfn.IFNA(VLOOKUP($B173,'2026年1月16日'!$B:$E,4,0),0) | AB173: =AA173-W173 | AC173: =_xlfn.IFNA(VLOOKUP($B173,'2026年1月17日'!$B:$E,4,0),0) | AD173: =AC173-AA173 | AE173: =_xlfn.IFNA(VLOOKUP($B173,'2026年1月19日'!$B:$E,4,0),0) | AF173: =AE173-AC173 | AG173: =_xlfn.IFNA(VLOOKUP($B173,'2026年1月20日'!$B:$E,4,0),0) | AH173: =AG173-AE173 | AI173: =_xlfn.IFNA(VLOOKUP($B173,'2026年1月21日'!$B:$E,4,0),0) | AJ173: =AI173-AG173 | AK173: =_xlfn.IFNA(VLOOKUP($B173,'2026年1月22日'!$B:$E,4,0),0) | AL173: =AK173-AI173 | AM173: =_xlfn.IFNA(VLOOKUP($B173,'2026年1月23日'!$B:$E,4,0),0) | AN173: =AM173-AK173 | AO173: =_xlfn.IFNA(VLOOKUP($B173,'2026年1月24日'!$B:$E,4,0),0) | AP173: =AO173-AM173 | AQ173: =_xlfn.IFNA(VLOOKUP($B173,'2026年1月26日'!$B:$E,4,0),0) | AR173: =AQ173-AO173 | AS173: 30400 | AU173: 30400 | AV173: 0 | AW173: 30400 | AX173: 0 | AY173: 30400 | AZ173: 0 | BA173: 30400 | BB173: 0 | BE173: 34900 | BG173: 34000 | BH173: -900 | BI173: 34900 | BJ173: 900 | BK173: 30400 | BL173: -4500 | BM173: 31100 | BN173: 700 | BO173: 30900 | BP173: -200 | BQ173: 30900 | BR173: 0 | BS173: 31000 | BT173: 100 | BU173: 30400 | BV173: -600 | BW173: 30400 | BX173: 0
B174: B01525 | C174: 祺昌證券有限公司 | D174: =_xlfn.IFNA(VLOOKUP($B174,'2026年1月2日'!$B:$E,4,0),0) | E174: =_xlfn.IFNA(VLOOKUP($B174,'2026年1月2日'!$B:$E,4,0),0) | F174: =E174-D174 | G174: =_xlfn.IFNA(VLOOKUP($B174,'2026年1月5日'!$B:$E,4,0),0) | H174: =G174-E174 | I174: =_xlfn.IFNA(VLOOKUP($B174,'2026年1月6日'!$B:$E,4,0),0) | J174: =I174-G174 | K174: =_xlfn.IFNA(VLOOKUP($B174,'2026年1月7日'!$B:$E,4,0),0) | L174: =K174-I174 | M174: =_xlfn.IFNA(VLOOKUP($B174,'2026年1月8日'!$B:$E,4,0),0) | N174: =M174-K174 | O174: =_xlfn.IFNA(VLOOKUP($B174,'2026年1月9日'!$B:$E,4,0),0) | P174: =O174-M174 | Q174: =_xlfn.IFNA(VLOOKUP($B174,'2026年1月10日'!$B:$E,4,0),0) | R174: =Q174-O174 | S174: =_xlfn.IFNA(VLOOKUP($B174,'2026年1月12日'!$B:$E,4,0),0) | T174: =S174-Q174 | U174: =_xlfn.IFNA(VLOOKUP($B174,'2026年1月13日'!$B:$E,4,0),0) | V174: =U174-S174 | W174: =_xlfn.IFNA(VLOOKUP($B174,'2026年1月14日'!$B:$E,4,0),0) | X174: =W174-U174 | Y174: =_xlfn.IFNA(VLOOKUP($B174,'2026年1月15日'!$B:$E,4,0),0) | Z174: =Y174-W174 | AA174: =_xlfn.IFNA(VLOOKUP($B174,'2026年1月16日'!$B:$E,4,0),0) | AB174: =AA174-W174 | AC174: =_xlfn.IFNA(VLOOKUP($B174,'2026年1月17日'!$B:$E,4,0),0) | AD174: =AC174-AA174 | AE174: =_xlfn.IFNA(VLOOKUP($B174,'2026年1月19日'!$B:$E,4,0),0) | AF174: =AE174-AC174 | AG174: =_xlfn.IFNA(VLOOKUP($B174,'2026年1月20日'!$B:$E,4,0),0) | AH174: =AG174-AE174 | AI174: =_xlfn.IFNA(VLOOKUP($B174,'2026年1月21日'!$B:$E,4,0),0) | AJ174: =AI174-AG174 | AK174: =_xlfn.IFNA(VLOOKUP($B174,'2026年1月22日'!$B:$E,4,0),0) | AL174: =AK174-AI174 | AM174: =_xlfn.IFNA(VLOOKUP($B174,'2026年1月23日'!$B:$E,4,0),0) | AN174: =AM174-AK174 | AO174: =_xlfn.IFNA(VLOOKUP($B174,'2026年1月24日'!$B:$E,4,0),0) | AP174: =AO174-AM174 | AQ174: =_xlfn.IFNA(VLOOKUP($B174,'2026年1月26日'!$B:$E,4,0),0) | AR174: =AQ174-AO174 | AS174: 5300 | AU174: 5300 | AV174: 0 | AW174: 5300 | AX174: 0 | AY174: 5300 | AZ174: 0 | BA174: 5300 | BB174: 0 | BE174: 5300 | BG174: 5300 | BH174: 0 | BI174: 5300 | BJ174: 0 | BK174: 5300 | BL174: 0 | BM174: 15300 | BN174: 10000 | BO174: 5300 | BP174: -10000 | BQ174: 5300 | BR174: 0 | BS174: 5300 | BT174: 0 | BU174: 5300 | BV174: 0 | BW174: 5300 | BX174: 0
B175: B01209 | C175: 茂宸證券有限公司 | D175: =_xlfn.IFNA(VLOOKUP($B175,'2026年1月2日'!$B:$E,4,0),0) | E175: =_xlfn.IFNA(VLOOKUP($B175,'2026年1月2日'!$B:$E,4,0),0) | F175: =E175-D175 | G175: =_xlfn.IFNA(VLOOKUP($B175,'2026年1月5日'!$B:$E,4,0),0) | H175: =G175-E175 | I175: =_xlfn.IFNA(VLOOKUP($B175,'2026年1月6日'!$B:$E,4,0),0) | J175: =I175-G175 | K175: =_xlfn.IFNA(VLOOKUP($B175,'2026年1月7日'!$B:$E,4,0),0) | L175: =K175-I175 | M175: =_xlfn.IFNA(VLOOKUP($B175,'2026年1月8日'!$B:$E,4,0),0) | N175: =M175-K175 | O175: =_xlfn.IFNA(VLOOKUP($B175,'2026年1月9日'!$B:$E,4,0),0) | P175: =O175-M175 | Q175: =_xlfn.IFNA(VLOOKUP($B175,'2026年1月10日'!$B:$E,4,0),0) | R175: =Q175-O175 | S175: =_xlfn.IFNA(VLOOKUP($B175,'2026年1月12日'!$B:$E,4,0),0) | T175: =S175-Q175 | U175: =_xlfn.IFNA(VLOOKUP($B175,'2026年1月13日'!$B:$E,4,0),0) | V175: =U175-S175 | W175: =_xlfn.IFNA(VLOOKUP($B175,'2026年1月14日'!$B:$E,4,0),0) | X175: =W175-U175 | Y175: =_xlfn.IFNA(VLOOKUP($B175,'2026年1月15日'!$B:$E,4,0),0) | Z175: =Y175-W175 | AA175: =_xlfn.IFNA(VLOOKUP($B175,'2026年1月16日'!$B:$E,4,0),0) | AB175: =AA175-W175 | AC175: =_xlfn.IFNA(VLOOKUP($B175,'2026年1月17日'!$B:$E,4,0),0) | AD175: =AC175-AA175 | AE175: =_xlfn.IFNA(VLOOKUP($B175,'2026年1月19日'!$B:$E,4,0),0) | AF175: =AE175-AC175 | AG175: =_xlfn.IFNA(VLOOKUP($B175,'2026年1月20日'!$B:$E,4,0),0) | AH175: =AG175-AE175 | AI175: =_xlfn.IFNA(VLOOKUP($B175,'2026年1月21日'!$B:$E,4,0),0) | AJ175: =AI175-AG175 | AK175: =_xlfn.IFNA(VLOOKUP($B175,'2026年1月22日'!$B:$E,4,0),0) | AL175: =AK175-AI175 | AM175: =_xlfn.IFNA(VLOOKUP($B175,'2026年1月23日'!$B:$E,4,0),0) | AN175: =AM175-AK175 | AO175: =_xlfn.IFNA(VLOOKUP($B175,'2026年1月24日'!$B:$E,4,0),0) | AP175: =AO175-AM175 | AQ175: =_xlfn.IFNA(VLOOKUP($B175,'2026年1月26日'!$B:$E,4,0),0) | AR175: =AQ175-AO175 | AS175: 3700 | AU175: 3700 | AV175: 0 | AW175: 3700 | AX175: 0 | AY175: 3700 | AZ175: 0 | BA175: 3700 | BB175: 0 | BE175: 7700 | BG175: 5700 | BH175: -2000 | BI175: 7700 | BJ175: 2000 | BK175: 3700 | BL175: -4000 | BM175: 4700 | BN175: 1000 | BO175: 15700 | BP175: 11000 | BQ175: 15700 | BR175: 0 | BS175: 5700 | BT175: -10000 | BU175: 3700 | BV175: -2000 | BW175: 3700 | BX175: 0
B176: B01875 | C176: 國都證券(香港)有限公司 | D176: =_xlfn.IFNA(VLOOKUP($B176,'2026年1月2日'!$B:$E,4,0),0) | E176: =_xlfn.IFNA(VLOOKUP($B176,'2026年1月2日'!$B:$E,4,0),0) | F176: =E176-D176 | G176: =_xlfn.IFNA(VLOOKUP($B176,'2026年1月5日'!$B:$E,4,0),0) | H176: =G176-E176 | I176: =_xlfn.IFNA(VLOOKUP($B176,'2026年1月6日'!$B:$E,4,0),0) | J176: =I176-G176 | K176: =_xlfn.IFNA(VLOOKUP($B176,'2026年1月7日'!$B:$E,4,0),0) | L176: =K176-I176 | M176: =_xlfn.IFNA(VLOOKUP($B176,'2026年1月8日'!$B:$E,4,0),0) | N176: =M176-K176 | O176: =_xlfn.IFNA(VLOOKUP($B176,'2026年1月9日'!$B:$E,4,0),0) | P176: =O176-M176 | Q176: =_xlfn.IFNA(VLOOKUP($B176,'2026年1月10日'!$B:$E,4,0),0) | R176: =Q176-O176 | S176: =_xlfn.IFNA(VLOOKUP($B176,'2026年1月12日'!$B:$E,4,0),0) | T176: =S176-Q176 | U176: =_xlfn.IFNA(VLOOKUP($B176,'2026年1月13日'!$B:$E,4,0),0) | V176: =U176-S176 | W176: =_xlfn.IFNA(VLOOKUP($B176,'2026年1月14日'!$B:$E,4,0),0) | X176: =W176-U176 | Y176: =_xlfn.IFNA(VLOOKUP($B176,'2026年1月15日'!$B:$E,4,0),0) | Z176: =Y176-W176 | AA176: =_xlfn.IFNA(VLOOKUP($B176,'2026年1月16日'!$B:$E,4,0),0) | AB176: =AA176-W176 | AC176: =_xlfn.IFNA(VLOOKUP($B176,'2026年1月17日'!$B:$E,4,0),0) | AD176: =AC176-AA176 | AE176: =_xlfn.IFNA(VLOOKUP($B176,'2026年1月19日'!$B:$E,4,0),0) | AF176: =AE176-AC176 | AG176: =_xlfn.IFNA(VLOOKUP($B176,'2026年1月20日'!$B:$E,4,0),0) | AH176: =AG176-AE176 | AI176: =_xlfn.IFNA(VLOOKUP($B176,'2026年1月21日'!$B:$E,4,0),0) | AJ176: =AI176-AG176 | AK176: =_xlfn.IFNA(VLOOKUP($B176,'2026年1月22日'!$B:$E,4,0),0) | AL176: =AK176-AI176 | AM176: =_xlfn.IFNA(VLOOKUP($B176,'2026年1月23日'!$B:$E,4,0),0) | AN176: =AM176-AK176 | AO176: =_xlfn.IFNA(VLOOKUP($B176,'2026年1月24日'!$B:$E,4,0),0) | AP176: =AO176-AM176 | AQ176: =_xlfn.IFNA(VLOOKUP($B176,'2026年1月26日'!$B:$E,4,0),0) | AR176: =AQ176-AO176 | AS176: 16500 | AU176: 16500 | AV176: 0 | AW176: 16500 | AX176: 0 | AY176: 16500 | AZ176: 0 | BA176: 16500 | BB176: 0 | BE176: 15000 | BG176: 13000 | BH176: -2000 | BI176: 15000 | BJ176: 2000 | BK176: 16500 | BL176: 1500 | BM176: 14600 | BN176: -1900 | BO176: 12300 | BP176: -2300 | BQ176: 12300 | BR176: 0 | BS176: 12300 | BT176: 0 | BU176: 16500 | BV176: 4200 | BW176: 16500 | BX176: 0
B177: B01680 | C177: 實德證券有限公司 | D177: =_xlfn.IFNA(VLOOKUP($B177,'2026年1月2日'!$B:$E,4,0),0) | E177: =_xlfn.IFNA(VLOOKUP($B177,'2026年1月2日'!$B:$E,4,0),0) | F177: =E177-D177 | G177: =_xlfn.IFNA(VLOOKUP($B177,'2026年1月5日'!$B:$E,4,0),0) | H177: =G177-E177 | I177: =_xlfn.IFNA(VLOOKUP($B177,'2026年1月6日'!$B:$E,4,0),0) | J177: =I177-G177 | K177: =_xlfn.IFNA(VLOOKUP($B177,'2026年1月7日'!$B:$E,4,0),0) | L177: =K177-I177 | M177: =_xlfn.IFNA(VLOOKUP($B177,'2026年1月8日'!$B:$E,4,0),0) | N177: =M177-K177 | O177: =_xlfn.IFNA(VLOOKUP($B177,'2026年1月9日'!$B:$E,4,0),0) | P177: =O177-M177 | Q177: =_xlfn.IFNA(VLOOKUP($B177,'2026年1月10日'!$B:$E,4,0),0) | R177: =Q177-O177 | S177: =_xlfn.IFNA(VLOOKUP($B177,'2026年1月12日'!$B:$E,4,0),0) | T177: =S177-Q177 | U177: =_xlfn.IFNA(VLOOKUP($B177,'2026年1月13日'!$B:$E,4,0),0) | V177: =U177-S177 | W177: =_xlfn.IFNA(VLOOKUP($B177,'2026年1月14日'!$B:$E,4,0),0) | X177: =W177-U177 | Y177: =_xlfn.IFNA(VLOOKUP($B177,'2026年1月15日'!$B:$E,4,0),0) | Z177: =Y177-W177 | AA177: =_xlfn.IFNA(VLOOKUP($B177,'2026年1月16日'!$B:$E,4,0),0) | AB177: =AA177-W177 | AC177: =_xlfn.IFNA(VLOOKUP($B177,'2026年1月17日'!$B:$E,4,0),0) | AD177: =AC177-AA177 | AE177: =_xlfn.IFNA(VLOOKUP($B177,'2026年1月19日'!$B:$E,4,0),0) | AF177: =AE177-AC177 | AG177: =_xlfn.IFNA(VLOOKUP($B177,'2026年1月20日'!$B:$E,4,0),0) | AH177: =AG177-AE177 | AI177: =_xlfn.IFNA(VLOOKUP($B177,'2026年1月21日'!$B:$E,4,0),0) | AJ177: =AI177-AG177 | AK177: =_xlfn.IFNA(VLOOKUP($B177,'2026年1月22日'!$B:$E,4,0),0) | AL177: =AK177-AI177 | AM177: =_xlfn.IFNA(VLOOKUP($B177,'2026年1月23日'!$B:$E,4,0),0) | AN177: =AM177-AK177 | AO177: =_xlfn.IFNA(VLOOKUP($B177,'2026年1月24日'!$B:$E,4,0),0) | AP177: =AO177-AM177 | AQ177: =_xlfn.IFNA(VLOOKUP($B177,'2026年1月26日'!$B:$E,4,0),0) | AR177: =AQ177-AO177 | AS177: 1300 | AU177: 1300 | AV177: 0 | AW177: 1300 | AX177: 0 | AY177: 1300 | AZ177: 0 | BA177: 1300 | BB177: 0 | BE177: 1300 | BG177: 1300 | BH177: 0 | BI177: 1300 | BJ177: 0 | BK177: 1300 | BL177: 0 | BM177: 1300 | BN177: 0 | BO177: 1300 | BP177: 0 | BQ177: 1300 | BR177: 0 | BS177: 1300 | BT177: 0 | BU177: 1300 | BV177: 0 | BW177: 1300 | BX177: 0
B178: B02203 | C178: 意博資本亞洲有限公司 | D178: =_xlfn.IFNA(VLOOKUP($B178,'2026年1月2日'!$B:$E,4,0),0) | E178: =_xlfn.IFNA(VLOOKUP($B178,'2026年1月2日'!$B:$E,4,0),0) | F178: =E178-D178 | G178: =_xlfn.IFNA(VLOOKUP($B178,'2026年1月5日'!$B:$E,4,0),0) | H178: =G178-E178 | I178: =_xlfn.IFNA(VLOOKUP($B178,'2026年1月6日'!$B:$E,4,0),0) | J178: =I178-G178 | K178: =_xlfn.IFNA(VLOOKUP($B178,'2026年1月7日'!$B:$E,4,0),0) | L178: =K178-I178 | M178: =_xlfn.IFNA(VLOOKUP($B178,'2026年1月8日'!$B:$E,4,0),0) | N178: =M178-K178 | O178: =_xlfn.IFNA(VLOOKUP($B178,'2026年1月9日'!$B:$E,4,0),0) | P178: =O178-M178 | Q178: =_xlfn.IFNA(VLOOKUP($B178,'2026年1月10日'!$B:$E,4,0),0) | R178: =Q178-O178 | S178: =_xlfn.IFNA(VLOOKUP($B178,'2026年1月12日'!$B:$E,4,0),0) | T178: =S178-Q178 | U178: =_xlfn.IFNA(VLOOKUP($B178,'2026年1月13日'!$B:$E,4,0),0) | V178: =U178-S178 | W178: =_xlfn.IFNA(VLOOKUP($B178,'2026年1月14日'!$B:$E,4,0),0) | X178: =W178-U178 | Y178: =_xlfn.IFNA(VLOOKUP($B178,'2026年1月15日'!$B:$E,4,0),0) | Z178: =Y178-W178 | AA178: =_xlfn.IFNA(VLOOKUP($B178,'2026年1月16日'!$B:$E,4,0),0) | AB178: =AA178-W178 | AC178: =_xlfn.IFNA(VLOOKUP($B178,'2026年1月17日'!$B:$E,4,0),0) | AD178: =AC178-AA178 | AE178: =_xlfn.IFNA(VLOOKUP($B178,'2026年1月19日'!$B:$E,4,0),0) | AF178: =AE178-AC178 | AG178: =_xlfn.IFNA(VLOOKUP($B178,'2026年1月20日'!$B:$E,4,0),0) | AH178: =AG178-AE178 | AI178: =_xlfn.IFNA(VLOOKUP($B178,'2026年1月21日'!$B:$E,4,0),0) | AJ178: =AI178-AG178 | AK178: =_xlfn.IFNA(VLOOKUP($B178,'2026年1月22日'!$B:$E,4,0),0) | AL178: =AK178-AI178 | AM178: =_xlfn.IFNA(VLOOKUP($B178,'2026年1月23日'!$B:$E,4,0),0) | AN178: =AM178-AK178 | AO178: =_xlfn.IFNA(VLOOKUP($B178,'2026年1月24日'!$B:$E,4,0),0) | AP178: =AO178-AM178 | AQ178: =_xlfn.IFNA(VLOOKUP($B178,'2026年1月26日'!$B:$E,4,0),0) | AR178: =AQ178-AO178
